Workbook

Sheet DRY
B1: financial yr week | C1: 10 | D1: 11 | E1: 12 | F1: 13 | G1: 14 | H1: 15 | I1: 16 | J1: 17 | K1: 18 | L1: 19 | M1: 20 | N1: 21 | O1: 22 | P1: 23 | Q1: 24 | R1: 25 | S1: 26 | T1: 27 | U1: 28 | V1: 29 | W1: 30 | X1: 31 | Y1: 32 | Z1: 33 | AA1: 34 | AB1: 35 | AC1: 36 | AD1: 37 | AE1: 38 | AF1: 39 | AG1: 40
B2: w/c | C2: 45936 | D2: =C2+7 -> 45943 | E2: =D2+7 -> 45950 | F2: =E2+7 -> 45957 | G2: =F2+7 -> 45964 | H2: =G2+7 -> 45971 | I2: =H2+7 -> 45978 | J2: =I2+7 -> 45985 | K2: =J2+7 -> 45992 | ... AG2: =AF2+7 -> 46146 | AH2: L5W AVG
A3: BC | B3: net dry sales | C3: =SALES!FN20/1.2 -> 12735.583 | D3: =SALES!FO20/1.2 -> 11434.367 | E3: =SALES!FP20/1.2 -> 13073.792 | F3: =SALES!FQ20/1.2 -> 12396.833 | G3: =SALES!FR20/1.2 -> 10482.292 | H3: =SALES!FS20/1.2 -> 10709 | I3: =SALES!FT20/1.2 -> 10232.333 | J3: =SALES!FU20/1.2 -> 12212.958 | ... AG3: =SALES!GR20/1.2 -> 12796.5 | AH3: =SUM(AC3:AG3) -> 64959.408
B4: pw spend | C4: 3885 | D4: 3225 | E4: 4220.49 | F4: 3372 | G4: 3788 | H4: 3345 | I4: 3722 | J4: 4687 | K4: 4501 | L4: 4365 | M4: 4174 | N4: 4987 | O4: 6463 | P4: 3221 | Q4: 2811 | R4: 3349 | S4: 2750 | T4: 3121 | U4: 4082 | V4: 3190 | W4: 3360 | X4: 3771 | Y4: 4623 | Z4: 3910 | AA4: 3942 | AB4: 5943 | AC4: 4039 | AD4: 3971 | AE4: 3431 | AF4: 4301 | AG4: 3327.82
B5: recharge | C5: =16+16 -> 32 | D5: 48 | E5: 36 | F5: 389 | G5: 220 | H5: 318 | I5: =-311+152 -> -159 | J5: 262 | K5: 454 | L5: 302 | M5: 562 | N5: 152 | O5: 122 | P5: 343 | Q5: 324 | S5: 324 | T5: 166 | U5: 422 | V5: 362 | W5: 234 | X5: 275 | Y5: 166 | Z5: 174 | AA5: 82 | AB5: 225 | AC5: 32 | AD5: 215 | AE5: 40 | AF5: =AVERAGE(AA5:AE5) -> 118.8 | AG5: =AVERAGE(AB5:AF5) -> 126.16
B6: total spend | C6: =SUM(C4:C5) -> 3917 | D6: =SUM(D4:D5) -> 3273 | E6: =SUM(E4:E5) -> 4256.49 | F6: =SUM(F4:F5) -> 3761 | G6: =SUM(G4:G5) -> 4008 | H6: =SUM(H4:H5) -> 3663 | I6: =SUM(I4:I5) -> 3563 | J6: =SUM(J4:J5) -> 4949 | ... AG6: =SUM(AG4:AG5) -> 3453.98 | AH6: =SUM(AC6:AG6) -> 19601.78
B7: GP% | C7: =(C3-C6)/C3 -> 0.69243655 | D7: =(D3-D6)/D3 -> 0.71375765 | E7: =(E3-E6)/E3 -> 0.67442574 | F7: =(F3-F6)/F3 -> 0.69661607 | G7: =(G3-G6)/G3 -> 0.61764086 | H7: =(H3-H6)/H3 -> 0.65795126 | I7: =(I3-I6)/I3 -> 0.65179008 | J7: =(J3-J6)/J3 -> 0.59477468 | ... AH7: =(AH3-AH6)/AH3 -> 0.69824571
A8: DG | B8: net dry sales | C8: =SALES!FN27/1.2 -> 10154.375 | D8: =SALES!FO27/1.2 -> 9317.5 | E8: =SALES!FP27/1.2 -> 11552.083 | F8: =SALES!FQ27/1.2 -> 10242.583 | G8: =SALES!FR27/1.2 -> 9972.125 | H8: =SALES!FS27/1.2 -> 10168.958 | I8: =SALES!FT27/1.2 -> 8561.875 | J8: =SALES!FU27/1.2 -> 9803.3333 | ... AG8: =SALES!GR27/1.2 -> 13072.708 | AH8: =SUM(AC8:AG8) -> 63088.367
B9: pw spend | C9: 2079 | D9: 2542 | E9: 2112.37 | F9: 2294 | G9: 2105 | H9: 3291 | I9: 2558 | J9: 3449 | K9: 2878 | L9: 3259 | M9: 3097 | N9: 1588 | O9: 2542 | R9: 2563 | S9: 2403 | T9: 2151 | U9: 2593 | V9: 2707 | W9: 2228 | X9: 2928 | Y9: 3232 | Z9: 2881 | AA9: 3446 | AB9: 3678 | AC9: 3382 | AD9: 3374 | AE9: 2916 | AF9: 3797 | AG9: 2190.13
B10: recharge | C10: =90+45+60+120+105 -> 420 | D10: 630 | E10: 750 | F10: 450 | G10: 480 | H10: 585 | I10: 495 | J10: 465 | K10: 435 | L10: 435 | M10: 735 | N10: 100 | O10: 340 | S10: 435 | T10: 330 | U10: 115 | V10: 490 | W10: 270 | X10: 555 | Y10: 510 | Z10: 571 | AA10: 753 | AB10: 525 | AC10: 479 | AD10: 497 | AE10: 652 | AF10: =AVERAGE(AA10:AE10) -> 581.2 | AG10: =AVERAGE(AB10:AF10) -> 546.84
B11: total spend | C11: =SUM(C9:C10) -> 2499 | D11: =SUM(D9:D10) -> 3172 | E11: =SUM(E9:E10) -> 2862.37 | F11: =SUM(F9:F10) -> 2744 | G11: =SUM(G9:G10) -> 2585 | H11: =SUM(H9:H10) -> 3876 | I11: =SUM(I9:I10) -> 3053 | J11: =SUM(J9:J10) -> 3914 | ... AG11: =SUM(AG9:AG10) -> 2736.97 | AH11: =SUM(AC11:AG11) -> 18415.17
B12: GP% | C12: =(C8-C11)/C8 -> 0.75389918 | D12: =(D8-D11)/D8 -> 0.65956533 | E12: =(E8-E11)/E8 -> 0.75222045 | F12: =(F8-F11)/F8 -> 0.73209884 | G12: =(G8-G11)/G8 -> 0.74077742 | H12: =(H8-H11)/H8 -> 0.61884002 | I12: =(I8-I11)/I8 -> 0.64341923 | J12: =(J8-J11)/J8 -> 0.60074804 | ... AH12: =(AH8-AH11)/AH8 -> 0.70810514
A13: FDL | B13: net dry sales | C13: =SALES!FN69/1.2 -> 9458.5417 | D13: =SALES!FO69/1.2 -> 9685.4167 | E13: =SALES!FP69/1.2 -> 8407.0833 | F13: =SALES!FQ69/1.2 -> 11074.375 | G13: =SALES!FR69/1.2 -> 10078.958 | H13: =SALES!FS69/1.2 -> 10452.083 | I13: =SALES!FT69/1.2 -> 10590.833 | J13: =SALES!FU69/1.2 -> 10012.5 | ... AG13: =SALES!GR69/1.2 -> 9113.3333 | AH13: =SUM(AC13:AG13) -> 52302.875
B14: pw spend | C14: 3025 | D14: 2619 | E14: 2530.38 | F14: 3403 | G14: 2564 | H14: 3034 | I14: 2818 | J14: 3339 | K14: 2711 | L14: 3226 | M14: 4236 | N14: 1983 | O14: 4257 | P14: 2354 | Q14: 2747 | R14: 2035 | S14: 3196 | T14: 2099 | U14: 2721 | V14: 2669 | W14: 2859 | X14: 2990 | Y14: 3713 | Z14: 2905 | AA14: 3041 | AB14: 4068 | AC14: 3678 | AD14: 3865 | AE14: 2920 | AF14: 2923 | AG14: 3024.82
B15: recharge | C15: =32+64+48+80 -> 224 | D15: 136 | E15: 262 | F15: 290 | G15: 288 | H15: 394 | I15: 224 | J15: 394 | K15: 462 | L15: 424 | M15: 428 | N15: 204 | O15: 610 | P15: 188 | Q15: 386 | S15: 486 | T15: 346 | U15: 370 | V15: 338 | W15: 244 | X15: 411 | Y15: 380 | Z15: 275 | AA15: 352 | AB15: 420 | AC15: 301 | AD15: 257 | AE15: 224 | AF15: =AVERAGE(AA15:AE15) -> 310.8 | AG15: =AVERAGE(AB15:AF15) -> 302.56
B16: total spend | C16: =SUM(C14:C15) -> 3249 | D16: =SUM(D14:D15) -> 2755 | E16: =SUM(E14:E15) -> 2792.38 | F16: =SUM(F14:F15) -> 3693 | G16: =SUM(G14:G15) -> 2852 | H16: =SUM(H14:H15) -> 3428 | I16: =SUM(I14:I15) -> 3042 | J16: =SUM(J14:J15) -> 3733 | ... AG16: =SUM(AG14:AG15) -> 3327.38 | AH16: =SUM(AC16:AG16) -> 17806.18
B17: GP% | C17: =(C13-C16)/C13 -> 0.65650096 | D17: =(D13-D16)/D13 -> 0.71555173 | E17: =(E13-E16)/E13 -> 0.66785389 | F17: =(F13-F16)/F13 -> 0.66652746 | G17: =(G13-G16)/G13 -> 0.71703425 | H17: =(H13-H16)/H13 -> 0.67202711 | I17: =(I13-I16)/I13 -> 0.71277048 | J17: =(J13-J16)/J13 -> 0.62716604 | ... AH17: =(AH13-AH16)/AH13 -> 0.65955638
A18: GA | B18: net dry sales | C18: =SALES!FN13/1.2 -> 11857.667 | D18: =SALES!FO13/1.2 -> 10873.083 | E18: =SALES!FP13/1.2 -> 13976.583 | F18: =SALES!FQ13/1.2 -> 13080.25 | G18: =SALES!FR13/1.2 -> 9203.5833 | H18: =SALES!FS13/1.2 -> 13843.25 | I18: =SALES!FT13/1.2 -> 14615.542 | J18: =SALES!FU13/1.2 -> 12556.5 | ... AG18: =SALES!GR13/1.2 -> 11658.892 | AH18: =SUM(AC18:AG18) -> 67069.975
B19: pw spend | C19: 3258 | D19: 3053 | E19: 3653.26 | F19: 4332 | G19: 3062 | H19: 3539 | I19: 4612 | J19: 3097 | K19: 4242 | L19: 3822 | M19: 4539 | N19: 2840 | O19: 5119 | P19: 3332 | Q19: 2933 | R19: 3043 | S19: 4484 | T19: 3580 | U19: 4018 | V19: 3993 | W19: 2917 | X19: 3167 | Y19: 3795 | Z19: 4325 | AA19: 3393 | AB19: 4234 | AC19: 5519 | AD19: 3851 | AE19: 3747 | AF19: 4624 | AG19: 3788.91
B20: recharge | C20: =16+150+90+30 -> 286 | D20: 140 | E20: 237 | F20: 364 | G20: 422 | H20: 280 | I20: 301 | J20: 343 | K20: 391 | L20: 380 | M20: 375 | N20: 210 | O20: 386 | P20: 363 | Q20: 410 | S20: 220 | T20: 588 | U20: 451 | V20: 459 | W20: 346 | X20: 474 | Y20: 391 | Z20: 374 | AA20: 324 | AB20: 585 | AC20: 304 | AD20: 375 | AE20: 387 | AF20: =AVERAGE(AA20:AE20) -> 395 | AG20: =AVERAGE(AB20:AF20) -> 409.2
B21: total spend | C21: =SUM(C19:C20) -> 3544 | D21: =SUM(D19:D20) -> 3193 | E21: =SUM(E19:E20) -> 3890.26 | F21: =SUM(F19:F20) -> 4696 | G21: =SUM(G19:G20) -> 3484 | H21: =SUM(H19:H20) -> 3819 | I21: =SUM(I19:I20) -> 4913 | J21: =SUM(J19:J20) -> 3440 | ... AG21: =SUM(AG19:AG20) -> 4198.11 | AH21: =SUM(AC21:AG21) -> 23400.11
B22: GP% | C22: =(C18-C21)/C18 -> 0.70112164 | D22: =(D18-D21)/D18 -> 0.70633905 | E22: =(E18-E21)/E18 -> 0.72165873 | F22: =(F18-F21)/F18 -> 0.64098546 | G22: =(G18-G21)/G18 -> 0.62145179 | H22: =(H18-H21)/H18 -> 0.72412548 | I22: =(I18-I21)/I18 -> 0.66385098 | J22: =(J18-J21)/J18 -> 0.72603831 | ... AH22: =(AH18-AH21)/AH18 -> 0.65110901
A23: KA | B23: net dry sales | C23: =SALES!FN55/1.2 -> 9934.7917 | D23: =SALES!FO55/1.2 -> 8826.875 | E23: =SALES!FP55/1.2 -> 10918.333 | F23: =SALES!FQ55/1.2 -> 9834.1667 | G23: =SALES!FR55/1.2 -> 9243.125 | H23: =SALES!FS55/1.2 -> 9442.7083 | I23: =SALES!FT55/1.2 -> 10297.5 | J23: =SALES!FU55/1.2 -> 13481.042 | ... AG23: =SALES!GR55/1.2 -> 9727.2917 | AH23: =SUM(AC23:AG23) -> 49902.917
B24: pw spend | C24: 2777 | D24: 2401 | E24: 1967 | F24: 2438 | G24: 1837 | H24: 1849 | I24: 2536 | J24: 2987 | K24: 3026 | L24: 3873 | M24: 4365 | N24: 1809 | O24: 4422 | P24: 1533 | Q24: 2694 | R24: 2282 | S24: 2603 | T24: 2939 | U24: 3043 | V24: 2707 | W24: 2330 | X24: 2722 | Y24: 2662 | Z24: 3204 | AA24: 2035 | AB24: 3476 | AC24: 2637 | AD24: 2403 | AE24: 2479 | AF24: 2574 | AG24: 2301.69
B25: recharge | C25: =90+30+30 -> 150 | D25: 120 | E25: 240 | F25: 270 | G25: 180 | H25: 330 | I25: 270 | J25: 440 | K25: 492 | L25: 327 | M25: 404 | N25: 118 | O25: 380 | P25: 256 | Q25: 381 | S25: 287 | T25: 387 | U25: 467 | V25: 399 | W25: 410 | X25: 380 | Y25: 301 | Z25: 351 | AA25: 271 | AB25: 375 | AC25: 300 | AD25: 367 | AE25: 266 | AF25: =AVERAGE(AA25:AE25) -> 315.8 | AG25: =AVERAGE(AB25:AF25) -> 324.76
B26: total spend | C26: =SUM(C24:C25) -> 2927 | D26: =SUM(D24:D25) -> 2521 | E26: =SUM(E24:E25) -> 2207 | F26: =SUM(F24:F25) -> 2708 | G26: =SUM(G24:G25) -> 2017 | H26: =SUM(H24:H25) -> 2179 | I26: =SUM(I24:I25) -> 2806 | J26: =SUM(J24:J25) -> 3427 | ... AG26: =SUM(AG24:AG25) -> 2626.45 | AH26: =SUM(AC26:AG26) -> 13968.25
B27: GP% | C27: =(C23-C26)/C23 -> 0.70537882 | D27: =(D23-D26)/D23 -> 0.71439496 | E27: =(E23-E26)/E23 -> 0.79786292 | F27: =(F23-F26)/F23 -> 0.72463351 | G27: =(G23-G26)/G23 -> 0.78178376 | H27: =(H23-H26)/H23 -> 0.76923993 | I27: =(I23-I26)/I23 -> 0.72750668 | J27: =(J23-J26)/J23 -> 0.74579116 | ... AH27: =(AH23-AH26)/AH23 -> 0.72009151
A28: MHI | B28: net dry sales | C28: =SALES!FN62/1.2 -> 11222.708 | D28: =SALES!FO62/1.2 -> 10948.758 | E28: =SALES!FP62/1.2 -> 11033.292 | F28: =SALES!FQ62/1.2 -> 11866.458 | G28: =SALES!FR62/1.2 -> 12339.583 | H28: =SALES!FS62/1.2 -> 12138.042 | I28: =SALES!FT62/1.2 -> 11304.167 | J28: =SALES!FU62/1.2 -> 11731.458 | ... AG28: =SALES!GR62/1.2 -> 13362.042 | AH28: =SUM(AC28:AG28) -> 68360.225
B29: pw spend | C29: 3423 | D29: 3351 | E29: 3012.66 | F29: 2762 | G29: 4419 | H29: 3034 | I29: 3965 | J29: 3266 | K29: 3893 | L29: 4174 | M29: 3660 | N29: 3131 | O29: 6869 | P29: 3111 | Q29: 3630 | R29: 2801 | S29: 3609 | T29: 3356 | U29: 3612 | V29: 4172 | W29: 3214 | X29: 3415 | Y29: 5875 | Z29: 4485 | AA29: 3602 | AB29: 5963 | AC29: 3141 | AD29: 4130 | AE29: 3878 | AF29: 4525 | AG29: 3099.86
B30: recharge | C30: =8+60 -> 68 | D30: 168 | E30: 171 | F30: 578 | G30: 405 | H30: 403 | I30: 276 | J30: 473 | K30: 182 | L30: 468 | M30: 588 | N30: 106 | O30: 665 | P30: 256 | Q30: 385 | S30: 314 | T30: 400 | U30: 445 | V30: 404 | W30: 419 | X30: 457 | Y30: 440 | Z30: 530 | AA30: 281 | AB30: 235 | AC30: 393 | AD30: 390 | AE30: 404 | AF30: =AVERAGE(AA30:AE30) -> 340.6 | AG30: =AVERAGE(AB30:AF30) -> 352.52
B31: total spend | C31: =SUM(C29:C30) -> 3491 | D31: =SUM(D29:D30) -> 3519 | E31: =SUM(E29:E30) -> 3183.66 | F31: =SUM(F29:F30) -> 3340 | G31: =SUM(G29:G30) -> 4824 | H31: =SUM(H29:H30) -> 3437 | I31: =SUM(I29:I30) -> 4241 | J31: =SUM(J29:J30) -> 3739 | ... AG31: =SUM(AG29:AG30) -> 3452.38 | AH31: =SUM(AC31:AG31) -> 20653.98
B32: GP% | C32: =(C28-C31)/C28 -> 0.68893427 | D32: =(D28-D31)/D28 -> 0.67859369 | E32: =(E28-E31)/E28 -> 0.71144967 | F32: =(F28-F31)/F28 -> 0.71853438 | G32: =(G28-G31)/G28 -> 0.60906297 | H32: =(H28-H31)/H28 -> 0.71684065 | I32: =(I28-I31)/I28 -> 0.6248286 | J32: =(J28-J31)/J28 -> 0.6812843 | ... AH32: =(AH28-AH31)/AH28 -> 0.69786554
A33: PA | B33: net dry sales | C33: =SALES!FN6/1.2 -> 23502.333 | D33: =SALES!FO6/1.2 -> 26071.625 | E33: =SALES!FP6/1.2 -> 28507.433 | F33: =SALES!FQ6/1.2 -> 25382.333 | G33: =SALES!FR6/1.2 -> 25477.542 | H33: =SALES!FS6/1.2 -> 24621.375 | I33: =SALES!FT6/1.2 -> 25282.833 | J33: =SALES!FU6/1.2 -> 24108.958 | ... AG33: =SALES!GR6/1.2 -> 30914.85 | AH33: =SUM(AC33:AG33) -> 148627.22
B34: pw spend | C34: 7813 | D34: 10390 | E34: 9800.45 | F34: 9133 | G34: 9016 | H34: 7954 | I34: 7783 | J34: 9396 | K34: =10510+K59 -> 12410 | L34: 8265 | M34: 15010 | N34: =10167-1500 -> 8667 | O34: 9023 | P34: 5747 | Q34: 7648 | R34: 6677 | S34: 8274 | T34: 8044 | U34: 7104 | V34: 8962 | W34: 8848 | X34: 7974 | Y34: 10842 | Z34: 10563 | AA34: 8694 | AB34: 13849 | AC34: 8354 | AD34: 7583 | AE34: 8606 | AF34: 13274 | AG34: 8125.33
B35: recharge | C35: =-SUM(C50,C45,C40,C30,C25,C20,C15,C10,C5)*0.5 -> -1380 | D35: =-SUM(D50,D45,D40,D30,D25,D20,D15,D10,D5)*0.5 -> -1148.5 | E35: =-SUM(E50,E45,E40,E30,E25,E20,E15,E10,E5)*0.5 -> -1449.5 | F35: =-SUM(F50,F45,F40,F30,F25,F20,F15,F10,F5)*0.5 -> -1993.5 | G35: =-SUM(G50,G45,G40,G30,G25,G20,G15,G10,G5)*0.5 -> -1338.5 | H35: =-SUM(H50,H45,H40,H30,H25,H20,H15,H10,H5)*0.5 -> -1281 | I35: =-SUM(I50,I45,I40,I30,I25,I20,I15,I10,I5)*0.5 -> -509 | J35: =-SUM(J50,J45,J40,J30,J25,J20,J15,J10,J5)*0.5 -> -1957 | ... Q35: =-SUM(Q50,Q45,Q40,Q30,Q25,Q20,Q15,Q10,Q5)*0.5 -> -1355 | R35: =Q35 -> -1355 | S35: =-SUM(S50,S45,S40,S30,S25,S20,S15,S10,S5)*0.5 -> -1549 | T35: =-SUM(T50,T45,T40,T30,T25,T20,T15,T10,T5)*0.5 -> -1480.5 | U35: =-SUM(U50,U45,U40,U30,U25,U20,U15,U10,U5)*0.5 -> -1615 | V35: =-SUM(V50,V45,V40,V30,V25,V20,V15,V10,V5)*0.5 -> -2059.5 | W35: =-SUM(W50,W45,W40,W30,W25,W20,W15,W10,W5)*0.5 -> -1653 | X35: =-SUM(X50,X45,X40,X30,X25,X20,X15,X10,X5)*0.5 -> -1876.5 | Y35: =-SUM(Y50,Y45,Y40,Y30,Y25,Y20,Y15,Y10,Y5)*0.5 -> -1474 | Z35: =-SUM(Z50,Z45,Z40,Z30,Z25,Z20,Z15,Z10,Z5)*0.5 -> -1914 | ... AG35: =-SUM(AG50,AG45,AG40,AG30,AG25,AG20,AG15,AG10,AG5)*0.5 -> -1932.245
B36: total spend | C36: =(C34+C35) -> 6433 | D36: =(D34+D35) -> 9241.5 | E36: =(E34+E35) -> 8350.95 | F36: =(F34+F35) -> 7139.5 | G36: =(G34+G35) -> 7677.5 | H36: =(H34+H35) -> 6673 | I36: =(I34+I35) -> 7274 | J36: =(J34+J35) -> 7439 | ... AG36: =(AG34+AG35) -> 6193.085 | AH36: =SUM(AC36:AG36) -> 36698.36
B37: GP% | C37: =(C33-C36)/C33 -> 0.7262825 | D37: =(D33-D36)/D33 -> 0.64553418 | E37: =(E33-E36)/E33 -> 0.70706061 | F37: =(F33-F36)/F33 -> 0.71872168 | G37: =(G33-G36)/G33 -> 0.69865617 | H37: =(H33-H36)/H33 -> 0.72897533 | I37: =(I33-I36)/I33 -> 0.7122949 | J37: =(J33-J36)/J33 -> 0.6914425 | ... AH37: =(AH33-AH36)/AH33 -> 0.75308452
A38: QH | B38: net dry sales | C38: =SALES!FN34/1.2 -> 6696.3333 | D38: =SALES!FO34/1.2 -> 4263.0417 | E38: =SALES!FP34/1.2 -> 9129.875 | F38: =SALES!FQ34/1.2 -> 7016.875 | G38: =SALES!FR34/1.2 -> 6159 | H38: =SALES!FS34/1.2 -> 8100.5 | I38: =SALES!FT34/1.2 -> 7283.5 | J38: =SALES!FU34/1.2 -> 7325.5 | ... Z38: =SALES!GK34/1.2 -> 0 | AB38: =SALES!GM34/1.2 -> 10916.25 | AC38: =SALES!GN34/1.2 -> 9396.0417 | AD38: =SALES!GO34/1.2 -> 8743.625 | AE38: =SALES!GP34/1.2 -> 9692.2917 | AF38: =SALES!GQ34/1.2 -> 11524.725 | AG38: =SALES!GR34/1.2 -> 10673.542 | AH38: =SUM(AC38:AG38) -> 50030.225
B39: pw spend | C39: 2091 | D39: 1169 | E39: 2010.87 | F39: =275+1835 -> 2110 | G39: 1675 | H39: 1300 | I39: =250+2723 -> 2973 | J39: 2416 | K39: 1930 | L39: 1949 | M39: 2185 | N39: 1662 | O39: 3346 | AB39: 4098 | AC39: 2350 | AD39: 2350 | AE39: 2835 | AF39: 3365 | AG39: 2596.21
B40: recharge | C40: =15+60+45+0+30+30+150 -> 330 | D40: 236 | E40: 275 | F40: 496 | G40: 254 | H40: 138 | I40: 140 | J40: 578 | K40: 494 | L40: =292+470 -> 762 | M40: 184 | N40: 64 | O40: 330 | AB40: 314 | AC40: 239 | AD40: 267 | AE40: 181 | AF40: =AVERAGE(AA40:AE40) -> 250.25 | AG40: =AVERAGE(AB40:AF40) -> 250.25
B41: total spend | C41: =SUM(C39:C40) -> 2421 | D41: =SUM(D39:D40) -> 1405 | E41: =SUM(E39:E40) -> 2285.87 | F41: =SUM(F39:F40) -> 2606 | G41: =SUM(G39:G40) -> 1929 | H41: =SUM(H39:H40) -> 1438 | I41: =SUM(I39:I40) -> 3113 | J41: =SUM(J39:J40) -> 2994 | ... Z41: =SUM(Z39:Z40) -> 0 | AB41: =SUM(AB39:AB40) -> 4412 | AC41: =SUM(AC39:AC40) -> 2589 | AD41: =SUM(AD39:AD40) -> 2617 | AE41: =SUM(AE39:AE40) -> 3016 | AF41: =SUM(AF39:AF40) -> 3615.25 | AG41: =SUM(AG39:AG40) -> 2846.46 | AH41: =SUM(AC41:AG41) -> 14683.71
B42: GP% | C42: =(C38-C41)/C38 -> 0.63845886 | D42: =(D38-D41)/D38 -> 0.67042311 | E42: =(E38-E41)/E38 -> 0.74962746 | F42: =(F38-F41)/F38 -> 0.6286096 | G42: =(G38-G41)/G38 -> 0.68679981 | H42: =(H38-H41)/H38 -> 0.82248009 | I42: =(I38-I41)/I38 -> 0.57259559 | J42: =(J38-J41)/J38 -> 0.5912907 | ... AH42: =(AH38-AH41)/AH38 -> 0.70650322
A43: SP | B43: net dry sales | C43: =SALES!FN41/1.2 -> 8804.6667 | D43: =SALES!FO41/1.2 -> 7847.5417 | E43: =SALES!FP41/1.2 -> 9167.25 | F43: =SALES!FQ41/1.2 -> 9283.375 | G43: =SALES!FR41/1.2 -> 8930.3333 | H43: =SALES!FS41/1.2 -> 8193.1667 | I43: =SALES!FT41/1.2 -> 8877.8333 | J43: =SALES!FU41/1.2 -> 9178.7917 | ... AG43: =SALES!GR41/1.2 -> 11838.15 | AH43: =SUM(AC43:AG43) -> 56916.492
B44: pw spend | C44: 2776 | D44: 2213 | E44: 2413.12 | F44: =3431-924 -> 2507 | G44: 3460 | I44: =92+3615 -> 3707 | K44: =3804-K59 -> 1904 | L44: 6150 | M44: 4914 | N44: 2269 | O44: 6639 | P44: 4439 | Q44: 2700 | R44: 3109 | S44: 2960 | T44: 2242 | U44: 3002 | V44: 2949 | W44: 2787 | X44: 2739 | Y44: 4720 | Z44: 2669 | AA44: 3239 | AB44: 3769 | AC44: 3374 | AD44: 2197 | AE44: 3027 | AF44: 3272 | AG44: 2554.1
B45: recharge | C45: =30+8+60+12+60+8 -> 178 | D45: 163 | E45: 152 | F45: 110 | G45: -484 | H45: 114 | I45: -1513 | K45: 72 | L45: =-2461+318 -> -2143 | M45: =-2370+178 -> -2192 | N45: 152 | O45: 490 | P45: -2101 | V45: 347 | W45: 343 | X45: 289 | Y45: -200 | Z45: 273 | AA45: 331 | AB45: =1544-724 -> 820 | AC45: 327 | AD45: 296 | AE45: 212 | AF45: =AVERAGE(AA45:AE45) -> 397.2 | AG45: =AVERAGE(AB45:AF45) -> 410.44
B46: total spend | C46: =SUM(C44:C45) -> 2954 | D46: =SUM(D44:D45) -> 2376 | E46: =SUM(E44:E45) -> 2565.12 | F46: =SUM(F44:F45) -> 2617 | G46: =SUM(G44:G45) -> 2976 | H46: =SUM(H44:H45) -> 114 | I46: =SUM(I44:I45) -> 2194 | J46: =SUM(J44:J45) -> 0 | ... AG46: =SUM(AG44:AG45) -> 2964.54 | AH46: =SUM(AC46:AG46) -> 16066.74
B47: GP% | C47: =(C43-C46)/C43 -> 0.6644961 | D47: =(D43-D46)/D43 -> 0.69723002 | E47: =(E43-E46)/E43 -> 0.72018653 | F47: =(F43-F46)/F43 -> 0.71809821 | G47: =(G43-G46)/G43 -> 0.66675376 | H47: =(H43-H46)/H43 -> 0.98608597 | I47: =(I43-I46)/I43 -> 0.75286763 | J47: =(J43-J46)/J43 -> 1 | ... AH47: =(AH43-AH46)/AH43 -> 0.7177138
A48: Nole | B48: net dry sales | C48: =SALES!FN48/1.2 -> 12184.625 | D48: =SALES!FO48/1.2 -> 9487.2917 | E48: =SALES!FP48/1.2 -> 7596.0417 | F48: =SALES!FQ48/1.2 -> 10391.375 | G48: =SALES!FR48/1.2 -> 10449.217 | H48: =SALES!FS48/1.2 -> 10020.833 | I48: =SALES!FT48/1.2 -> 10779.225 | J48: =SALES!FU48/1.2 -> 11398.917 | ... AG48: =SALES!GR48/1.2 -> 14398.208 | AH48: =SUM(AC48:AG48) -> 72821.825
B49: pw spend | C49: 2101 | D49: 1572 | E49: 1320.48 | F49: 1999 | G49: 2157 | I49: 2563 | J49: 2318 | K49: 2129 | L49: 3322 | M49: 3648 | N49: 1608 | O49: 2820 | P49: 2000 | Q49: 1832 | R49: 2012 | S49: 1746 | T49: 1746 | U49: 1692 | V49: 2147 | W49: 2338 | X49: 2006 | Y49: 2258 | Z49: 3117 | AA49: 2281 | AB49: 2600 | AC49: 2115 | AD49: 1833 | AE49: 2338 | AF49: 3693 | AG49: 2870.9
B50: recharge | C50: =112+88+112+280+320+160 -> 1072 | D50: 656 | E50: 776 | F50: 1040 | G50: 912 | I50: 984 | J50: 959 | K50: 880 | L50: 1280 | M50: 1560 | N50: 752 | O50: 500 | P50: 912 | Q50: 824 | S50: 1032 | T50: 744 | U50: 960 | V50: 1320 | W50: 1040 | X50: 912 | Y50: 960 | Z50: 1280 | AA50: 992 | AB50: 1200 | AC50: 1240 | AD50: 1032 | AE50: 1120 | AF50: =AVERAGE(AA50:AE50) -> 1116.8 | AG50: =AVERAGE(AB50:AF50) -> 1141.76
B51: total spend | C51: =SUM(C49:C50) -> 3173 | D51: =SUM(D49:D50) -> 2228 | E51: =SUM(E49:E50) -> 2096.48 | F51: =SUM(F49:F50) -> 3039 | G51: =SUM(G49:G50) -> 3069 | H51: =SUM(H49:H50) -> 0 | I51: =SUM(I49:I50) -> 3547 | J51: =SUM(J49:J50) -> 3277 | ... AG51: =SUM(AG49:AG50) -> 4012.66 | AH51: =SUM(AC51:AG51) -> 18500.46
B52: GP% | C52: =(C48-C51)/C48 -> 0.73958985 | D52: =(D48-D51)/D48 -> 0.76515953 | E52: =(E48-E51)/E48 -> 0.72400362 | F52: =(F48-F51)/F48 -> 0.70754592 | G52: =(G48-G51)/G48 -> 0.70629377 | H52: =(H48-H51)/H48 -> 1 | I52: =(I48-I51)/I48 -> 0.67094109 | J52: =(J48-J51)/J48 -> 0.71251654 | ... AH52: =(AH48-AH51)/AH48 -> 0.74594897
A53: TOTAL | B53: net dry sales | C53: =C3+C8+C13+C18+C23+C28+C33+C38+C43+C48 -> 116551.63 | D53: =D3+D8+D13+D18+D23+D28+D33+D38+D43+D48 -> 108755.5 | E53: =E3+E8+E13+E18+E23+E28+E33+E38+E43+E48 -> 123361.77 | F53: =F3+F8+F13+F18+F23+F28+F33+F38+F43+F48 -> 120568.62 | G53: =G3+G8+G13+G18+G23+G28+G33+G38+G43+G48 -> 112335.76 | H53: =H3+H8+H13+H18+H23+H28+H33+H38+H43+H48 -> 117689.92 | I53: =I3+I8+I13+I18+I23+I28+I33+I38+I43+I48 -> 117825.64 | J53: =J3+J8+J13+J18+J23+J28+J33+J38+J43+J48 -> 121809.96 | ... S53: =S3+S8+S13+S18+S23+S28+S33+S38+S43+S48 -> 113153.5 | T53: =T3+T8+T13+T18+T23+U28+T33+T38+T43+T48 -> 106445.23 | U53: =U3+U8+U13+U18+U23+V28+U33+U38+U43+U48 -> 115074.57 | V53: =V3+V8+V13+V18+V23+W28+V33+V38+V43+V48 -> 121950.23 | W53: =W3+W8+W13+W18+W23+X28+W33+W38+W43+W48 -> 106851.11 | X53: =X3+X8+X13+X18+X23+Y28+X33+X38+X43+X48 -> 116937.15 | Y53: =Y3+Y8+Y13+Y18+Y23+Z28+Y33+Y38+Y43+Y48 -> 134886.93 | Z53: =Z3+Z8+Z13+Z18+Z23+Z28+Z33+Z38+Z43+Z48 -> 120277.07 | AA53: =AA3+AA8+AA13+AA18+AA23+AA28+AA33+AA38+AA43+AA48 -> 115572.23 | AB53: =AB3+AB8+AB13+AB18+AB23+AB28+AB33+AB38+AB43+AB48 -> 159206.08 | AC53: =AC3+AC8+AC13+AC18+AC23+AC28+AC33+AC38+AC43+AC48 -> 150617.46 | AD53: =AD3+AD8+AD13+AD18+AD23+AD28+AD33+AD38+AD43+AD48 -> 130705.22 | AE53: =AE3+AE8+AE13+AE18+AE23+AE28+AE33+AE38+AE43+AE48 -> 131011.07 | AF53: =AF3+AF8+AF13+AF18+AF23+AF28+AF33+AF38+AF43+AF48 -> 144190.26 | AG53: =AG3+AG8+AG13+AG18+AG23+AG28+AG33+AG38+AG43+AG48 -> 137555.52 | AH53: =SUM(AC53:AG53) -> 694079.53
B54: pw spend | C54: =C4+C9+C14+C19+C24+C29+C34+C39+C44+C49 -> 33228 | D54: =D4+D9+D14+D19+D24+D29+D34+D39+D44+D49 -> 32535 | E54: =E4+E9+E14+E19+E24+E29+E34+E39+E44+E49 -> 33041.08 | F54: =F4+F9+F14+F19+F24+F29+F34+F39+F44+F49 -> 34350 | G54: =G4+G9+G14+G19+G24+G29+G34+G39+G44+G49 -> 34083 | H54: =H4+H9+H14+H19+H24+H29+H34+H39+H44+H49 -> 27346 | I54: =I4+I9+I14+I19+I24+I29+I34+I39+I44+I49 -> 37237 | J54: =J4+J9+J14+J19+J24+J29+J34+J39+J44+J49 -> 34955 | ... AG54: =AG4+AG9+AG14+AG19+AG24+AG29+AG34+AG39+AG44+AG49 -> 33879.77
B55: recharge | C55: =C5+C10+C15+C20+C25+C30+C35+C40+C45+C50 -> 1380 | D55: =D5+D10+D15+D20+D25+D30+D35+D40+D45+D50 -> 1148.5 | E55: =E5+E10+E15+E20+E25+E30+E35+E40+E45+E50 -> 1449.5 | F55: =F5+F10+F15+F20+F25+F30+F35+F40+F45+F50 -> 1993.5 | G55: =G5+G10+G15+G20+G25+G30+G35+G40+G45+G50 -> 1338.5 | H55: =H5+H10+H15+H20+H25+H30+H35+H40+H45+H50 -> 1281 | I55: =I5+I10+I15+I20+I25+I30+I35+I40+I45+I50 -> 509 | J55: =J5+J10+J15+J20+J25+J30+J35+J40+J45+J50 -> 1957 | ... AG55: =AG5+AG10+AG15+AG20+AG25+AG30+AG35+AG40+AG45+AG50 -> 1932.245
B56: total spend | C56: =C54+C55 -> 34608 | D56: =D54+D55 -> 33683.5 | E56: =E54+E55 -> 34490.58 | F56: =F54+F55 -> 36343.5 | G56: =G54+G55 -> 35421.5 | H56: =H54+H55 -> 28627 | I56: =I54+I55 -> 37746 | J56: =J54+J55 -> 36912 | ... AG56: =AG54+AG55 -> 35812.015 | AH56: =SUM(AC56:AG56) -> 199794.74
B57: GP% | C57: =(C53-C56)/C53 -> 0.7030672 | D57: =(D53-D56)/D53 -> 0.69028233 | E57: =(E53-E56)/E53 -> 0.72041111 | F57: =(F53-F56)/F53 -> 0.69856586 | G57: =(G53-G56)/G53 -> 0.68468188 | H57: =(H53-H56)/H53 -> 0.75675911 | I57: =(I53-I56)/I53 -> 0.67964528 | J57: =(J53-J56)/J53 -> 0.69697059 | ... AH57: =(AH53-AH56)/AH53 -> 0.71214431
B59: SP PA adjustment | K59: 1900

Sheet LABOUR
B1: finanial yr week | C1: 10 | D1: 11 | E1: 12 | F1: 13 | G1: 14 | H1: 15 | I1: 16 | J1: 17 | K1: 18 | L1: 19 | M1: 20 | N1: 21 | O1: 22 | P1: 23 | Q1: 24 | R1: 25 | S1: 26 | T1: 27 | U1: 28 | V1: 29 | W1: 30 | X1: 31 | Y1: 32 | Z1: 33 | AA1: 34 | AB1: 35 | AC1: 36 | AD1: 37 | AE1: 38 | AF1: 39 | AG1: 40
B2: w/c | C2: 45936 | D2: =C2+7 -> 45943 | E2: =D2+7 -> 45950 | F2: =E2+7 -> 45957 | G2: =F2+7 -> 45964 | H2: =G2+7 -> 45971 | I2: =H2+7 -> 45978 | J2: =I2+7 -> 45985 | K2: =J2+7 -> 45992 | ... AG2: =AF2+7 -> 46146
A3: BC | B3: gross F&B sales | C3: =SALES!FN21 -> 25015.15 | D3: =SALES!FO21 -> 21827.99 | E3: =SALES!FP21 -> 25174.4 | F3: =SALES!FQ21 -> 24150.15 | G3: =SALES!FR21 -> 21663.4 | H3: =SALES!FS21 -> 20883.75 | I3: =SALES!FT21 -> 20595.6 | J3: =SALES!FU21 -> 24183.95 | ... AG3: =SALES!GR21 -> 25483.8
B4: vouchers redeemed
B5: gross accom sales | C5: 3608 | D5: 4737 | E5: 4445.48 | F5: 2648 | G5: 4002.23 | H5: 3888 | I5: 4684 | J5: 4366 | K5: 2951.91 | L5: 3671.7 | M5: 4387.85 | N5: 3238.3 | O5: 4390.23 | P5: 3974.42 | Q5: 2662.21 | R5: 2092.5 | S5: 1849.4 | T5: 2242 | U5: 4540.5 | V5: 4262 | W5: 2830 | X5: 3183.69 | Y5: 3229 | Z5: 4480 | AA5: 3083.1 | AB5: 4411 | AC5: 3802.44 | AD5: 3684.6 | AE5: 4942 | AF5: 4929.59 | AG5: 4738
B6: net revenue | C6: =(C3+C5)/1.2 -> 23852.625 | D6: =(D3+D5)/1.2 -> 22137.492 | E6: =(E3+E5)/1.2 -> 24683.233 | F6: =(F3+F5)/1.2 -> 22331.792 | G6: =(G3+G5)/1.2 -> 21388.025 | H6: =(H3+H5)/1.2 -> 20643.125 | I6: =(I3+I5)/1.2 -> 21066.333 | J6: =(J3+J5)/1.2 -> 23791.625 | ... AG6: =(AG3+AG5)/1.2 -> 25184.833
B7: hours | C7: 533 | D7: 536 | E7: =48+473+22.5 -> 543.5 | F7: =484+48+(48-35) -> 545 | G7: 545 | H7: 511 | I7: 544 | J7: 565 | K7: 607 | L7: 568 | M7: 669 | N7: =534+20 -> 554 | O7: 680 | P7: 511 | Q7: 554 | R7: 522 | S7: 514 | T7: 558 | U7: 545.84 | V7: 593 | W7: 526 | X7: 566 | Y7: 604 | Z7: 527 | AA7: 500 | AB7: 556
B8: cost £ (inc hol) | C8: =C7*12.21*1.1*1.1207 -> 8022.7809 | D8: =D7*12.21*1.1*1.1207 -> 8067.9372 | E8: =E7*12.21*1.1*1.1207 -> 8180.8281 | F8: =F7*12.21*1.1*1.1207 -> 8203.4063 | G8: =G7*12.21*1.1*1.1207 -> 8203.4063 | H8: =H7*12.21*1.1*1.1207 -> 7691.6342 | I8: =I7*12.21*1.1*1.1207 -> 8188.3542 | J8: =J7*12.21*1.1*1.1207 -> 8504.4488 | ... AA8: =AA7*12.21*1.1*1.1207 -> 7526.0609 | AB8: =AB7*12.71*1.1*1.1207 -> 8711.6897 | AC8: 7288 | AD8: 8055 | AE8: 7900 | AF8: 7926 | AG8: 8385.59
B9: Labour% | C9: =C8/C6 -> 0.33634792 | D9: =D8/D6 -> 0.36444677 | E9: =E8/E6 -> 0.3314326 | F9: =F8/F6 -> 0.36734206 | G9: =G8/G6 -> 0.38355137 | H9: =H8/H6 -> 0.37260028 | I9: =I8/I6 -> 0.38869385 | J9: =J8/J6 -> 0.35745557 | ... AG9: =AG8/AG6 -> 0.3329619
A10: DG | B10: gross F&B sales | C10: =SALES!FN28 -> 18020.5 | D10: =SALES!FO28 -> 16918.35 | E10: =SALES!FP28 -> 19321.65 | F10: =SALES!FQ28 -> 17919.85 | G10: =SALES!FR28 -> 17917.85 | H10: =SALES!FS28 -> 18204.8 | I10: =SALES!FT28 -> 15335.6 | J10: =SALES!FU28 -> 17816.1 | ... AG10: =SALES!GR28 -> 22746.6
B11: gross accom sales | C11: 2615 | D11: 3978 | E11: 3369.4 | F11: 2661 | G11: 3782.7 | H11: 3051 | I11: 2004 | J11: 3429 | K11: 3097.6 | L11: 1458.58 | M11: 2053.7 | N11: 803 | O11: 2064.5 | R11: 791 | S11: 1700.2 | T11: 2377 | U11: 3419.12 | V11: 4019 | W11: 3043 | X11: 3048.5 | Y11: 3420 | Z11: 4034.73 | AA11: 4545.8 | AB11: 4235 | AC11: 3614.52 | AD11: 4884.8 | AE11: 3996.9 | AF11: 4443.6 | AG11: 4142
B12: net revenue | C12: =(C10+C11)/1.2 -> 17196.25 | D12: =(D10+D11)/1.2 -> 17413.625 | E12: =(E10+E11)/1.2 -> 18909.208 | F12: =(F10+F11)/1.2 -> 17150.708 | G12: =(G10+G11)/1.2 -> 18083.792 | H12: =(H10+H11)/1.2 -> 17713.167 | I12: =(I10+I11)/1.2 -> 14449.667 | J12: =(J10+J11)/1.2 -> 17704.25 | ... AG12: =(AG10+AG11)/1.2 -> 22407.167
B13: hours | C13: 424 | D13: 449 | E13: 449 | F13: =24+414 -> 438 | G13: 446 | H13: 471 | I13: 453 | J13: 460 | K13: 469 | L13: 470 | M13: 468 | N13: 347 | O13: 552 | R13: 417 | S13: 482 | T13: 459.45 | U13: 448 | V13: 430 | W13: 459 | X13: 480 | Y13: 498 | Z13: 490 | AA13: 488 | AB13: 486
B14: cost £ (inc hol) | C14: =C13*12.21*1.1*1.1207 -> 6382.0996 | D14: =D13*12.21*1.1*1.1207 -> 6758.4026 | E14: =E13*12.21*1.1*1.1207 -> 6758.4026 | F14: =F13*12.21*1.1*1.1207 -> 6592.8293 | G14: =G13*12.21*1.1*1.1207 -> 6713.2463 | H14: =H13*12.21*1.1*1.1207 -> 7089.5493 | I14: =I13*12.21*1.1*1.1207 -> 6818.6111 | J14: =J13*12.21*1.1*1.1207 -> 6923.976 | ... AA14: =AA13*12.21*1.1*1.1207 -> 7345.4354 | AB14: =AB13*12.71*1.1*1.1207 -> 7614.8943 | AC14: 7295 | AD14: 8504 | AE14: 7823 | AF14: 7828 | AG14: 7665
B15: Labour% | C15: =C14/C12 -> 0.37113322 | D15: =D14/D12 -> 0.38811004 | E15: =E14/E12 -> 0.3574133 | F15: =F14/F12 -> 0.38440566 | G15: =G14/G12 -> 0.37123002 | H15: =H14/H12 -> 0.40024178 | I15: =I14/I12 -> 0.47188709 | J15: =J14/J12 -> 0.39109118 | ... O15: =O14/O12 -> 0.40913616 | R15: =R14/R12 -> 0.62205939 | S15: =S14/S12 -> 0.38283335 | T15: =T14/T12 -> 0.42021767 | U15: =U14/U12 -> 0.43909478 | V15: =V14/V12 -> 0.34358962 | W15: =W14/W12 -> 0.36186191 | X15: =X14/X12 -> 0.35722396 | Y15: =Y14/Y12 -> 0.36913166 | ... AG15: =AG14/AG12 -> 0.34207806
A16: FDL | B16: gross F&B sales | C16: =SALES!FN70 -> 20137.35 | D16: =SALES!FO70 -> 20774.05 | E16: =SALES!FP70 -> 19290.1 | F16: =SALES!FQ70 -> 22776.75 | G16: =SALES!FR70 -> 20291.65 | H16: =SALES!FS70 -> 20489.85 | I16: =SALES!FT70 -> 20089.3 | J16: =SALES!FU70 -> 20412 | ... AG16: =SALES!GR70 -> 17616.25
B17: gross accom sales | C17: 1887 | D17: 2663 | E17: 2799.1 | F17: 4060 | G17: 5172 | H17: 4084 | I17: 3986 | J17: 3792 | K17: 4294.91 | L17: 5326 | M17: 4617 | N17: 2015 | O17: 7078.66 | P17: 1670.7 | Q17: 2709 | R17: 1959.6 | S17: 2647.9 | T17: 1716.5 | U17: 5064.02 | V17: 3785 | W17: 3807 | X17: 4004.68 | Y17: 3903 | Z17: 5217.47 | AA17: 4438.48 | AB17: 5242 | AC17: 4082.69 | AD17: 5747.73 | AE17: 5757.35 | AF17: 7314.07 | AG17: 5056
B18: net revenue | C18: =(C16+C17)/1.2 -> 18353.625 | D18: =(D16+D17)/1.2 -> 19530.875 | E18: =(E16+E17)/1.2 -> 18407.667 | F18: =(F16+F17)/1.2 -> 22363.958 | G18: =(G16+G17)/1.2 -> 21219.708 | H18: =(H16+H17)/1.2 -> 20478.208 | I18: =(I16+I17)/1.2 -> 20062.75 | J18: =(J16+J17)/1.2 -> 20170 | ... AG18: =(AG16+AG17)/1.2 -> 18893.542
B19: hours | C19: 566 | D19: 512 | E19: 530 | F19: 486 | G19: 527 | H19: 525 | I19: 531 | J19: 563 | K19: 498 | L19: 548 | M19: 547 | N19: =389+24 -> 413 | O19: 682 | P19: 490 | Q19: 558 | R19: 532 | S19: 537 | T19: 491.94 | U19: 538 | V19: 536 | W19: 528 | X19: 504 | Y19: 549 | Z19: 552 | AA19: 554 | AB19: 528
B20: cost £ (inc hol) | C20: =C19*12.21*1.1*1.1207 -> 8519.5009 | D20: =D19*12.21*1.1*1.1207 -> 7706.6863 | E20: =E19*12.21*1.1*1.1207 -> 7977.6245 | F20: =F19*12.21*1.1*1.1207 -> 7315.3311 | G20: =G19*12.21*1.1*1.1207 -> 7932.4681 | H20: =H19*12.21*1.1*1.1207 -> 7902.3639 | I20: =I19*12.21*1.1*1.1207 -> 7992.6766 | J20: =J19*12.21*1.1*1.1207 -> 8474.3445 | ... AA20: =AA19*12.21*1.1*1.1207 -> 8338.8754 | AB20: =AB19*12.71*1.1*1.1207 -> 8272.9715 | AC20: 9208 | AD20: 7970 | AE20: 8413 | AF20: 8150 | AG20: 7005
B21: Labour% | C21: =C20/C18 -> 0.46418628 | D21: =D20/D18 -> 0.39458992 | E21: =E20/E18 -> 0.43338597 | F21: =F20/F18 -> 0.32710359 | G21: =G20/G18 -> 0.3738255 | H21: =H20/H18 -> 0.38589137 | I21: =I20/I18 -> 0.3983839 | J21: =J20/J18 -> 0.42014598 | ... AG21: =AG20/AG18 -> 0.37076161
A22: GA | B22: gross F&B sales | C22: =SALES!FN14 -> 23854.9 | D22: =SALES!FO14 -> 22257.95 | E22: =SALES!FP14 -> 27587.26 | F22: =SALES!FQ14 -> 25736.3 | G22: =SALES!FR14 -> 19459.4 | H22: =SALES!FS14 -> 26891.05 | I22: =SALES!FT14 -> 29234.3 | J22: =SALES!FU14 -> 24741.7 | ... AG22: =SALES!GR14 -> 23850.45
B23: gross accom sales | C23: 6669 | D23: 6867 | E23: 7175.5 | F23: 6981 | G23: 5172.7 | H23: 6377 | I23: 5299 | J23: 7085 | K23: 5203.56 | L23: 3588.38 | M23: 5155.08 | N23: 3988.2 | O23: 6270.9 | P23: 3283.4 | Q23: 4704.2 | R23: 4183.37 | S23: 4658.54 | T23: 3407 | U23: 6215.3 | V23: 4766 | W23: 2698 | X23: 4428.7 | Y23: 4394 | Z23: 5401.08 | AA23: 5006.7 | AB23: 7630 | AC23: 6750.6 | AD23: 6858.86 | AE23: 7267.9 | AF23: 7208.2 | AG23: 6003
B24: net revenue | C24: =(C22+C23)/1.2 -> 25436.583 | D24: =(D22+D23)/1.2 -> 24270.792 | E24: =(E22+E23)/1.2 -> 28968.967 | F24: =(F22+F23)/1.2 -> 27264.417 | G24: =(G22+G23)/1.2 -> 20526.75 | H24: =(H22+H23)/1.2 -> 27723.375 | I24: =(I22+I23)/1.2 -> 28777.75 | J24: =(J22+J23)/1.2 -> 26522.25 | ... AG24: =(AG22+AG23)/1.2 -> 24877.875
B25: hours | C25: 643 | D25: 635 | E25: 663 | F25: 634 | G25: 583 | H25: 610 | I25: 704 | J25: 688 | K25: 678 | L25: 632 | M25: 651 | N25: =528+12 -> 540 | O25: 859 | P25: 571 | Q25: 614 | R25: 549 | S25: 635 | T25: 635 | U25: 660.5 | V25: 619 | W25: 587 | X25: 639 | Y25: 641 | Z25: 627 | AA25: 626
B26: cost £ (inc hol) | C26: =C25*12.21*1.1*1.1207 -> 9678.5143 | D26: =D25*12.21*1.1*1.1207 -> 9558.0973 | E26: =E25*12.21*1.1*1.1207 -> 9979.5567 | F26: =F25*12.21*1.1*1.1207 -> 9543.0452 | G26: =G25*12.21*1.1*1.1207 -> 8775.387 | H26: =H25*12.21*1.1*1.1207 -> 9181.7942 | I26: =I25*12.21*1.1*1.1207 -> 10596.694 | J26: =J25*12.21*1.1*1.1207 -> 10355.86 | ... AA26: =AA25*12.21*1.1*1.1207 -> 9422.6282 | AB26: 10485 | AC26: 11707 | AD26: 9607 | AE26: 8669 | AF26: 9758 | AG26: 9991
B27: Labour% | C27: =C26/C24 -> 0.38049584 | D27: =D26/D24 -> 0.39381069 | E27: =E26/E24 -> 0.34449129 | F27: =F26/F24 -> 0.35001831 | G27: =G26/G24 -> 0.42750981 | H27: =H26/H24 -> 0.33119323 | I27: =I26/I24 -> 0.36822523 | J27: =J26/J24 -> 0.39045932 | ... AG27: =AG26/AG24 -> 0.40160182
A28: KA | B28: gross F&B sales | C28: =SALES!FN56 -> 23516.8 | D28: =SALES!FO56 -> 20162.55 | E28: =SALES!FP56 -> 24161.15 | F28: =SALES!FQ56 -> 22013.9 | G28: =SALES!FR56 -> 21116.7 | H28: =SALES!FS56 -> 21328.15 | I28: =SALES!FT56 -> 23655.1 | J28: =SALES!FU56 -> 29517.65 | ... AG28: =SALES!GR56 -> 22048.2
B29: net revenue | C29: =C28/1.2 -> 19597.333 | D29: =D28/1.2 -> 16802.125 | E29: =E28/1.2 -> 20134.292 | F29: =F28/1.2 -> 18344.917 | G29: =G28/1.2 -> 17597.25 | H29: =H28/1.2 -> 17773.458 | I29: =I28/1.2 -> 19712.583 | J29: =J28/1.2 -> 24598.042 | ... AG29: =AG28/1.2 -> 18373.5
B30: hours | C30: 441 | D30: 437 | E30: 449 | F30: 397 | G30: 437 | H30: 432 | I30: 449 | J30: 500 | K30: 478 | L30: 512 | M30: 577 | N30: =520+15 -> 535 | O30: 711 | P30: 408 | Q30: 424 | R30: 441 | S30: 428 | T30: 421 | U30: 434 | V30: 503 | W30: 476 | X30: 439 | Y30: 485 | Z30: 498 | AA30: 454
B31: cost £ (inc hol) | C31: =C30*12.21*1.1*1.1207 -> 6637.9857 | D31: =D30*12.21*1.1*1.1207 -> 6577.7772 | E31: =E30*12.21*1.1*1.1207 -> 6758.4026 | F31: =F30*12.21*1.1*1.1207 -> 5975.6923 | G31: =G30*12.21*1.1*1.1207 -> 6577.7772 | H31: =H30*12.21*1.1*1.1207 -> 6502.5166 | I31: =I30*12.21*1.1*1.1207 -> 6758.4026 | J31: =J30*12.21*1.1*1.1207 -> 7526.0609 | ... AA31: =AA30*12.21*1.1*1.1207 -> 6833.6633 | AB31: 6934 | AC31: 6557 | AD31: 7300 | AE31: 6195 | AF31: 7492 | AG31: 7094
B32: Labour% | C32: =C31/C29 -> 0.33871882 | D32: =D31/D29 -> 0.39148484 | E32: =E31/E29 -> 0.33566627 | F32: =F31/F29 -> 0.32574104 | G32: =G31/G29 -> 0.37379575 | H32: =H31/H29 -> 0.36585545 | I32: =I31/I29 -> 0.34284713 | J32: =J31/J29 -> 0.30596179 | ... AG32: =AG31/AG29 -> 0.38609955
A33: MHI | B33: gross F&B sales | C33: =SALES!FN63 -> 21140.05 | D33: =SALES!FO63 -> 20659.06 | E33: =SALES!FP63 -> 21464.9 | F33: =SALES!FQ63 -> 24200.4 | G33: =SALES!FR63 -> 24134.55 | H33: =SALES!FS63 -> 22955.3 | I33: =SALES!FT63 -> 22439.3 | J33: =SALES!FU63 -> 21525.05 | ... AG33: =SALES!GR63 -> 26985.65
B34: gross accom sales | C34: 5434 | D34: 6314 | E34: 8183.5 | F34: 6454 | G34: 5366 | H34: 7270 | I34: 4180 | J34: 5917 | K34: 7269.54 | L34: 5384.72 | M34: 6341.97 | N34: 4149.35 | O34: 8804.05 | P34: 4889.1 | Q34: 5032.2 | R34: 4524.49 | S34: 4911.2 | T34: 6713 | U34: 6539.89 | V34: 7888 | W34: 6997 | X34: 5297.07 | Y34: 7217 | Z34: 5704.9 | AA34: 6589.78 | AB34: 8938 | AC34: 7518.36 | AD34: 7708.73 | AE34: 7193.72 | AF34: 7661.67 | AG34: 10758
B35: net revenue | C35: =(C33+C34)/1.2 -> 22145.042 | D35: =(D33+D34)/1.2 -> 22477.55 | E35: =(E33+E34)/1.2 -> 24707 | F35: =(F33+F34)/1.2 -> 25545.333 | G35: =(G33+G34)/1.2 -> 24583.792 | H35: =(H33+H34)/1.2 -> 25187.75 | I35: =(I33+I34)/1.2 -> 22182.75 | J35: =(J33+J34)/1.2 -> 22868.375 | ... AG35: =(AG33+AG34)/1.2 -> 31453.042
B36: hours | C36: 635 | D36: 561 | E36: 593 | F36: =529+48-15 -> 562 | G36: 596 | H36: 591 | I36: 584 | J36: 589 | K36: 584 | L36: 588 | M36: 628 | N36: =576+8 -> 584 | O36: 814 | P36: 536 | Q36: 553 | R36: 533 | S36: 622 | T36: 603 | U36: 599 | V36: 610 | W36: 532 | X36: 546 | Y36: 596 | Z36: =533+48 -> 581 | AA36: 592 | AB36: 614
B37: cost £ (inc hol) | C37: =C36*12.21*1.1*1.1207 -> 9558.0973 | D37: =D36*12.21*1.1*1.1207 -> 8444.2403 | E37: =E36*12.21*1.1*1.1207 -> 8925.9082 | F37: =F36*12.21*1.1*1.1207 -> 8459.2924 | G37: =G36*12.21*1.1*1.1207 -> 8971.0645 | H37: =H36*12.21*1.1*1.1207 -> 8895.8039 | I37: =I36*12.21*1.1*1.1207 -> 8790.4391 | J37: =J36*12.21*1.1*1.1207 -> 8865.6997 | ... AA37: =AA36*12.21*1.1*1.1207 -> 8910.856 | AB37: =AB36*12.71*1.1*1.1207 -> 9620.4631 | AC37: 9759 | AD37: 10120 | AE37: 9751 | AF37: 9779 | AG37: 10319
B38: Labour% | C38: =C37/C35 -> 0.43161342 | D38: =D37/D35 -> 0.37567441 | E38: =E37/E35 -> 0.36127042 | F38: =F37/F35 -> 0.33114825 | G38: =G37/G35 -> 0.36491786 | H38: =H37/H35 -> 0.35317978 | I38: =I37/I35 -> 0.39627364 | J38: =J37/J35 -> 0.38768385 | ... AG38: =AG37/AG35 -> 0.32807638
A39: PA | B39: gross F&B sales | C39: =SALES!FN7 -> 43635.85 | D39: =SALES!FO7 -> 46567.31 | E39: =SALES!FP7 -> 53650.33 | F39: =SALES!FQ7 -> 48442.24 | G39: =SALES!FR7 -> 45560.44 | H39: =SALES!FS7 -> 44220.02 | I39: =SALES!FT7 -> 45139.46 | J39: =SALES!FU7 -> 42845.74 | ... AG39: =SALES!GR7 -> 55601.8
B40: gross accom sales | C40: 6034 | D40: 7120 | E40: 8082.1 | F40: 6324 | G40: 5025.3 | H40: 5362 | I40: 5715 | J40: 6227 | K40: 6185.5 | L40: 5386.45 | M40: 7704.35 | N40: 3303.63 | O40: 6251.45 | P40: 7618.23 | Q40: 5515 | R40: 1444.97 | S40: 5511.26 | T40: 4401 | U40: 4157.3 | V40: 6887 | W40: 4735 | X40: 5213.23 | Y40: 4222 | Z40: 6729.2 | AA40: 6868.16 | AB40: 6086 | AC40: 6040.43 | AD40: 4828.1 | AE40: 6390.7 | AF40: 9290.56 | AG40: 7347
B41: net revenue | C41: =(C39+C40)/1.2 -> 41391.542 | D41: =(D39+D40)/1.2 -> 44739.425 | E41: =(E39+E40)/1.2 -> 51443.692 | F41: =(F39+F40)/1.2 -> 45638.533 | G41: =(G39+G40)/1.2 -> 42154.783 | H41: =(H39+H40)/1.2 -> 41318.35 | I41: =(I39+I40)/1.2 -> 42378.717 | J41: =(J39+J40)/1.2 -> 40893.95 | ... AG41: =(AG39+AG40)/1.2 -> 52457.333
B42: hours | C42: 1213 | D42: 1208 | E42: 1306 | F42: 1172 | G42: 1204 | H42: 1166 | I42: 1080 | J42: 1196 | K42: 1238 | L42: 1261 | M42: 1344 | N42: 1017 | O42: 1426 | P42: 1128 | Q42: 1156 | R42: 1051 | S42: 1142 | T42: 1118 | U42: 1124 | V42: 1136 | W42: 1160 | X42: 1098 | Y42: 1290 | Z42: 1194 | AA42: 1174 | AB42: 1347
B43: cost £ (inc hol) | C43: =(C42*12.21*1.1*1.1207)+DRY!C35 -> 16878.224 | D43: =(D42*12.21*1.1*1.1207)+DRY!D35 -> 17034.463 | E43: =(E42*12.21*1.1*1.1207)+DRY!E35 -> 18208.571 | F43: =(F42*12.21*1.1*1.1207)+DRY!F35 -> 15647.587 | G43: =(G42*12.21*1.1*1.1207)+DRY!G35 -> 16784.255 | H43: =(H42*12.21*1.1*1.1207)+DRY!H35 -> 16269.774 | I43: =(I42*12.21*1.1*1.1207)+DRY!I35 -> 15747.291 | J43: =(J42*12.21*1.1*1.1207)+DRY!J35 -> 16045.338 | ... AB43: =(AB42*12.21*1.1*1.1207)+DRY!AB35 -> 17925.708 | AC43: =20331+DRY!AC35 -> 18523.5 | AD43: =18681+DRY!AD35 -> 16833 | AE43: =19021+DRY!AE35 -> 17278 | AF43: =19976+DRY!AF35 -> 18062.775 | AG43: =19835+DRY!AG35 -> 17902.755
B44: Labour% | C44: =C43/C41 -> 0.40776987 | D44: =D43/D41 -> 0.38074837 | E44: =E43/E41 -> 0.35395148 | F44: =F43/F41 -> 0.3428591 | G44: =G43/G41 -> 0.39815777 | H44: =H43/H41 -> 0.3937663 | I44: =I43/I41 -> 0.37158491 | J44: =J43/J41 -> 0.39236458 | ... AG44: =AG43/AG41 -> 0.34128222
A45: QH | B45: gross F&B sales | C45: =SALES!FN35 -> 17373.85 | D45: =SALES!FO35 -> 9700.1 | E45: =SALES!FP35 -> 18866.95 | F45: =SALES!FQ35 -> 14709.45 | G45: =SALES!FR35 -> 14216.35 | H45: =SALES!FS35 -> 17207 | I45: =SALES!FT35 -> 16055.8 | J45: =SALES!FU35 -> 16218.2 | ... T45: =SALES!GE35 -> 0 | AA45: =SALES!GL35 -> 12438.91 | AB45: =SALES!GM35 -> 25180.85 | AC45: =SALES!GN35 -> 21403.95 | AD45: =SALES!GO35 -> 18853.45 | AE45: =SALES!GP35 -> 21852.65 | AF45: =SALES!GQ35 -> 24884.37 | AG45: =SALES!GR35 -> 22788.35
B46: gross accom sales | C46: 2189 | D46: 1789 | E46: 2781.13 | F46: 2425 | G46: 2058.4 | H46: 1725 | I46: 1982 | J46: 1499 | K46: 2448.8 | L46: 3183.5 | M46: 3152.2 | N46: 554.3 | O46: 1948.3 | AA46: 919.7 | AB46: 1524 | AC46: 3172.3 | AD46: 1840.83 | AE46: 4268.95 | AF46: 4739.18 | AG46: 5081
B47: net revenue | C47: =(C45+C46)/1.2 -> 16302.375 | D47: =(D45+D46)/1.2 -> 9574.25 | E47: =(E45+E46)/1.2 -> 18040.067 | F47: =(F45+F46)/1.2 -> 14278.708 | G47: =(G45+G46)/1.2 -> 13562.292 | H47: =(H45+H46)/1.2 -> 15776.667 | I47: =(I45+I46)/1.2 -> 15031.5 | J47: =(J45+J46)/1.2 -> 14764.333 | ... T47: =(T45+T46)/1.2 -> 0 | AA47: =(AA45+AA46)/1.2 -> 11132.175 | AB47: =(AB45+AB46)/1.2 -> 22254.042 | AC47: =(AC45+AC46)/1.2 -> 20480.208 | AD47: =(AD45+AD46)/1.2 -> 17245.233 | AE47: =(AE45+AE46)/1.2 -> 21768 | AF47: =(AF45+AF46)/1.2 -> 24686.292 | AG47: =(AG45+AG46)/1.2 -> 23224.458
B48: hours | C48: 416 | D48: 450 | E48: 464 | F48: 412 | G48: 405 | H48: 403 | I48: 438 | J48: 470 | K48: 429 | L48: 445 | M48: 445 | N48: 385 | O48: 533 | AA48: 521 | AB48: 546
B49: cost £ (inc hol) | C49: =C48*12.21*1.1*1.1207 -> 6261.6826 | D49: =D48*12.21*1.1*1.1207 -> 6773.4548 | E49: =E48*12.21*1.1*1.1207 -> 6984.1845 | F49: =F48*12.21*1.1*1.1207 -> 6201.4741 | G49: =G48*12.21*1.1*1.1207 -> 6096.1093 | H49: =H48*12.21*1.1*1.1207 -> 6066.005 | I49: =I48*12.21*1.1*1.1207 -> 6592.8293 | J49: =J48*12.21*1.1*1.1207 -> 7074.4972 | ... T49: =T48*12.21*1.1*1.1207 -> 0 | AA49: =AA48*12.21*1.1*1.1207 -> 7842.1554 | AB49: =AB48*12.71*1.1*1.1207 -> 8555.0047 | AC49: 7869 | AD49: 7194 | AE49: 7195 | AF49: 7622 | AG49: 7925
B50: Labour% | C50: =C49/C47 -> 0.38409634 | D50: =D49/D47 -> 0.70746583 | E50: =E49/E47 -> 0.38714848 | F50: =F49/F47 -> 0.43431619 | G50: =G49/G47 -> 0.44948962 | H50: =H49/H47 -> 0.38449219 | I50: =I49/I47 -> 0.43860089 | J50: =J49/J47 -> 0.4791613 | ... O50: =O49/O47 -> 0.32845508 | AB50: =AB49/AB47 -> 0.38442476 | AC50: =AC49/AC47 -> 0.38422461 | AD50: =AD49/AD47 -> 0.41715875 | AE50: =AE49/AE47 -> 0.33053105 | AF50: =AF49/AF47 -> 0.30875435 | AG50: =AG49/AG47 -> 0.34123508
A51: SP | B51: gross F&B sales | C51: =SALES!FN42 -> 18887.75 | D51: =SALES!FO42 -> 18523.7 | E51: =SALES!FP42 -> 19740.55 | F51: =SALES!FQ42 -> 18988.75 | G51: =SALES!FR42 -> 19084.45 | H51: =SALES!FS42 -> 17304.45 | I51: =SALES!FT42 -> 18865.45 | J51: =SALES!FU42 -> 19276.1 | ... AG51: =SALES!GR42 -> 22959.45
B52: net revenue | C52: =C51/1.2 -> 15739.792 | D52: =D51/1.2 -> 15436.417 | E52: =E51/1.2 -> 16450.458 | F52: =F51/1.2 -> 15823.958 | G52: =G51/1.2 -> 15903.708 | H52: =H51/1.2 -> 14420.375 | I52: =I51/1.2 -> 15721.208 | J52: =J51/1.2 -> 16063.417 | ... AG52: =AG51/1.2 -> 19132.875
B53: hours | C53: 430 | D53: 416 | E53: 420 | F53: 384 | G53: 404 | H53: 401 | I53: 409 | J53: 463 | K53: 402 | L53: 425 | M53: 435 | N53: =359+20 -> 379 | O53: 498 | P53: 405 | Q53: 410 | R53: 394 | S53: 428 | T53: 394 | U53: 412 | V53: 394 | W53: 423 | X53: 436 | Y53: 440 | Z53: 419 | AA53: 423 | AB53: 475
B54: cost £ (inc hol) | C54: =C53*12.21*1.1*1.1207 -> 6472.4123 | D54: =D53*12.21*1.1*1.1207 -> 6261.6826 | E54: =E53*12.21*1.1*1.1207 -> 6321.8911 | F54: =F53*12.21*1.1*1.1207 -> 5780.0147 | G54: =G53*12.21*1.1*1.1207 -> 6081.0572 | H54: =H53*12.21*1.1*1.1207 -> 6035.9008 | I54: =I53*12.21*1.1*1.1207 -> 6156.3178 | J54: =J53*12.21*1.1*1.1207 -> 6969.1323 | ... AA54: =AA53*12.21*1.1*1.1207 -> 6367.0475 | AB54: =AB53*12.71*1.1*1.1207 -> 7442.5407 | AC54: 6605 | AD54: =6870-741 -> 6129 | AE54: 7251 | AF54: 8071 | AG54: 7540
B55: Labour% | C55: =C54/C52 -> 0.41121334 | D55: =D54/D52 -> 0.40564354 | E55: =E54/E52 -> 0.38429878 | F55: =F54/F52 -> 0.36526984 | G55: =G54/G52 -> 0.38236725 | H55: =H54/H52 -> 0.41856753 | I55: =I54/I52 -> 0.39159317 | J55: =J54/J52 -> 0.43385118 | ... AG55: =AG54/AG52 -> 0.3940861
A56: Nole | B56: gross F&B sales | C56: =SALES!FN49 -> 16036.55 | D56: =SALES!FO49 -> 12404.65 | E56: =SALES!FP49 -> 9818.95 | F56: =SALES!FQ49 -> 13864.45 | G56: =SALES!FR49 -> 13815.66 | H56: =SALES!FS49 -> 12945.3 | I56: =SALES!FT49 -> 13876.67 | J56: =SALES!FU49 -> 14934.2 | ... AG56: =SALES!GR49 -> 19397.05
B57: net revenue | C57: =C56/1.2 -> 13363.792 | D57: =D56/1.2 -> 10337.208 | E57: =E56/1.2 -> 8182.4583 | F57: =F56/1.2 -> 11553.708 | G57: =G56/1.2 -> 11513.05 | H57: =H56/1.2 -> 10787.75 | I57: =I56/1.2 -> 11563.892 | J57: =J56/1.2 -> 12445.167 | ... AG57: =AG56/1.2 -> 16164.208
B58: hours | C58: 278 | D58: 239 | E58: 174 | F58: 228 | G58: 254 | H58: 268 | I58: 263 | J58: 255 | K58: 280 | L58: 265 | M58: 330 | N58: =225+5 -> 230 | O58: 305 | P58: 240 | Q58: 196 | R58: 180 | S58: 201 | T58: 191 | U58: 193 | V58: 181 | W58: 224 | X58: 214 | Y58: 200 | Z58: 220 | AA58: 240 | AB58: 281
B59: cost £ (inc hol) | C59: =C58*12.21*1.1*1.1207 -> 4184.4898 | D59: =D58*12.21*1.1*1.1207 -> 3597.4571 | E59: =E58*12.21*1.1*1.1207 -> 2619.0692 | F59: =F58*12.21*1.1*1.1207 -> 3431.8837 | G59: =G58*12.21*1.1*1.1207 -> 3823.2389 | H59: =H58*12.21*1.1*1.1207 -> 4033.9686 | I59: =I58*12.21*1.1*1.1207 -> 3958.708 | J59: =J58*12.21*1.1*1.1207 -> 3838.291 | ... AA59: =AA58*12.21*1.1*1.1207 -> 3612.5092 | AB59: =AB58*12.71*1.1*1.1207 -> 4402.8504 | AC59: 3473 | AD59: 2788 | AE59: 3411 | AF59: 3318 | AG59: 3852
B60: Labour% | C60: =C59/C57 -> 0.31312145 | D60: =D59/D57 -> 0.3480105 | E60: =E59/E57 -> 0.32008341 | F60: =F59/F57 -> 0.29703742 | G60: =G59/G57 -> 0.33207872 | H60: =H59/H57 -> 0.37393976 | I60: =I59/I57 -> 0.34233354 | J60: =J59/J57 -> 0.3084162 | ... AG60: =AG59/AG57 -> 0.23830428
A61: HB | B61: gross F&B sales | AE61: =SALES!GP85 -> 21466.65 | AF61: =SALES!GQ85 -> 23648.46 | AG61: =SALES!GR85 -> 22644.276
B62: net revenue | AE62: =AE61/1.2 -> 17888.875 | AF62: =AF61/1.2 -> 19707.05 | AG62: =AG61/1.2 -> 18870.23
B63: cost £ (inc hol) | AE63: 3526 | AF63: 3939 | AG63: 3817
B64: Labour% | AE64: =AE63/AE62 -> 0.19710574 | AF64: =AF63/AF62 -> 0.19987771 | AG64: =AG63/AG62 -> 0.20227628
A65: TAV | B65: gross F&B sales | AE65: =SALES!GP92 -> 29414.9 | AF65: =SALES!GQ92 -> 27614.49 | AG65: =SALES!GR92 -> 19621.2
B66: net revenue | AE66: =AE65/1.2 -> 24512.417 | AF66: =AF65/1.2 -> 23012.075 | AG66: =AG65/1.2 -> 16351
B67: cost £ (inc hol) | AE67: 3431 | AF67: 4044 | AG67: 3420
B68: Labour% | AE68: =AE67/AE66 -> 0.13996988 | AF68: =AF67/AF66 -> 0.17573383 | AG68: =AG67/AG66 -> 0.20916152
A69: FIV B | B69: gross F&B sales | AE69: =SALES!GP99 -> 9757.95 | AF69: =SALES!GQ99 -> 13145.5 | AG69: =SALES!GR99 -> 9886.95
B70: net revenue | AE70: =AE69/1.2 -> 8131.625 | AF70: =AF69/1.2 -> 10954.583 | AG70: =AG69/1.2 -> 8239.125
B71: cost £ (inc hol) | AE71: 1646 | AF71: 1754 | AG71: 1201
B72: Labour% | AE72: =AE71/AE70 -> 0.20241957 | AF72: =AF71/AF70 -> 0.16011563 | AG72: =AG71/AG70 -> 0.14576791
A73: SAM W | B73: gross F&B sales | AE73: =SALES!GP106 -> 11655.25 | AF73: =SALES!GQ106 -> 15361.25 | AG73: =SALES!GR106 -> 15476.3
B74: net revenue | AE74: =AE73/1.2 -> 9712.7083 | AF74: =AF73/1.2 -> 12801.042 | AG74: =AG73/1.2 -> 12896.917
B75: cost £ (inc hol) | AE75: 2081 | AF75: 2161 | AG75: 1946
B76: Labour% | AE76: =AE75/AE74 -> 0.21425538 | AF76: =AF75/AF74 -> 0.16881439 | AG76: =AG75/AG74 -> 0.15088878
A77: WEL A | B77: gross F&B sales | AE77: =SALES!GP113 -> 6976.9 | AF77: =SALES!GQ113 -> 8188.25 | AG77: =SALES!GR113 -> 7632.35
B78: net revenue | AE78: =AE77/1.2 -> 5814.0833 | AF78: =AF77/1.2 -> 6823.5417 | AG78: =AG77/1.2 -> 6360.2917
B79: cost £ (inc hol) | AE79: 880 | AF79: 1000 | AG79: 1000
B80: Labour% | AE80: =AE79/AE78 -> 0.15135662 | AF80: =AF79/AF78 -> 0.14655146 | AG80: =AG79/AG78 -> 0.15722549
A81: TOTAL | B81: total revenue | C81: =C57+C52+C47+C41+C35+C29+C24+C18+C12+C6 -> 213378.96 | D81: =D57+D52+D47+D41+D35+D29+D24+D18+D12+D6 -> 202719.76 | E81: =E57+E52+E47+E41+E35+E29+E24+E18+E12+E6 -> 229927.04 | F81: =F57+F52+F47+F41+F35+F29+F24+F18+F12+F6 -> 220296.03 | G81: =G57+G52+G47+G41+G35+G29+G24+G18+G12+G6 -> 206533.15 | H81: =H57+H52+H47+H41+H35+H29+H24+H18+H12+H6 -> 211822.23 | I81: =I57+I52+I47+I41+I35+I29+I24+I18+I12+I6 -> 210947.15 | J81: =J57+J52+J47+J41+J35+J29+J24+J18+J12+J6 -> 219821.41 | ... AG81: =AG57+AG52+AG47+AG41+AG35+AG29+AG24+AG18+AG12+AG6 -> 252168.83
B82: cost £ (inc hol) | C82: =C59+C54+C49+C43+C37+C31+C26+C20+C14+C8 -> 82595.787 | D82: =D59+D54+D49+D43+D37+D31+D26+D20+D14+D8 -> 80780.198 | E82: =E59+E54+E49+E43+E37+E31+E26+E20+E14+E8 -> 82714.438 | F82: =F59+F54+F49+F43+F37+F31+F26+F20+F14+F8 -> 77150.556 | G82: =G59+G54+G49+G43+G37+G31+G26+G20+G14+G8 -> 79958.009 | H82: =H59+H54+H49+H43+H37+H31+H26+H20+H14+H8 -> 79669.311 | I82: =I59+I54+I49+I43+I37+I31+I26+I20+I14+I8 -> 81600.324 | J82: =J59+J54+J49+J43+J37+J31+J26+J20+J14+J8 -> 84577.648 | ... AG82: =AG59+AG54+AG49+AG43+AG37+AG31+AG26+AG20+AG14+AG8 -> 87679.345
B83: Labour% | C83: =C82/C81 -> 0.38708497 | D83: =D82/D81 -> 0.39848212 | E83: =E82/E81 -> 0.35974211 | F83: =F82/F81 -> 0.3502131 | G83: =G82/G81 -> 0.38714371 | H83: =H82/H81 -> 0.37611403 | I83: =I82/I81 -> 0.38682828 | J83: =J82/J81 -> 0.38475619 | ... AG83: =AG82/AG81 -> 0.34770096

Sheet SALES
A1: Financial year week | FE1: 1 | FF1: 2 | FG1: 3 | FH1: 4 | FI1: 5 | FJ1: 6 | FK1: 7 | FL1: 8 | FM1: 9 | FN1: 10 | FO1: 11 | FP1: 12 | FQ1: 13 | FR1: 14 | FS1: 15 | FT1: 16 | FU1: 17 | FV1: 18 | FW1: 19 | FX1: 20 | FY1: 21 | FZ1: 22 | GA1: 23 | GB1: 24 | GC1: 25 | GD1: 26 | GE1: 27 | GF1: 28 | GG1: 29 | GH1: 30 | GI1: 31 | GJ1: 32 | GK1: 32 | GL1: 33 | GM1: 34 | GN1: 35 | GO1: 36 | GP1: 37 | GQ1: 38 | GR1: 39
A2: Calendar yr week | B2: GROSS WEEKLY SALES | Z2: 1 | AA2: 2 | AB2: 3 | AC2: 4 | AD2: 5 | AE2: 6 | AF2: 7 | AG2: 8 | AH2: 9 | AI2: 10 | AJ2: 11 | AK2: 12 | AL2: 13 | AM2: 14 | AN2: 15 | AO2: 16 | AP2: 17 | AQ2: 18 | AR2: 19 | AS2: 20 | AT2: 21 | AU2: 22 | AV2: 23 | AW2: 24 | AX2: 25 | AY2: 26 | AZ2: 27 | BA2: 28 | BB2: 29 | BC2: 30 | BD2: 31 | BE2: 32 | BF2: 33 | BG2: 34 | BH2: 35 | BI2: 36 | BJ2: 37 | BK2: 38 | BL2: 39 | BM2: 40 | BN2: 41 | BO2: 42 | BP2: 43 | BQ2: 44 | BR2: 45 | BS2: 46 | BT2: 47 | BU2: 48 | BV2: 49 | BW2: 50 | BX2: 51 | BY2: 52 | BZ2: 1 | CA2: 2 | CB2: 3 | CC2: 4 | CD2: 5 | CE2: 6 | CF2: 7 | CG2: 8 | CH2: 9 | CI2: 10 | CJ2: 11 | CK2: 12 | CL2: Easter 24 | CM2: 14 | CN2: 15 | CO2: 16 | CP2: 17 | CQ2: 18 | CR2: 19 | CS2: 20 | CT2: 21 | CU2: 22 | CV2: 23 | CW2: 24 | CX2: 25 | CY2: 26 | CZ2: 27 | DA2: 28 | DB2: 29 | DC2: 30 | DD2: 31 | DE2: 32 | DF2: 33 | DG2: 34 | DH2: 35 | DI2: 36 | DJ2: 37 | DK2: 38 | DL2: 39 | DM2: 40 | DN2: 41 | DO2: 42 | DP2: 43 | DQ2: 44 | DR2: 45 | DS2: 46 | DT2: 47 | DU2: 48 | DV2: 49 | DW2: 50 | DX2: 51 | DY2: 52 | DZ2: 1 | EA2: 2 | EB2: 3 | EC2: 4 | ED2: 5 | EE2: 6 | EF2: 7 | EG2: 8 | EH2: 9 | EI2: 10 | EJ2: 11 | EK2: 12 | EL2: 13 | EM2: 14 | EN2: 15 | EO2: 16 | EP2: 17 | EQ2: 18 | ER2: 19 | ES2: 20 | ET2: 21 | EU2: 22 | EV2: 23 | EW2: 24 | EX2: 25 | EY2: 26 | EZ2: 27 | FA2: 28 | FB2: 29 | FC2: 30 | FD2: 31 | FE2: 32 | FF2: 33 | FG2: 34 | FH2: 35 | FI2: 36 | FJ2: 37 | FK2: 38 | FL2: 39 | FM2: 40 | FN2: 41 | FO2: 42 | FP2: 43 | FQ2: 44 | FR2: 45 | FS2: 46 | FT2: 47 | FU2: 48 | FV2: 49 | FW2: 50 | FX2: 51 | FY2: 52 | FZ2: 53 | GA2: 1 | GB2: 2 | GC2: 3 | GD2: 4 | GE2: 5 | GF2: 6 | GG2: 7 | GH2: 8 | GI2: 9 | GJ2: 10 | GK2: 11 | GL2: 12 | GM2: 13 | GN2: 14 | GO2: 15 | GP2: 16 | GQ2: 17 | GR2: 18
A3: Calender notes | EL3: Mother's Day | EO3: Good Friday | EP3: Easter Monday | ER3: Bank hol Mon | EU3: Bank hol Mon | EW3: Father's Day | FK3: PA lunch closure | FO3: QH cls Mon-Thurs; N/MAR cls Sun | FP3: N/MAR closed Mon-Weds | FQ3: Closed Tues for staff bash | FV3: SP no lunch 3/12 | GC3: PA closed Tues-Thurs kitchen work, DG closed Mon-Thurs | GE3: HB internet - no sales 7/8 Feb | GJ3: Mother's Day | GL3: QH reopen Fri | GM3: Good Friday/Easter | GN3: Easter Monday | GQ3: Bank hol weekend | GR3: Bank hol Monday
A4: Site | C4: Item | D4: 01/08/2022 | E4: 08/08/2022 | F4: 15/08/2022 | G4: 22/08/2022 | H4: 29/08/2022 | I4: 05/09/2022 | J4: 12/09/2022 | K4: 19/09/2022 | L4: 26/09/2022 | M4: 03/10/2022 | N4: 10/10/2022 | O4: 17/10/2022 | P4: 24/10/2022 | Q4: 31/10/2022 | R4: 07/11/2022 | S4: 14/11/2022 | T4: 21/11/2022 | U4: 28/11/2022 | V4: 05/12/2022 | W4: 12/12/2022 | X4: 19/12/2022 | Y4: 26/12/2022 | Z4: 02/01/2023 | AA4: 09/01/2023 | AB4: 16/01/2023 | AC4: 23/01/2023 | AD4: 30/01/2023 | AE4: 06/02/2023 | AF4: 13/02/2023 | AG4: 20/02/2023 | AH4: 27/02/2023 | AI4: 06/03/2023 | AJ4: 13/03/2023 | AK4: 20/03/2023 | AL4: 27/03/2023 | AM4: 03/04/2023 | AN4: 10/04/2023 | AO4: 17/04/2023 | AP4: 24/04/2023 | AQ4: 01/05/2023 | AR4: 08/05/2023 | AS4: 15/05/2023 | AT4: 22/05/2023 | AU4: 29/05/2023 | AV4: 05/06/2023 | AW4: 12/06/2023 | AX4: 19/06/2023 | AY4: 26/06/2023 | AZ4: 03/07/2023 | BA4: 10/07/2023 | BB4: 17/07/2023 | BC4: 24/07/2023 | BD4: 31/07/2023 | BE4: 07/08/2023 | BF4: 14/08/2023 | BG4: 21/08/2023 | BH4: 28/08/2023 | BI4: 04/09/2023 | BJ4: 11/09/2023 | BK4: 18/09/2023 | BL4: 25/09/2023 | BM4: 02/10/2023 | BN4: 09/10/2023 | BO4: 16/10/2023 | BP4: 23/10/2023 | BQ4: 30/10/2023 | BR4: 06/11/2023 | BS4: 13/11/2023 | BT4: 20/11/2023 | BU4: 27/11/2023 | BV4: 04/12/2023 | BW4: 11/12/2023 | BX4: 18/12/2023 | BY4: 25/12/2023 | BZ4: 01/01/2024 | CA4: 08/01/2024 | CB4: 45306 | CC4: 45313 | CD4: 45320 | CE4: 45327 | CF4: 45334 | CG4: 45341 | CH4: 45348 | CI4: 45355 | CJ4: 45362 | CK4: 45369 | CL4: 45376 | CM4: 45017 | CN4: 45390 | CO4: 45397 | CP4: 45404 | CQ4: 45411 | CR4: 45418 | CS4: 45425 | CT4: 45432 | CU4: 45439 | CV4: 45446 | CW4: 45453 | CX4: 45460 | CY4: 45467 | CZ4: 45474 | DA4: 45481 | DB4: 45488 | DC4: 45495 | DD4: 45502 | DE4: 45509 | DF4: 45516 | DG4: 45523 | DH4: 45530 | DI4: 45537 | DJ4: 45544 | DK4: =DJ4+7 -> 45551 | DL4: =DK4+7 -> 45558 | DM4: =DL4+7 -> 45565 | DN4: =DM4+7 -> 45572 | DO4: 45579 | DP4: 45586 | DQ4: 45593 | DR4: 45600 | DS4: 45607 | DT4: 45614 | DU4: 45621 | DV4: 45628 | DW4: 45635 | DX4: 45642 | DY4: 45649 | DZ4: 45656 | EA4: 45663 | EB4: 45670 | EC4: 45677 | ED4: 45684 | EE4: 45691 | EF4: 45698 | EG4: 45705 | EH4: 45712 | EI4: 45719 | EJ4: 45726 | EK4: 45733 | EL4: 45740 | EM4: 45747 | EN4: 45754 | EO4: 45761 | EP4: 45768 | EQ4: 45775 | ER4: 45782 | ES4: 45789 | ET4: 45796 | EU4: 45803 | EV4: 45810 | EW4: 45817 | EX4: 45824 | EY4: 45831 | EZ4: =EY4+7 -> 45838 | FA4: 45845 | FB4: 45852 | FC4: 45859 | FD4: 45866 | FE4: 45873 | FF4: 45880 | FG4: 45887 | FH4: 45894 | FI4: 45901 | FJ4: 45908 | FK4: 45915 | FL4: 45922 | FM4: 45929 | FN4: 45936 | FO4: 45943 | FP4: 45950 | FQ4: 45957 | FR4: 45964 | FS4: 45971 | FT4: 45978 | FU4: 45984 | FV4: 45992 | FW4: 45999 | FX4: 46006 | FY4: 46013 | FZ4: 46385 | GA4: 46027 | GB4: 46034 | GC4: 46041 | GD4: 46048 | GE4: 46055 | GF4: 46062 | GG4: 46069 | GH4: 46076 | GI4: 46083 | GJ4: 46090 | GK4: 46097 | GL4: 46104 | GM4: 46111 | GN4: 46118 | GO4: =GN4+7 -> 46125 | GP4: =GO4+7 -> 46132 | GQ4: =GP4+7 -> 46139 | GR4: 46146 | GW4: Avg LTM | GX4: Avg L6M | GY4: Avg L3M | GZ4: Avg L5W | HA4: Max
A5: PEMBROKE ARMS | B5: PEMBROKE ARMS | C5: WET | D5: 16059.93 | E5: 14743.2 | F5: 13060.15 | G5: 14018.67 | H5: 12910.32 | I5: 10380.94 | J5: 14393.38 | K5: 14639.05 | L5: 9804.33 | M5: 10976.16 | N5: 3400.74 | O5: 8820.59 | P5: 9837.22 | Q5: 8261.97 | R5: 10154.5 | S5: 8111.16 | T5: 7634.04 | U5: 8959.86 | V5: 8900.03 | W5: 10074.19 | X5: 15168.63 | Y5: 9231.34 | Z5: 6885.7 | AA5: 7292.26 | AB5: 6874.75 | AC5: 7019.35 | AD5: 8384.3 | AE5: 9339.12 | AF5: 12390.8 | AG5: 9908.04 | AH5: 11229.05 | AI5: 10400.51 | AJ5: 10087.07 | AK5: 10727.69 | AL5: 11847.27 | AM5: 17493.89 | AN5: 14955.66 | AO5: 10543.3 | AP5: 13703.75 | AQ5: 12235.01 | AR5: 12383.32 | AS5: 13696.76 | AT5: 15493.92 | AU5: 19694.51 | AV5: 15963.98 | AW5: 16931.52 | AX5: 18523.22 | AY5: 18404.17 | AZ5: 16303.4 | BA5: 15982.92 | BB5: 18571.42 | BC5: 15198.53 | BD5: 18973.05 | BE5: 16255.49 | BF5: 17193.68 | BG5: 20226.89 | BH5: 16116.01 | BI5: 19664.19 | BJ5: 16813.45 | BK5: 9962.55 | BL5: 14874.35 | BM5: 14770.21 | BN5: 11796.8 | BO5: 11610.34 | BP5: 11660.45 | BQ5: 10999.3 | BR5: 11437.75 | BS5: 15361.59 | BT5: 12289.77 | BU5: 12149.54 | BV5: 14465.39 | BW5: 14677.05 | BX5: 20832.69 | BY5: 13794 | BZ5: 11436.34 | CA5: 10462.15 | CB5: 11166.39 | CC5: 11059.39 | CD5: 13380.57 | CE5: 12087.76 | CF5: 12606.34 | CG5: 11476.21 | CH5: 12727.6 | CI5: 12835.84 | CJ5: 12100.97 | CK5: 12838.33 | CL5: 17314.62 | CM5: 15891.1 | CN5: 15921.27 | CO5: 14073.81 | CP5: 12666.1 | CQ5: 17605.29 | CR5: 18507.86 | CS5: 14311.87 | CT5: 19474.95 | CU5: 18546.62 | CV5: 14699.07 | CW5: 17458.14 | CX5: 22063.17 | CY5: 17503.72 | CZ5: 17085.59 | DA5: 22507.4 | DB5: 17925.6 | DC5: 19148.37 | DD5: 23981.25 | DE5: 17433.27 | DF5: 20703.49 | DG5: 18434.6 | DH5: 19472.77 | DI5: 16315.68 | DJ5: 14446.85 | DK5: 17713.75 | DL5: 17239.76 | DM5: 14670.97 | DN5: 15526.1 | DO5: 14054.64 | DP5: 16005.95 | DQ5: 14622.45 | DR5: 13738.36 | DS5: 11966.32 | DT5: 12596.89 | DU5: 15642.97 | DV5: 16214.9 | DW5: 16519.45 | DX5: 20979.27 | DY5: 18559.7 | DZ5: 12716.05 | EA5: 10937.12 | EB5: 12726.52 | EC5: 13617 | ED5: 12252.45 | EE5: 11010.73 | EF5: 12996.7 | EG5: 16875.71 | EH5: 14614.85 | EI5: 14073.32 | EJ5: 14207.57 | EK5: 13359.06 | EL5: 16295.5 | EM5: 19701.45 | EN5: 17682.46 | EO5: 19957.79 | EP5: 17483.04 | EQ5: 19745.2 | ER5: 16520.2 | ES5: 15780.63 | ET5: 15801.1 | EU5: 20531.49 | EV5: 17645.65 | EW5: 22130.29 | EX5: 19959.57 | EY5: 22901 | EZ5: 24710.54 | FA5: 23529.26 | FB5: 20823.84 | FC5: 24409.62 | FD5: 21834.77 | FE5: 21427.7 | FF5: 24161.05 | FG5: 20856.82 | FH5: 19494.94 | FI5: 16093.85 | FJ5: 19481.44 | FK5: 16252.1 | FL5: 14809.29 | FM5: 16019.65 | FN5: 15433.05 | FO5: 15281.36 | FP5: 19441.41 | FQ5: =15983.44+2000 -> 17983.44 | FR5: =16987.39-2000 -> 14987.39 | FS5: 14674.37 | FT5: 14800.06 | FU5: 13914.99 | FV5: 16030 | FW5: 17931.78 | FX5: =23193.68+1164.6+632.57 -> 24990.85 | FY5: =16545.65-1164.6-632.57 -> 14748.48 | FZ5: 20149.25 | GA5: 13751.34 | GB5: 16372.77 | GC5: 8290.04 | GD5: 13979.77 | GE5: 13718.23 | GF5: 15512.47 | GG5: =2385.65+12179.4 -> 14565.05 | GH5: 15149.75 | GI5: 15800.34 | GJ5: 18289.5 | GK5: 18612.33 | GL5: 16332.29 | GM5: 20450.81 | GN5: 20043.63 | GO5: 16105.84 | GP5: 18227.28 | GQ5: 21234.97 | GR5: 18503.98 | GS5: =EQ5 -> 19745.2 | GT5: WET | GU5: Weekly margins
C6: DRY | D6: 26988.4 | E6: 24638.39 | F6: 23660.75 | G6: 23119.67 | H6: 25149.63 | I6: 19736.5 | J6: 18496.25 | K6: 16527.42 | L6: 16170.75 | M6: 17821.57 | N6: 14138.75 | O6: 15903.16 | P6: 18564.13 | Q6: 15174.15 | R6: 17495.68 | S6: 15674.35 | T6: 13759 | U6: 17398.1 | V6: 17542 | W6: 18377.2 | X6: 20429.26 | Y6: 15338.6 | Z6: 13169.75 | AA6: 10372.7 | AB6: 12875.25 | AC6: 12784.5 | AD6: 15188.8 | AE6: 15200.3 | AF6: 19723.48 | AG6: 17835.83 | AH6: 22249.55 | AI6: 16972.15 | AJ6: 20107.65 | AK6: 18834 | AL6: 21032.5 | AM6: 28058.5 | AN6: 25519.8 | AO6: 18569.23 | AP6: 25943.7 | AQ6: 19053.05 | AR6: 18887.8 | AS6: 22257.85 | AT6: 26242.35 | AU6: 30256.35 | AV6: 23426.5 | AW6: 27747.96 | AX6: 26386.8 | AY6: 31460.99 | AZ6: 26694.22 | BA6: 26440.5 | BB6: 32258.2 | BC6: 27154 | BD6: 32974.27 | BE6: 28687.77 | BF6: 28130.6 | BG6: 32845.17 | BH6: 31128.46 | BI6: 27924.4 | BJ6: 26948.75 | BK6: 21222.32 | BL6: 23588.65 | BM6: 24922.31 | BN6: 23283.85 | BO6: 23024.6 | BP6: 22669.6 | BQ6: 20395.85 | BR6: 24775.25 | BS6: 26049.18 | BT6: 21722 | BU6: 23479.9 | BV6: 30071.6 | BW6: 29489.34 | BX6: 28745.88 | BY6: 24382.03 | BZ6: 25339.5 | CA6: 21628.25 | CB6: 20737.9 | CC6: 20259.15 | CD6: 22952.25 | CE6: 22122.7 | CF6: 25050.1 | CG6: 22297.85 | CH6: 25201.35 | CI6: 26510.63 | CJ6: 22851.3 | CK6: 24215.2 | CL6: 30498.95 | CM6: 29117.35 | CN6: 30092.7 | CO6: 26206.37 | CP6: 26193.61 | CQ6: 30332.2 | CR6: 28235 | CS6: 23848.7 | CT6: 32905.95 | CU6: 32026.1 | CV6: 27081.9 | CW6: 33904.9 | CX6: 32719.5 | CY6: 31105.44 | CZ6: 31269.75 | DA6: 33524.06 | DB6: 31440.75 | DC6: 33081.3 | DD6: 37381.55 | DE6: 38604.4 | DF6: 36050.75 | DG6: 35919.65 | DH6: 36422.7 | DI6: 30723.25 | DJ6: 24686.8 | DK6: 31361.65 | DL6: 32314.5 | DM6: 28626.6 | DN6: 27819.92 | DO6: 26298.84 | DP6: 29840.1 | DQ6: 29883.12 | DR6: 25292.55 | DS6: 22608.97 | DT6: 23005.75 | DU6: 32375.8 | DV6: 31392.5 | DW6: 34010.87 | DX6: 35173.77 | DY6: 29640.05 | DZ6: 23149.95 | EA6: 24365.64 | EB6: 26671.27 | EC6: 26861.25 | ED6: 25523.19 | EE6: 23396.05 | EF6: 26153.4 | EG6: 32740.07 | EH6: 26675.8 | EI6: 29021.37 | EJ6: 28525.1 | EK6: 28719.5 | EL6: 35795.5 | EM6: 34969.5 | EN6: 30905.25 | EO6: 39463.75 | EP6: 32186.65 | EQ6: 32723.7 | ER6: 32052.15 | ES6: 30029.05 | ET6: 30566.55 | EU6: 42214.45 | EV6: 30756 | EW6: 39317.95 | EX6: 32122.6 | EY6: 39197.3 | EZ6: 40449.51 | FA6: 36274.59 | FB6: 37249.35 | FC6: 36181.1 | FD6: 39902.05 | FE6: 39336.05 | FF6: 42864.57 | FG6: 40145.7 | FH6: 36935.15 | FI6: 33302.85 | FJ6: 40161.8 | FK6: 30025.55 | FL6: 28626.35 | FM6: 30845 | FN6: 28202.8 | FO6: 31285.95 | FP6: 34208.92 | FQ6: =28458.8+2000 -> 30458.8 | FR6: =32573.05-2000 -> 30573.05 | FS6: 29545.65 | FT6: 30339.4 | FU6: 28930.75 | FV6: 32639.9 | FW6: 37935.5 | FX6: =40863.21+1750+632.57 -> 43245.78 | FY6: =29505.77-1750-632.57 -> 27123.2 | FZ6: 43763.18 | GA6: 27393.41 | GB6: 32888.07 | GC6: 18852.85 | GD6: 31057.55 | GE6: 29598.3 | GF6: 31926.05 | GG6: =3379.35+27303 -> 30682.35 | GH6: 30581.59 | GI6: 31685.93 | GJ6: 40598.43 | GK6: 33340.6 | GL6: 30841.39 | GM6: 39514.12 | GN6: 39419.17 | GO6: 31642.42 | GP6: 34138.52 | GQ6: 36054.73 | GR6: 37097.82 | GS6: =EQ6 -> 32723.7 | GT6: DRY | GU6: Dry % | GV6: =DRY!AG37 -> 0.79967281
B7: Site total | D7: =SUM(D5+D6) -> 43048.33 | E7: =SUM(E5+E6) -> 39381.59 | F7: =SUM(F5+F6) -> 36720.9 | G7: =SUM(G5+G6) -> 37138.34 | H7: =SUM(H5+H6) -> 38059.95 | I7: =SUM(I5+I6) -> 30117.44 | J7: =SUM(J5+J6) -> 32889.63 | K7: =SUM(K5+K6) -> 31166.47 | ... GM7: =SUM(GM5+GM6) -> 59964.93 | GN7: =SUM(GN6+GN5) -> 59462.8 | GO7: =SUM(GO6+GO5) -> 47748.26 | GP7: =SUM(GP6+GP5) -> 52365.8 | GQ7: =SUM(GQ6+GQ5) -> 57289.7 | GR7: =SUM(GR6+GR5) -> 55601.8 | GS7: =SUM(GS5+GS6) -> 52468.9 | GT7: =B5 -> PEMBROKE ARMS | GU7: Dry % (avg) | GV7: =DRY!AH37 -> 0.75308452 | GW7: =AVERAGE(ES7:GR7) -> 52039.06 | GX7: =AVERAGE(FS7:GR7) -> 49731.417 | GY7: =AVERAGE(GF7:GR7) -> 52027.028 | GZ7: =AVERAGE(GN7:GR7) -> 54493.672 | HA7: =MAX(D7:GR7) -> 68236.63
B8: vs last week % | E8: =SUM(E7-D7) -> -3666.74 | F8: =SUM(F7-E7) -> -2660.69 | G8: =SUM(G7-F7) -> 417.44 | H8: =SUM(H7-G7) -> 921.61 | I8: =SUM(I7-H7) -> -7942.51 | J8: =SUM(J7-I7) -> 2772.19 | K8: =SUM(K7-J7) -> -1723.16 | L8: =SUM(L7-K7) -> -5191.39 | ... DH8: =SUM(DH7-DG7) -> 1541.22 | DI8: =SUM(DI7-DH7)/DH7 -> -0.15844826 | DJ8: =SUM(DJ7-DI7)/DI7 -> -0.16805824 | DK8: =(DK7-DJ7)/DJ7 -> 0.25404607 | DL8: =(DL7-DK7)/DK7 -> 0.0097576382 | DM8: =(DM7-DL7)/DL7 -> -0.12625938 | DN8: =(DN7-DM7)/DM7 -> 0.0011190004 | DO8: =(DO7-DN7)/DN7 -> -0.069038403 | DP8: =(DP7-DO7)/DO7 -> 0.13611143 | DQ8: =(DQ7-DP7)/DP7 -> -0.029238724 | DR8: =(DR7-DQ7)/DQ7 -> -0.12301067 | ... GR8: =(GR7-GQ7)/GQ7 -> -0.029462539 | GU8: Labour % | GV8: =LABOUR!AG44 -> 0.34128222
B9: Same week last year | BD9: =D7 -> 43048.33 | BE9: =E7 -> 39381.59 | BF9: =F7 -> 36720.9 | BG9: =G7 -> 37138.34 | BH9: =H7 -> 38059.95 | BI9: =I7 -> 30117.44 | BJ9: =J7 -> 32889.63 | BK9: =K7 -> 31166.47 | ... GL9: =EL7 -> 52091 | GM9: =EL7 -> 52091 | GN9: =EM7 -> 54670.95 | GO9: =EN7 -> 48587.71 | GP9: =EO7 -> 59421.54 | GQ9: =EP7 -> 49669.69 | GR9: =EQ7 -> 52468.9 | GT9: Same week last year
B10: vs SWLY % | BD10: =(BD7-BD9)/BD9 -> 0.20672091 | BE10: =(BE7-BE9)/BE9 -> 0.14122513 | BF10: =(BF7-BF9)/BF9 -> 0.2342911 | BG10: =(BG7-BG9)/BG9 -> 0.42903695 | BH10: =(BH7-BH9)/BH9 -> 0.24131719 | BI10: =(BI7-BI9)/BI9 -> 0.58010077 | BJ10: =(BJ7-BJ9)/BJ9 -> 0.33057745 | BK10: =(BK7-BK9)/BK9 -> 0.00059037806 | ... GR10: =(GR7-GR9)/GR9 -> 0.059709657 | GT10: YoY LFL %
A12: GROSVENOR ARMS | B12: GROSVENOR ARMS | C12: WET | D12: 7610.5 | E12: 10441.75 | F12: 9527.8 | G12: 11075.05 | H12: 9164.25 | I12: 6835.3 | J12: 9807.25 | K12: 7345.75 | L12: 8007.25 | M12: 7614.9 | N12: 8751.05 | O12: 7277.15 | P12: 8236.3 | Q12: 6844.9 | R12: 8727.9 | S12: 8734.05 | T12: 7806.25 | U12: 7769.15 | V12: 8085.1 | W12: 7638.1 | X12: 8079.8 | Y12: 14240.45 | Z12: 7235.4 | AA12: 7851.9 | AB12: 8682.55 | AC12: 8149.7 | AD12: 9048.25 | AE12: 7498.8 | AF12: 9434.45 | AG12: 7750.6 | AH12: 7604.15 | AI12: 6945.75 | AJ12: 9546.9 | AK12: 8599.7 | AL12: 8745.3 | AM12: 13471.05 | AN12: 9910.55 | AO12: 8436.25 | AP12: 10773.1 | AQ12: 9525.3 | AR12: 9285.6 | AS12: 8927.75 | AT12: 11138.85 | AU12: 12240.15 | AV12: 10562.3 | AW12: 10782.2 | AX12: 10372.95 | AY12: 9081.17 | AZ12: 10403.7 | BA12: 13064.65 | BB12: 12091.65 | BC12: 11711.2 | BD12: 11350.2 | BE12: 11916.85 | BF12: 10187.7 | BG12: 10833.61 | BH12: 11004.7 | BI12: 9325.5 | BJ12: 9086.35 | BK12: 7143.55 | BL12: 9489.95 | BM12: 7724.45 | BN12: 9782.25 | BO12: 9505.35 | BP12: 10397.45 | BQ12: 9883 | BR12: 8651.85 | BS12: 6256.5 | BT12: 11310.4 | BU12: 9205.55 | BV12: 9930 | BW12: 10316.3 | BX12: 12642.25 | BY12: 15042.2 | BZ12: 8972.4 | CA12: 8192 | CB12: 7838.95 | CC12: 7033.15 | CD12: 8960 | CE12: 10010.6 | CF12: 10913.35 | CG12: 7897.95 | CH12: 8858.6 | CI12: 9809.4 | CJ12: 7780.85 | CK12: 8315.1 | CL12: 11389.85 | CM12: 8761.8 | CN12: 8608.8 | CO12: 9047.75 | CP12: 8990.1 | CQ12: 10265.5 | CR12: 8240.3 | CS12: 8624.4 | CT12: 10941.15 | CU12: 10103.7 | CV12: 9053 | CW12: 9549.6 | CX12: 7759.3 | CY12: 10390.85 | CZ12: 8295.9 | DA12: 9249.2 | DB12: 10048.45 | DC12: 9196.2 | DD12: 10133.55 | DE12: 10092.5 | DF12: 10894.65 | DG12: 12049.3 | DH12: 10319.6 | DI12: 8942.2 | DJ12: 7698.55 | DK12: 10418.9 | DL12: 10077.5 | DM12: 9813.55 | DN12: 10757.2 | DO12: 10980.5 | DP12: 13041.1 | DQ12: 11155.3 | DR12: 9204.15 | DS12: 9510.85 | DT12: 7175.3 | DU12: 11606.8 | DV12: 8984.95 | DW12: 9916.2 | DX12: 10946.85 | DY12: 14334.6 | DZ12: 13094.6 | EA12: 8513.75 | EB12: 9699.35 | EC12: 8547.65 | ED12: 8501.2 | EE12: 8133.7 | EF12: 8249.1 | EG12: 9196.85 | EH12: 9338.65 | EI12: 0 | EJ12: 7418.9 | EK12: 9073.7 | EL12: 10583.45 | EM12: 9728.2 | EN12: 10724 | EO12: 13932.1 | EP12: 11886.15 | EQ12: 10765.5 | ER12: 10082.85 | ES12: 10445.35 | ET12: 10463.2 | EU12: 12655.3 | EV12: 11041.1 | EW12: 11224.45 | EX12: 8624.75 | EY12: 11019.4 | EZ12: 9807.8 | FA12: 10061.65 | FB12: 10544.5 | FC12: 10319.4 | FD12: 12275.2 | FE12: 12021.6 | FF12: 11865.4 | FG12: 11830.2 | FH12: 12529.3 | FI12: 9542.7 | FJ12: 11478.15 | FK12: 9923.7 | FL12: 9912.05 | FM12: 9840.5 | FN12: 9625.7 | FO12: 9210.25 | FP12: 10815.36 | FQ12: 10040 | FR12: 8415.1 | FS12: 10279.15 | FT12: =11345.65+350 -> 11695.65 | FU12: 9673.9 | FV12: 8172.55 | FW12: 9217.85 | FX12: 10922.25 | FY12: 9771.35 | FZ12: 18954.3 | GA12: =8002.1+368 -> 8370.1 | GB12: 8831.4 | GC12: 8976.2 | GD12: 8942.3 | GE12: 10406 | GF12: 9311.7 | GG12: 9995.3 | GH12: 8741.6 | GI12: 8897 | GJ12: 9421.35 | GK12: 10057.1 | GL12: 9034.85 | GM12: 12011.67 | GN12: 11298.05 | GO12: 10904.4 | GP12: 9760.72 | GQ12: 12211.85 | GR12: 9859.78 | GS12: =EQ12 -> 10765.5 | GT12: WET | GU12: Weekly margins
C13: DRY | D13: 11896.2 | E13: 13671.7 | F13: 14691.95 | G13: 16925.45 | H13: 12383.75 | I13: 11073.85 | J13: 12946.6 | K13: 11586.65 | L13: 12890 | M13: 12082.95 | N13: 12386.1 | O13: 12759 | P13: 13131 | Q13: 8816.45 | R13: 11703.55 | S13: 13299.25 | T13: 11497.25 | U13: 11540.3 | V13: 11037.35 | W13: 12937.65 | X13: 10753.25 | Y13: 17934.7 | Z13: 12885.95 | AA13: 10994.85 | AB13: 12250.25 | AC13: 12762.5 | AD13: 12983.05 | AE13: 11589.6 | AF13: 15630.85 | AG13: 11148.5 | AH13: 12420 | AI13: 11639.8 | AJ13: 15522.05 | AK13: 13316.9 | AL13: 14936.95 | AM13: 20858.85 | AN13: 15947.55 | AO13: 12495.31 | AP13: 15963.3 | AQ13: 14711.3 | AR13: 12743.55 | AS13: 12670.3 | AT13: 16218.9 | AU13: 18922.9 | AV13: 14937.6 | AW13: 16278.2 | AX13: 14049.15 | AY13: 12712.15 | AZ13: 14636.5 | BA13: 19965.35 | BB13: 17651.8 | BC13: 18319.2 | BD13: 20735.9 | BE13: 18349.7 | BF13: 16548 | BG13: 17568.6 | BH13: 17007.4 | BI13: 13540.5 | BJ13: 13933.15 | BK13: 12361.65 | BL13: 13398.5 | BM13: 11815.65 | BN13: 14275.87 | BO13: 15987.35 | BP13: 18503.3 | BQ13: 14137.55 | BR13: 12773.35 | BS13: 15046.55 | BT13: 15374.6 | BU13: 15223.5 | BV13: 16100.85 | BW13: 17608.6 | BX13: 17346.65 | BY13: 18584.55 | BZ13: 14889.8 | CA13: 14475.8 | CB13: 13637 | CC13: 12847.3 | CD13: 13115.1 | CE13: 14470.1 | CF13: 18325.7 | CG13: 12170.1 | CH13: 13429.6 | CI13: 16907.5 | CJ13: 11998.8 | CK13: 13835.7 | CL13: 16526.2 | CM13: 14199.3 | CN13: 13909.2 | CO13: 14495.4 | CP13: 14770.5 | CQ13: 15742.35 | CR13: 11570.65 | CS13: 13635.8 | CT13: 17146.35 | CU13: 16242 | CV13: 13805.1 | CW13: 15318.3 | CX13: 12136.3 | CY13: 15584.1 | CZ13: 12949.35 | DA13: 14685.1 | DB13: 15402.45 | DC13: 15430.15 | DD13: 16090.8 | DE13: 15557.15 | DF13: 17080.05 | DG13: 19503.75 | DH13: 18204.25 | DI13: 14410.3 | DJ13: 12558.05 | DK13: 15763.8 | DL13: 15185.55 | DM13: 15108.2 | DN13: 15652.8 | DO13: 17343.95 | DP13: 19573.75 | DQ13: 18204.15 | DR13: 13429.8 | DS13: 14088.65 | DT13: 12660.2 | DU13: 16438.45 | DV13: 12460.55 | DW13: 13702.45 | DX13: 16713.7 | DY13: 20518.05 | DZ13: 18965.55 | EA13: 13079 | EB13: 13744.2 | EC13: 13519 | ED13: 13859.55 | EE13: 11433.85 | EF13: 13316.55 | EG13: 13919.64 | EH13: 14957.55 | EI13: 0 | EJ13: 11444.6 | EK13: 13810.56 | EL13: 17068.1 | EM13: 14639.35 | EN13: 15537.55 | EO13: 19609.05 | EP13: 17058.5 | EQ13: 16718.95 | ER13: 16296.6 | ES13: 13642 | ET13: 14615.5 | EU13: 16933.75 | EV13: 16280.8 | EW13: 15473.7 | EX13: 11613.1 | EY13: 15013.4 | EZ13: 13956.7 | FA13: 12825.62 | FB13: 16497.15 | FC13: 14822.8 | FD13: 17680 | FE13: 16917.9 | FF13: 16847.57 | FG13: 18096.7 | FH13: 18243.6 | FI13: 14956.1 | FJ13: 15874.2 | FK13: 14357.4 | FL13: 14873.45 | FM13: 15607 | FN13: 14229.2 | FO13: 13047.7 | FP13: 16771.9 | FQ13: 15696.3 | FR13: 11044.3 | FS13: 16611.9 | FT13: 17538.65 | FU13: 15067.8 | FV13: 13036.2 | FW13: 14291.15 | FX13: 14891.76 | FY13: 16977.2 | FZ13: 26815.55 | GA13: 12818.1 | GB13: 13081.18 | GC13: 14420.2 | GD13: 14037.2 | GE13: 14511.8 | GF13: 14124.5 | GG13: 15603.75 | GH13: 12221.5 | GI13: 13265.25 | GJ13: 16427.75 | GK13: 13748.75 | GL13: 12660 | GM13: 18977.73 | GN13: 19414.07 | GO13: 14457 | GP13: 14681.43 | GQ13: 17940.8 | GR13: 13990.67 | GS13: =EQ13 -> 16718.95 | GT13: DRY | GU13: Dry % | GV13: =DRY!AG22 -> 0.63992203
B14: Site total | D14: =SUM(D12:D13) -> 19506.7 | E14: =SUM(E12:E13) -> 24113.45 | F14: =SUM(F12:F13) -> 24219.75 | G14: =SUM(G12:G13) -> 28000.5 | H14: =SUM(H12:H13) -> 21548 | I14: =SUM(I12:I13) -> 17909.15 | J14: =SUM(J12:J13) -> 22753.85 | K14: =SUM(K12:K13) -> 18932.4 | ... GR14: =SUM(GR12:GR13) -> 23850.45 | GS14: =SUM(GS12+GS13) -> 27484.45 | GT14: =B12 -> GROSVENOR ARMS | GU14: Dry % (avg) | GV14: =DRY!AH22 -> 0.65110901 | GW14: =AVERAGE(ES14:GR14) -> 25745.773 | GX14: =AVERAGE(FS14:GR14) -> 25666.548 | GY14: =AVERAGE(GF14:GR14) -> 25309.121 | GZ14: =AVERAGE(GN14:GR14) -> 26903.754 | HA14: =MAX(D14:GR14) -> 45769.85
B15: vs last week % | E15: =SUM(E14-D14) -> 4606.75 | F15: =SUM(F14-E14) -> 106.3 | G15: =SUM(G14-F14) -> 3780.75 | H15: =SUM(H14-G14) -> -6452.5 | I15: =SUM(I14-H14) -> -3638.85 | J15: =SUM(J14-I14) -> 4844.7 | K15: =SUM(K14-J14) -> -3821.45 | L15: =SUM(L14-K14) -> 1964.85 | ... DH15: =SUM(DH14-DG14) -> -3029.2 | DI15: =SUM(DI14-DH14)/DH14 -> -0.18129916 | DJ15: =SUM(DJ14-DI14)/DI14 -> -0.13257253 | DK15: =SUM(DK14-DJ14)/DJ14 -> 0.29255156 | DL15: =SUM(DL14-DK14)/DK14 -> -0.035124338 | DM15: =SUM(DM14-DL14)/DL14 -> -0.013509849 | DN15: =SUM(DN14-DM14)/DM14 -> 0.059716914 | DO15: =SUM(DO14-DN14)/DN14 -> 0.072489587 | DP15: =SUM(DP14-DO14)/DO14 -> 0.15147337 | ... GK15: =SUM(GK14-GJ14)/GJ14 -> -0.079045305 | GL15: =(GL14-GK14)/GK14 -> -0.088675683 | GM15: =(GM14-GL14)/GL14 -> 0.42842195 | GN15: =(GN14-GM14)/GM14 -> -0.0089475756 | GO15: =(GO14-GN14)/GN14 -> -0.17422177 | GP15: =(GP14-GO14)/GO14 -> -0.036246027 | GQ15: =(GQ14-GP14)/GP14 -> 0.23363329 | GR15: =(GR14-GQ14)/GQ14 -> -0.20900982 | GU15: Labour % | GV15: =LABOUR!AG27 -> 0.40160182
B16: Same week last year | BD16: =D14 -> 19506.7 | BE16: =E14 -> 24113.45 | BF16: =F14 -> 24219.75 | BG16: =G14 -> 28000.5 | BH16: =H14 -> 21548 | BI16: =I14 -> 17909.15 | BJ16: =J14 -> 22753.85 | BK16: =K14 -> 18932.4 | ... GL16: =EL14 -> 27651.55 | GM16: =EL14 -> 27651.55 | GN16: =EM14 -> 24367.55 | GO16: =EN14 -> 26261.55 | GP16: =EO14 -> 33541.15 | GQ16: =EP14 -> 28944.65 | GR16: =EQ14 -> 27484.45 | GT16: Same week last year
B17: vs SWLY % | BD17: =(BD14-BD16)/BD16 -> 0.64487586 | BE17: =(BE14-BE16)/BE16 -> 0.25517294 | BF17: =(BF14-BF16)/BF16 -> 0.1038801 | BG17: =(BG14-BG16)/BG16 -> 0.01434653 | BH17: =(BH14-BH16)/BH16 -> 0.29998608 | BI17: =(BI14-BI16)/BI16 -> 0.27677751 | BJ17: =(BJ14-BJ16)/BJ16 -> 0.011674947 | BK17: =(BK14-BK16)/BK16 -> 0.030255013 | ... GH17: =(GH14-GH16)/GH16 -> -0.13718606 | GJ17: =(GJ14-GJ16)/GJ16 -> 0.37032364 | GK17: =(GK14-GK16)/GK16 -> 0.040271785 | GL17: =(GL14-GL16)/GL16 -> -0.21542011 | GM17: =(GM14-GM16)/GM16 -> 0.12071114 | GN17: =(GN14-GN16)/GN16 -> 0.26036963 | GO17: =(GO14-GO16)/GO16 -> -0.034276347 | GP17: =(GP14-GP16)/GP16 -> -0.27127871 | GQ17: =(GQ14-GQ16)/GQ16 -> 0.041734828 | GR17: =(GR14-GR16)/GR16 -> -0.13222022 | GT17: YoY LFL %
A19: BELL & CROWN | B19: BELL & CROWN | C19: WET | D19: 5855.15 | E19: 5747 | F19: 6077.15 | G19: 5918.9 | H19: 5671.5 | I19: 4350.5 | J19: 4936.1 | K19: 4504.1 | L19: 4670.75 | M19: 5834.7 | N19: 5110.35 | O19: 6347.5 | P19: 7389.75 | Q19: 6380.7 | R19: 6359.4 | S19: 5886.9 | T19: 7154.6 | U19: 6663.05 | V19: 6569.25 | W19: 6418.4 | X19: 7100.62 | Y19: 10195.28 | Z19: 7077.55 | AA19: 5689.35 | AB19: 5858.95 | AC19: 6266 | AD19: 6458.2 | AE19: 6811.75 | AF19: 7562.75 | AG19: 7036.1 | AH19: 6510.85 | AI19: 5734.6 | AJ19: 7400.8 | AK19: 6898 | AL19: 7199.95 | AM19: 10895.8 | AN19: 8084.9 | AO19: 7431.6 | AP19: 8555.55 | AQ19: 8749.95 | AR19: 6611 | AS19: 7012.65 | AT19: 7103.32 | AU19: 8892.6 | AV19: 9014.5 | AW19: 8000.3 | AX19: 7889.3 | AY19: 7297.55 | AZ19: 9345.65 | BA19: 8120.5 | BB19: 8238.3 | BC19: 8333.35 | BD19: 8578.25 | BE19: 9308.6 | BF19: 8556.5 | BG19: 8543.79 | BH19: 8066.65 | BI19: 9293.2 | BJ19: 7589.05 | BK19: 6448.25 | BL19: 7737.85 | BM19: 7703.95 | BN19: 8439.25 | BO19: 8392.85 | BP19: 8939.2 | BQ19: 8140.8 | BR19: 9187.25 | BS19: 8415.9 | BT19: 9091.1 | BU19: 7688.3 | BV19: 8863.05 | BW19: 11081.3 | BX19: 14521.3 | BY19: 14153.4 | BZ19: 8134.8 | CA19: 7554.94 | CB19: 9188.34 | CC19: 8493.95 | CD19: 9070.25 | CE19: 8399 | CF19: 8862.75 | CG19: 7919.9 | CH19: 8911.3 | CI19: 10286.75 | CJ19: 8275.4 | CK19: 9250.75 | CL19: 11085.2 | CM19: 11012.05 | CN19: 9972.6 | CO19: 8693.55 | CP19: 9039.4 | CQ19: 9995.65 | CR19: 9477.05 | CS19: 7476.15 | CT19: 8642.8 | CU19: 9554.25 | CV19: 8725.7 | CW19: 8252.8 | CX19: 7998.75 | CY19: 8545.5 | CZ19: 8342.8 | DA19: 7460.55 | DB19: 8768.3 | DC19: 7714.15 | DD19: 8739.25 | DE19: 7997.95 | DF19: 8306.75 | DG19: 8649.3 | DH19: 8614.4 | DI19: 8814.45 | DJ19: 6372.4 | DK19: 7300.95 | DL19: 8971.3 | DM19: 7010.95 | DN19: 8107.1 | DO19: 8953.4 | DP19: 10795.85 | DQ19: 9373 | DR19: 8826.64 | DS19: 8433.45 | DT19: 7855.1 | DU19: 7912.45 | DV19: 8064 | DW19: 10620.7 | DX19: 10231 | DY19: 10996.95 | DZ19: 12596.65 | EA19: 6657.35 | EB19: 7211.85 | EC19: 8138.8 | ED19: 8705.3 | EE19: 7484.8 | EF19: 7923.5 | EG19: 7529.35 | EH19: 7516.1 | EI19: 8941.2 | EJ19: 6997.75 | EK19: 8299.95 | EL19: 8466.15 | EM19: 8486.55 | EN19: 8988.8 | EO19: 9747.8 | EP19: 8000.3 | EQ19: 9237.5 | ER19: 7584.25 | ES19: 7120.6 | ET19: 7070.15 | EU19: 7901.15 | EV19: 6429.6 | EW19: 8847.65 | EX19: 7678.95 | EY19: 7484.55 | EZ19: 7502 | FA19: 6629.05 | FB19: 8360.3 | FC19: 10341.05 | FD19: 9799.55 | FE19: 9341.65 | FF19: 8385.35 | FG19: 8149.35 | FH19: 9578.45 | FI19: 8123.95 | FJ19: 9047.55 | FK19: 9531.7 | FL19: 7750.5 | FM19: 7835.8 | FN19: 9732.45 | FO19: 8106.75 | FP19: 9485.85 | FQ19: 9273.95 | FR19: 9084.65 | FS19: 8032.95 | FT19: 8316.8 | FU19: 9528.4 | FV19: 9843.8 | FW19: 9754.3 | FX19: 11417 | FY19: 12823.6 | FZ19: 15005.2 | GA19: 6649.5 | GB19: 8664.55 | GC19: 7727.15 | GD19: 7746.9 | GE19: 7726.95 | GF19: 8190.7 | GG19: 8179.81 | GH19: 6742.66 | GI19: 7405.69 | GJ19: 8523.1 | GK19: 9346.88 | GL19: 8505.8 | GM19: 11301.95 | GN19: 10277.7 | GO19: 8486.03 | GP19: 9188.35 | GQ19: 10574.4 | GR19: 10128 | GS19: =EQ19 -> 9237.5 | GT19: WET | GU19: Weekly margins
C20: DRY | D20: 10242 | E20: 9942.6 | F20: 11182.35 | G20: 11567.65 | H20: 10095.3 | I20: 8741.75 | J20: 9032.8 | K20: 9003.3 | L20: 9440.55 | M20: 9712.6 | N20: 10103.8 | O20: 10931.9 | P20: 14245.2 | Q20: 10843.25 | R20: 10892.35 | S20: 10987.1 | T20: 10512.1 | U20: 11368.6 | V20: 11266.1 | W20: 12198.85 | X20: 11502.35 | Y20: 16405.5 | Z20: 13674.2 | AA20: 10382.35 | AB20: 10367.55 | AC20: 11883.7 | AD20: 10654.65 | AE20: 12029.45 | AF20: 14136.89 | AG20: 12328.55 | AH20: 10598.45 | AI20: 10135.2 | AJ20: 13418.1 | AK20: 10784.7 | AL20: 13326.2 | AM20: 18240.4 | AN20: 15776.9 | AO20: 13345.8 | AP20: 14922.7 | AQ20: 14778.05 | AR20: 11352 | AS20: 13317.1 | AT20: 12059.55 | AU20: 16241.45 | AV20: 13282.3 | AW20: 14507.75 | AX20: 11712.7 | AY20: 12414.6 | AZ20: 14896.75 | BA20: 14687.7 | BB20: 12843.8 | BC20: 14321.05 | BD20: 15595.75 | BE20: 14993.6 | BF20: 12996.15 | BG20: 14501.5 | BH20: 14146.6 | BI20: 13228.85 | BJ20: 12876.45 | BK20: 11249.4 | BL20: 12236.25 | BM20: 13475.75 | BN20: 13314.7 | BO20: 13119.6 | BP20: 13913.05 | BQ20: 12483.95 | BR20: 15478.25 | BS20: 14312.8 | BT20: 13529.75 | BU20: 13313.55 | BV20: 14155.77 | BW20: 20143.15 | BX20: 21790.2 | BY20: 18175.1 | BZ20: 13797.2 | CA20: 10963.6 | CB20: 13319.25 | CC20: 12119 | CD20: 10929.5 | CE20: 12594.55 | CF20: 15994.3 | CG20: 13539.55 | CH20: 13320.6 | CI20: 17718.25 | CJ20: 13154.2 | CK20: 13219.45 | CL20: 15457.85 | CM20: 17401.15 | CN20: 15386.75 | CO20: =12591.7+1250 -> 13841.7 | CP20: 12852.9 | CQ20: 14512.25 | CR20: 14508.9 | CS20: 12015.95 | CT20: 15420.35 | CU20: 14043.1 | CV20: 12795.4 | CW20: 13974.1 | CX20: 12260.05 | CY20: 11036.35 | CZ20: 13101.7 | DA20: 10706.35 | DB20: 15479.55 | DC20: 13064.9 | DD20: 13028.8 | DE20: 13949.8 | DF20: 12276.27 | DG20: 14731.5 | DH20: 16259.48 | DI20: 14118.2 | DJ20: 11825.05 | DK20: 12481.5 | DL20: 13768 | DM20: 12183.7 | DN20: 14519.5 | DO20: 14507.4 | DP20: 16896.45 | DQ20: 16787.4 | DR20: 13686.59 | DS20: 12126 | DT20: 10598.65 | DU20: 11982.8 | DV20: 12768.45 | DW20: 19233.2 | DX20: 17887.4 | DY20: 17577.5 | DZ20: 18970.75 | EA20: 12044.45 | EB20: 12193.8 | EC20: 12128.4 | ED20: 12352.6 | EE20: 12210.1 | EF20: 13186 | EG20: 12753.2 | EH20: 12024.25 | EI20: 14104.65 | EJ20: 12371.25 | EK20: 13675.05 | EL20: 14754.75 | EM20: 10338.2 | EN20: 13227.5 | EO20: 15640.75 | EP20: 12059.3 | EQ20: 11175 | ER20: 11236.25 | ES20: 9983.3 | ET20: 10336.6 | EU20: 13716.87 | EV20: 10011.2 | EW20: 14183.55 | EX20: 11261.75 | EY20: 10911.2 | EZ20: 10572.25 | FA20: 9637.35 | FB20: 12997.83 | FC20: 14759.85 | FD20: 15141.75 | FE20: 13653.35 | FF20: 11542.6 | FG20: 14328 | FH20: 13229.6 | FI20: 12607 | FJ20: 12167.8 | FK20: 13275.3 | FL20: 11458.45 | FM20: 12444.2 | FN20: 15282.7 | FO20: 13721.24 | FP20: 15688.55 | FQ20: 14876.2 | FR20: 12578.75 | FS20: 12850.8 | FT20: 12278.8 | FU20: 14655.55 | FV20: 16227.45 | FW20: 17868.6 | FX20: 21329.15 | FY20: 17941.7 | FZ20: 26554.9 | GA20: 10202.1 | GB20: 12885.15 | GC20: 11655.5 | GD20: 13164.1 | GE20: 12260.25 | GF20: 13686.1 | GG20: 14049.96 | GH20: 11964.94 | GI20: 12819.66 | GJ20: 14396.25 | GK20: 13386.57 | GL20: 13885.5 | GM20: 19392 | GN20: 17805.05 | GO20: 15188.44 | GP20: 13433 | GQ20: 16169 | GR20: 15355.8 | GS20: =EQ20 -> 11175 | GT20: DRY | GU20: Dry % | GV20: =DRY!AG7 -> 0.73008401
B21: Site total | D21: =SUM(D19:D20) -> 16097.15 | E21: =SUM(E19:E20) -> 15689.6 | F21: =SUM(F19:F20) -> 17259.5 | G21: =SUM(G19:G20) -> 17486.55 | H21: =SUM(H19:H20) -> 15766.8 | I21: =SUM(I19:I20) -> 13092.25 | J21: =SUM(J19:J20) -> 13968.9 | K21: =SUM(K19:K20) -> 13507.4 | ... GR21: =SUM(GR19:GR20) -> 25483.8 | GS21: =SUM(GS19+GS20) -> 20412.5 | GT21: =B19 -> BELL & CROWN | GU21: Dry % (avg) | GV21: =DRY!AH7 -> 0.69824571 | GW21: =AVERAGE(ES21:GR21) -> 22701.044 | GX21: =AVERAGE(FS21:GR21) -> 24288.25 | GY21: =AVERAGE(GF21:GR21) -> 23721.795 | GZ21: =AVERAGE(GN21:GR21) -> 25321.154 | HA21: =MAX(D21:GR21) -> 41560.1
B22: vs last week % | E22: =SUM(E21-D21) -> -407.55 | F22: =SUM(F21-E21) -> 1569.9 | G22: =SUM(G21-F21) -> 227.05 | H22: =SUM(H21-G21) -> -1719.75 | I22: =SUM(I21-H21) -> -2674.55 | J22: =SUM(J21-I21) -> 876.65 | K22: =SUM(K21-J21) -> -461.5 | L22: =SUM(L21-K21) -> 603.9 | ... DH22: =SUM(DH21-DG21) -> 1493.08 | DI22: =SUM(DI21-DH21)/DH21 -> -0.078042911 | DJ22: =SUM(DJ21-DI21)/DI21 -> -0.2064829 | DK22: =SUM(DK21-DJ21)/DJ21 -> 0.087100116 | DL22: =SUM(DL21-DK21)/DK21 -> 0.14946834 | DM22: =SUM(DM21-DL21)/DL21 -> -0.15588211 | DN22: =SUM(DN21-DM21)/DM21 -> 0.17879722 | DO22: =SUM(DO21-DN21)/DN21 -> 0.036868111 | DP22: =SUM(DP21-DO21)/DO21 -> 0.18036469 | ... GK22: =SUM(GK21-GJ21)/GJ21 -> -0.0081110503 | GL22: =(GL21-GK21)/GK21 -> -0.015050509 | GM22: =(GM21-GL21)/GL21 -> 0.37079803 | GN22: =(GN21-GM21)/GM21 -> -0.08507214 | GO22: =(GO21-GN21)/GN21 -> -0.15697466 | GP22: =(GP21-GO21)/GO21 -> -0.044483361 | GQ22: =(GQ21-GP21)/GP21 -> 0.18221945 | GR22: =(GR21-GQ21)/GQ21 -> -0.047099471 | GU22: Labour % | GV22: =LABOUR!AG9 -> 0.3329619
B23: Same week last year | BD23: =D21 -> 16097.15 | BE23: =E21 -> 15689.6 | BF23: =F21 -> 17259.5 | BG23: =G21 -> 17486.55 | BH23: =H21 -> 15766.8 | BI23: =I21 -> 13092.25 | BJ23: =J21 -> 13968.9 | BK23: =K21 -> 13507.4 | ... GL23: =EL21 -> 23220.9 | GM23: =EL21 -> 23220.9 | GN23: =EM21 -> 18824.75 | GO23: =EN21 -> 22216.3 | GP23: =EO21 -> 25388.55 | GQ23: =EP21 -> 20059.6 | GR23: =EQ21 -> 20412.5 | GT23: Same week last year
B24: vs SWLY % | BD24: =(BD21-BD23)/BD23 -> 0.50175652 | BE24: =(BE21-BE23)/BE23 -> 0.54893688 | BF24: =(BF21-BF23)/BF23 -> 0.24874127 | BG24: =(BG21-BG23)/BG23 -> 0.3178866 | BH24: =(BH21-BH23)/BH23 -> 0.40886229 | BI24: =(BI21-BI23)/BI23 -> 0.72025817 | BJ24: =(BJ21-BJ23)/BJ23 -> 0.46507599 | BK24: =(BK21-BK23)/BK23 -> 0.31021884 | ... GR24: =(GR21-GR23)/GR23 -> 0.24844091 | GT24: YoY LFL %
A26: DOG & GUN | B26: DOG & GUN | C26: WET | D26: 6504.4 | E26: 4434.7 | F26: 4188.85 | G26: 5809.75 | H26: 5097.6 | I26: 4095.3 | J26: 4810.89 | K26: 4312.8 | L26: 3939 | M26: 3622.65 | N26: 3736.35 | O26: 3787.65 | P26: 3492.7 | Q26: 3176.05 | R26: 3084.6 | S26: 3166.25 | T26: 3064.75 | U26: 3749.15 | V26: 4084.35 | W26: 4529.95 | X26: 4050.7 | Y26: 5745.7 | Z26: 4465.55 | AA26: 3308.55 | AB26: 4246.8 | AC26: 4228.45 | AD26: 4722.85 | AE26: 3835.75 | AF26: 5626.5 | AG26: 3569.75 | AH26: 4259.95 | AI26: 3693.75 | AJ26: 4189.2 | AK26: 4355.35 | AL26: 4006.6 | AM26: 4286.55 | AN26: 3751.5 | AO26: 4437.8 | AP26: 4572.95 | AQ26: 4301.75 | AR26: 4829.6 | AS26: 4821.4 | AT26: 4125.7 | AU26: 4628.6 | AV26: 5090.9 | AW26: 4438 | AX26: 5538.75 | AY26: 4766.95 | AZ26: 4801.05 | BA26: 4217.4 | BB26: 5224.75 | BC26: 5683.05 | BD26: 4373.95 | BE26: 4362.35 | BF26: 4386.85 | BG26: 5608.15 | BH26: 4950.95 | BI26: 5247.5 | BJ26: 4848 | BK26: 5293.15 | BL26: 4656 | BM26: 4855.05 | BN26: 4421.4 | BO26: 4409.25 | BP26: 5852.05 | BQ26: 5285.25 | BR26: 4645.55 | BS26: 4265.15 | BT26: 4677.85 | BU26: 4458.55 | BV26: 5153.85 | BW26: 3420.1 | BX26: 6051.8 | BY26: 6460.05 | BZ26: 4133.55 | CA26: 5681.05 | CB26: 5066.9 | CC26: 4991.55 | CD26: 5522.12 | CE26: 5391.1 | CF26: 5648.3 | CG26: 6563.8 | CH26: 4581.74 | CI26: 5184.05 | CJ26: 4244.05 | CK26: 5352.3 | CL26: 7304.75 | CM26: 5932.3 | CN26: 5520.95 | CO26: 6286.45 | CP26: 5656.5 | CQ26: 5512.65 | CR26: 6235.75 | CS26: 6173.05 | CT26: 5387.45 | CU26: 6115.95 | CV26: 5239.45 | CW26: 6073.25 | CX26: 5365.7 | CY26: 6292.85 | CZ26: 4879.25 | DA26: 5682.8 | DB26: 6614.25 | DC26: 5274.75 | DD26: 6811.6 | DE26: 4847.95 | DF26: 5093.7 | DG26: 4641.45 | DH26: 4840.6 | DI26: 4322.3 | DJ26: 4307.2 | DK26: 4256.15 | DL26: 5059.15 | DM26: 5295.8 | DN26: 4169.8 | DO26: 5783.3 | DP26: 5457.7 | DQ26: 5108.65 | DR26: 4986.75 | DS26: 4684.2 | DT26: 4425.9 | DU26: 5216.5 | DV26: 5025.65 | DW26: 4375.15 | DX26: 5220.3 | DY26: 4798.1 | DZ26: 8193.1 | EA26: 5683.05 | EB26: 4080.6 | EC26: 5121.42 | ED26: 6064.37 | EE26: 5084.35 | EF26: 5160.65 | EG26: 5394.15 | EH26: 6483.55 | EI26: 5587.25 | EJ26: 5653.15 | EK26: 5685.15 | EL26: 5728.3 | EM26: 5556 | EN26: 5497.55 | EO26: 6358.8 | EP26: 6167.65 | EQ26: 6409.4 | ER26: 5565.3 | ES26: 5627.45 | ET26: 5463.35 | EU26: 7212.25 | EV26: 5363.65 | EW26: 5533.1 | EX26: 7012.85 | EY26: 7818.65 | EZ26: 6728 | FA26: 7755.8 | FC26: 8189.05 | FD26: 6070.5 | FE26: 6877.35 | FF26: 6216.35 | FG26: 5664.5 | FH26: 5752.2 | FI26: 5367.75 | FJ26: 5752.95 | FK26: 5602.2 | FL26: 5875.05 | FM26: 5978.05 | FN26: 5835.25 | FO26: 5737.35 | FP26: 5459.15 | FQ26: 5628.75 | FR26: 5951.3 | FS26: 6002.05 | FT26: 5061.35 | FU26: 6052.1 | FV26: 6274.2 | FW26: 5646.8 | FX26: 5358.2 | FY26: 4708.7 | FZ26: 7662.2 | GA26: 0 | GB26: 0 | GC26: 3652.8 | GD26: 6829.9 | GE26: 5449.9 | GF26: 5244.75 | GG26: 5824.23 | GH26: 7038 | GI26: 7262.55 | GJ26: 6132.4 | GK26: 8099.55 | GL26: 6856.64 | GM26: 5825.25 | GN26: 6709.85 | GO26: 6648.15 | GP26: 7592.11 | GQ26: 6771.3 | GR26: 7059.35 | GS26: =EQ26 -> 6409.4 | GT26: WET | GU26: Weekly margins
C27: DRY | D27: 8365.7 | E27: 6180.15 | F27: 6056.75 | G27: 8865.24 | H27: 7523.75 | I27: 6999.57 | J27: 6760.25 | K27: 6759.9 | L27: 6932.75 | M27: 7379.5 | N27: 7444.9 | O27: 7186.95 | P27: 6028.8 | Q27: 7119.05 | R27: 7285.35 | S27: 6856.55 | T27: 6151.8 | U27: 6597.45 | V27: 6558.35 | W27: 5888.85 | X27: 4370.25 | Y27: 6909 | Z27: 6992.75 | AA27: 5985.7 | AB27: 6530.5 | AC27: 7324 | AD27: 8689 | AE27: 7416.49 | AF27: 6979.34 | AG27: 7158.45 | AH27: 7202 | AI27: 7223.25 | AJ27: 7908.45 | AK27: 7957.5 | AL27: 7170.95 | AM27: 8314.7 | AN27: 7630.75 | AO27: 7930.7 | AP27: 8421.59 | AQ27: 8203.2 | AR27: 9334.35 | AS27: 9382.73 | AT27: 8468.35 | AU27: 9206 | AV27: 9150.65 | AW27: 9363.65 | AX27: 9880.3 | AY27: 9845 | AZ27: 10644.95 | BA27: 9901.1 | BB27: 12424.85 | BC27: 11448 | BD27: 10404.8 | BE27: 8773.6 | BF27: 7939.8 | BG27: 8703.72 | BH27: 10449.2 | BI27: 8783.95 | BJ27: 8388 | BK27: 8976 | BL27: 8360.42 | BM27: 8756.55 | BN27: 7552.2 | BO27: 8968.6 | BP27: 9701.3 | BQ27: 6949.4 | BR27: 9248.5 | BS27: 8603.15 | BT27: 7365.4 | BU27: 9042.3 | BV27: 8617.35 | BW27: 7891.85 | BX27: 9049.15 | BY27: 8947.7 | BZ27: 8475.2 | CA27: 8782.45 | CB27: 6881.8 | CC27: 10423.45 | CD27: 9363.2 | CE27: 9981.6 | CF27: 10943.4 | CG27: 11057.3 | CH27: 9396.1 | CI27: 10263.6 | CJ27: 10276.9 | CK27: 10178.1 | CL27: 12398.14 | CM27: 10418.6 | CN27: 9376.1 | CO27: 9897.8 | CP27: 10478.4 | CQ27: 11247.65 | CR27: 10608.2 | CS27: 10676 | CT27: 9644.98 | CU27: 12253.85 | CV27: 10624.9 | CW27: 11106.7 | CX27: 10005.9 | CY27: 10785.82 | CZ27: 10006.35 | DA27: 13192.4 | DB27: 12748.8 | DC27: 9962.8 | DD27: 11066.95 | DE27: 9704 | DF27: 9513.1 | DG27: 10084.68 | DH27: 10859.45 | DI27: 8848.75 | DJ27: 8270.75 | DK27: 7919.25 | DL27: 10281.45 | DM27: 10860.5 | DN27: 8800.3 | DO27: 10628.9 | DP27: 10411.85 | DQ27: 10206.95 | DR27: 8421.05 | DS27: 8370.15 | DT27: 8440.2 | DU27: 9845.5 | DV27: 9430.55 | DW27: 9568.85 | DX27: 9379.7 | DY27: 7697.9 | DZ27: 11911.7 | EA27: 10086.9 | EB27: 8101.55 | EC27: 9563.65 | ED27: 10712.75 | EE27: 10695.5 | EF27: 10074 | EG27: 9635 | EH27: 11261.5 | EI27: 9612.6 | EJ27: 11663.45 | EK27: 9971.5 | EL27: 11355.1 | EM27: 9800.5 | EN27: 9623.35 | EO27: 10285.25 | EP27: 10838.3 | EQ27: 10593.35 | ER27: 8881.36 | ES27: 9413.25 | ET27: 10157.85 | EU27: 13109.75 | EV27: 11436.2 | EW27: 11736 | EX27: 10764.25 | EY27: 12349.25 | EZ27: 10953.85 | FA27: 13241.25 | FC27: 10764.05 | FD27: 10417.95 | FE27: 12197.7 | FF27: 10733.85 | FG27: 10620.25 | FH27: 11389.1 | FI27: 9522.1 | FJ27: 10269.25 | FK27: 10389.7 | FL27: 10490.25 | FM27: 10166.25 | FN27: 12185.25 | FO27: 11181 | FP27: 13862.5 | FQ27: 12291.1 | FR27: 11966.55 | FS27: 12202.75 | FT27: 10274.25 | FU27: 11764 | FV27: 15045.45 | FW27: 13107.25 | FX27: 9896 | FY27: 9374.5 | FZ27: 14643 | GA27: 0 | GB27: 0 | GC27: 7664.5 | GD27: 14211.25 | GE27: 11922 | GF27: 9765 | GG27: 12761.92 | GH27: 12830.25 | GI27: 13959.5 | GJ27: 14816 | GK27: 16457.5 | GL27: 14690.16 | GM27: 13274.25 | GN27: 15322 | GO27: 14464.25 | GP27: 14995.54 | GQ27: 15237 | GR27: 15687.25 | GS27: =EQ27 -> 10593.35 | GT27: DRY | GU27: Dry % | GV27: =DRY!AG12 -> 0.79063481
B28: Site total | D28: =SUM(D26:D27) -> 14870.1 | E28: =SUM(E26:E27) -> 10614.85 | F28: =SUM(F26:F27) -> 10245.6 | G28: =SUM(G26:G27) -> 14674.99 | H28: =SUM(H26:H27) -> 12621.35 | I28: =SUM(I26:I27) -> 11094.87 | J28: =SUM(J26:J27) -> 11571.14 | K28: =SUM(K26:K27) -> 11072.7 | ... FA28: =SUM(FA26:FA27) -> 20997.05 | FB28: 21185 | FC28: =SUM(FC26:FC27) -> 18953.1 | FD28: =SUM(FD26:FD27) -> 16488.45 | FE28: =SUM(FE26:FE27) -> 19075.05 | FF28: =SUM(FF26:FF27) -> 16950.2 | FG28: =SUM(FG26:FG27) -> 16284.75 | FH28: =SUM(FH26:FH27) -> 17141.3 | FI28: =SUM(FI26:FI27) -> 14889.85 | FJ28: =SUM(FJ26:FJ27) -> 16022.2 | ... GR28: =SUM(GR26:GR27) -> 22746.6 | GS28: =SUM(GS26+GS27) -> 17002.75 | GT28: =B26 -> DOG & GUN | GU28: Dry % (avg) | GV28: =DRY!AH12 -> 0.70810514 | GW28: =AVERAGE(ES28:GR28) -> 17719.12 | GX28: =AVERAGE(FS28:GR28) -> 17851.073 | GY28: =AVERAGE(GF28:GR28) -> 20871.135 | GZ28: =AVERAGE(GN28:GR28) -> 22097.36 | HA28: =MAX(D28:GR28) -> 24557.05
B29: vs last week % | E29: =SUM(E28-D28) -> -4255.25 | F29: =SUM(F28-E28) -> -369.25 | G29: =SUM(G28-F28) -> 4429.39 | H29: =SUM(H28-G28) -> -2053.64 | I29: =SUM(I28-H28) -> -1526.48 | J29: =SUM(J28-I28) -> 476.27 | K29: =SUM(K28-J28) -> -498.44 | L29: =SUM(L28-K28) -> -200.95 | ... DH29: =SUM(DH28-DG28) -> 973.92 | DI29: =SUM(DI28-DH28)/DH28 -> -0.16108229 | DJ29: =SUM(DJ28-DI28)/DI28 -> -0.045030578 | DK29: =SUM(DK28-DJ28)/DJ28 -> -0.03200442 | DL29: =SUM(DL28-DK28)/DK28 -> 0.25996682 | DM29: =SUM(DM28-DL28)/DL28 -> 0.053172627 | DN29: =SUM(DN28-DM28)/DM28 -> -0.197211 | DO29: =SUM(DO28-DN28)/DN28 -> 0.26538731 | DP29: =SUM(DP28-DO28)/DO28 -> -0.033063818 | ... FZ29: =SUM(FZ28-FY28)/FY28 -> 0.58381618 | GD29: =SUM(GD28-GC28)/GC28 -> 0.85920228 | GE29: =SUM(GE28-GD28)/GD28 -> -0.17438448 | GF29: =SUM(GF28-GE28)/GE28 -> -0.13597534 | GG29: =SUM(GG28-GF28)/GF28 -> 0.23827179 | GH29: =SUM(GH28-GG28)/GG28 -> 0.068981473 | GI29: =SUM(GI28-GH28)/GH28 -> 0.068138865 | GJ29: =SUM(GJ28-GI28)/GI28 -> -0.012894607 | GK29: =SUM(GK28-GJ28)/GJ28 -> 0.17226375 | GL29: =(GL28-GK28)/GK28 -> -0.12258191 | GM29: =(GM28-GL28)/GL28 -> -0.11358067 | GN29: =(GN28-GM28)/GM28 -> 0.1535302 | GO29: =(GO28-GN28)/GN28 -> -0.041732764 | GP29: =(GP28-GO28)/GO28 -> 0.069875997 | GQ29: =(GQ28-GP28)/GP28 -> -0.025648972 | GR29: =(GR28-GQ28)/GQ28 -> 0.033546435 | GU29: Labour % | GV29: =LABOUR!AG15 -> 0.34207806
B30: Same week last year | BD30: =D28 -> 14870.1 | BE30: =E28 -> 10614.85 | BF30: =F28 -> 10245.6 | BG30: =G28 -> 14674.99 | BH30: =H28 -> 12621.35 | BI30: =I28 -> 11094.87 | BJ30: =J28 -> 11571.14 | BK30: =K28 -> 11072.7 | ... GL30: =EL28 -> 17083.4 | GM30: =EL28 -> 17083.4 | GN30: =EM28 -> 15356.5 | GO30: =EN28 -> 15120.9 | GP30: =EO28 -> 16644.05 | GQ30: =EP28 -> 17005.95 | GR30: =EQ28 -> 17002.75 | GT30: Same week last year
B31: vs SWLY % | BD31: =(BD28-BD30)/BD30 -> -0.0061432001 | BE31: =(BE28-BE30)/BE30 -> 0.23750689 | BF31: =(BF28-BF30)/BF30 -> 0.20311646 | BG31: =(BG28-BG30)/BG30 -> -0.02474414 | BH31: =(BH28-BH30)/BH30 -> 0.22016662 | BI31: =(BI28-BI30)/BI30 -> 0.26467908 | BJ31: =(BJ28-BJ30)/BJ30 -> 0.14388038 | BK31: =(BK28-BK30)/BK30 -> 0.28867846 | ... FZ31: =(FZ28-FZ30)/FZ30 -> 0.1094465 | GC31: =(GC28-GC30)/GC30 -> -0.22933292 | GD31: =(GD28-GD30)/GD30 -> 0.25415745 | GE31: =(GE28-GE30)/GE30 -> 0.10089133 | GF31: =(GF28-GF30)/GF30 -> -0.0147624 | GG31: =(GG28-GG30)/GG30 -> 0.2366734 | GH31: =(GH28-GH30)/GH30 -> 0.11965027 | GI31: =(GI28-GI30)/GI30 -> 0.39620128 | GJ31: =(GJ28-GJ30)/GJ30 -> 0.20972939 | ... GR31: =(GR28-GR30)/GR30 -> 0.33781888 | GT31: YoY LFL %
A33: QUEENS HEAD | B33: QUEENS HEAD | C33: WET | AL33: 7490.8 | AM33: 12298.9 | AN33: 7288.45 | AO33: 7771.8 | AP33: 7738.4 | AQ33: 9302.9 | AR33: 7771.8 | AS33: 7557.3 | AT33: 10514.5 | AU33: 8800.75 | AV33: 6869 | AW33: 7664.15 | AX33: 7635.55 | AY33: 9050.2 | AZ33: 6366.6 | BA33: 7200.75 | BB33: 5984.85 | BC33: 5949 | BD33: 7243.25 | BE33: 8161.45 | BF33: 7401.9 | BG33: 7836.25 | BH33: 8668.6 | BI33: 7142.17 | BJ33: 5282.9 | BK33: 5477.05 | BL33: 5098.75 | BM33: 5881.45 | BN33: 5811.2 | BO33: 6545.65 | BP33: 7004.85 | BQ33: 7228.7 | BR33: 8880.45 | BS33: 6195.45 | BT33: 6853.8 | BU33: 6444.25 | BV33: 7303.5 | BW33: 7888.7 | BX33: 10267.95 | BY33: 11430.2 | BZ33: 6757.8 | CA33: 5429.85 | CB33: 6117.9 | CC33: 6304.7 | CD33: 6505.45 | CE33: 6972.6 | CF33: 7808.35 | CG33: 6151.05 | CH33: 7340.9 | CI33: 8600.15 | CJ33: 8330.45 | CK33: 7699.35 | CL33: 11327.95 | CM33: 9321.2 | CN33: 8787.9 | CO33: 7804.8 | CP33: 8550.7 | CQ33: 8622.3 | CR33: 9842.05 | CS33: 7406.55 | CT33: 9921.8 | CU33: 9771.53 | CV33: 8042.35 | CW33: 8819.25 | CX33: 8830.2 | CY33: 9135.6 | CZ33: 7209.25 | DA33: 7440.65 | DB33: 6984.1 | DC33: 8174.95 | DD33: 7752.2 | DE33: 9486.15 | DF33: 8034.65 | DG33: 9357.4 | DH33: 9846.2 | DI33: 7065.25 | DJ33: 5861.35 | DK33: 7192.1 | DL33: 8052.25 | DM33: 7377.5 | DN33: 6723.55 | DO33: 6442.6 | DP33: 5067.4 | DQ33: 7924.6 | DR33: 6500.5 | DS33: 8741.7 | DT33: 6230.85 | DU33: 7186.75 | DV33: 5471.85 | DW33: 8598.2 | DX33: 8279.97 | DY33: 11636.9 | DZ33: 12359 | EA33: 6407.55 | EB33: 6634.05 | EC33: 6841.8 | ED33: 7245.2 | EE33: 6077.8 | EF33: 6905.55 | EG33: 6426.35 | EH33: 8860.7 | EI33: 7674 | EJ33: 6626.3 | EK33: 7215.1 | EL33: 9108.95 | EM33: 8252.4 | EN33: 8925.35 | EO33: 11001.1 | EP33: 8503.92 | EQ33: 8503.45 | ER33: 8115.4 | ES33: 7085.1 | ET33: 8176.35 | EU33: 9653.35 | EV33: 5933.35 | EW33: 7778.75 | EX33: 9781.15 | EY33: 9517.7 | EZ33: 8265.05 | FA33: 7321.45 | FB33: 7881.5 | FC33: 7949.4 | FD33: 8548.45 | FE33: 8745.25 | FF33: 10726.05 | FG33: 8998.8 | FH33: 8937.05 | FI33: 6124.95 | FJ33: 7415.1 | FK33: 7205.3 | FL33: 7878.8 | FM33: 7286.7 | FN33: 9338.25 | FO33: 4584.45 | FP33: 7911.1 | FQ33: 6289.2 | FR33: 6825.55 | FS33: 7486.4 | FT33: 7315.6 | FU33: 7427.6 | FV33: 7409.6 | FW33: 8082.25 | FX33: 7446.5 | FY33: 9694.8 | FZ33: 10939.85 | GA33: 0 | GB33: 0 | GC33: 0 | GD33: 0 | GE33: 0 | GF33: 0 | GG33: 0 | GH33: 0 | GI33: 0 | GJ33: 0 | GK33: 0 | GL33: 6297.85 | GM33: 12081.35 | GN33: 10128.7 | GO33: 8361.1 | GP33: 10221.9 | GQ33: 11054.7 | GR33: 9980.1 | GS33: =EQ33 -> 8503.45 | GT33: WET | GU33: Weekly margins
C34: DRY | AL34: 8715 | AM34: 10969.65 | AN34: 9770.7 | AO34: 8603.7 | AP34: 8630.2 | AQ34: 10821 | AR34: 7011.1 | AS34: 8252.2 | AT34: 11019.6 | AU34: 9622.8 | AV34: 7467.2 | AW34: 8851.6 | AX34: 7945.1 | AY34: 11581.9 | AZ34: 7435.6 | BA34: 8058 | BB34: 7355.3 | BC34: 8108 | BD34: 9641.5 | BE34: 8441.8 | BF34: 8401.6 | BG34: 8568.7 | BH34: 9899.6 | BI34: 7967.55 | BJ34: 6515.4 | BK34: 6551.2 | BL34: 6839.6 | BM34: 8011.1 | BN34: 6442.3 | BO34: 7999.8 | BP34: 9645.1 | BQ34: 8985.9 | BR34: 10336.8 | BS34: 8094.7 | BT34: 8244.95 | BU34: 6423.6 | BV34: 8944.3 | BW34: 8853.45 | BX34: 8298.3 | BY34: 9986.9 | BZ34: 7067.35 | CA34: 5145.4 | CB34: 6978.6 | CC34: 6943.2 | CD34: 7649.8 | CE34: 8126.9 | CF34: 10596.5 | CG34: 6602.4 | CH34: 8113.5 | CI34: 11395.05 | CJ34: 9270.35 | CK34: 9709.45 | CL34: 12501.3 | CM34: 12001.9 | CN34: 10740.05 | CO34: 8971.55 | CP34: 10275.2 | CQ34: 9137.6 | CR34: 11162.9 | CS34: 7450.05 | CT34: 11719.05 | CU34: 11339.95 | CV34: 8185.1 | CW34: 12264.75 | CX34: 9129.95 | CY34: 12369 | CZ34: 7706.7 | DA34: 7858.9 | DB34: 7861.2 | DC34: 9429.4 | DD34: 9637.8 | DE34: 10004.3 | DF34: 10339.3 | DG34: 12506.05 | DH34: 11395.15 | DI34: 8142.25 | DJ34: 7426.95 | DK34: 8329.4 | DL34: 9223.55 | DM34: 9614.05 | DN34: 8012.55 | DO34: 8038 | DP34: 5934.65 | DQ34: 9541.6 | DR34: 7417.68 | DS34: 10845.05 | DT34: 6615.9 | DU34: 8628.84 | DV34: 3704.2 | DW34: 8505.71 | DX34: 8932.76 | DY34: 10318 | DZ34: 14146.45 | EA34: 6749.9 | EB34: 9666.15 | EC34: 6958.7 | ED34: 8460.35 | EE34: 8291.3 | EF34: 9308.9 | EG34: 9403.2 | EH34: 10017 | EI34: 9220.15 | EJ34: 8954.9 | EK34: 9097.8 | EL34: 12641.15 | EM34: 9295.35 | EN34: 9782.45 | EO34: 12363.85 | EP34: 9275.2 | EQ34: 8337.75 | ER34: 7514.9 | ES34: 7997.95 | ET34: 8005.95 | EU34: 10311.1 | EV34: 6316.4 | EW34: 9329.3 | EX34: 10297.2 | EY34: 13776.75 | EZ34: 12116.8 | FA34: 8597.85 | FB34: 10407.53 | FC34: 11667.75 | FD34: 11755.9 | FE34: 11285.45 | FF34: 12745.35 | FG34: 12213.4 | FH34: 11544.2 | FI34: 8652.35 | FJ34: 8621.05 | FK34: 8112.8 | FL34: 9228.05 | FM34: 8211.55 | FN34: 8035.6 | FO34: 5115.65 | FP34: 10955.85 | FQ34: 8420.25 | FR34: 7390.8 | FS34: 9720.6 | FT34: 8740.2 | FU34: 8790.6 | FV34: 9990.4 | FW34: 8918.8 | FX34: 7335.95 | FY34: 9506.6 | FZ34: 16422.82 | GA34: 0 | GB34: 0 | GC34: 0 | GD34: 0 | GE34: 0 | GF34: 0 | GG34: 0 | GH34: 0 | GI34: 0 | GJ34: 0 | GK34: 0 | GL34: 6141.06 | GM34: 13099.5 | GN34: 11275.25 | GO34: 10492.35 | GP34: 11630.75 | GQ34: 13829.67 | GR34: 12808.25 | GS34: =EQ34 -> 8337.75 | GT34: DRY | GU34: Dry % | GV34: =DRY!AG42 -> 0.73331626
B35: Site total | AL35: =SUM(AL33:AL34) -> 16205.8 | AM35: =SUM(AM33:AM34) -> 23268.55 | AN35: =SUM(AN33:AN34) -> 17059.15 | AO35: =SUM(AO33:AO34) -> 16375.5 | AP35: =SUM(AP33:AP34) -> 16368.6 | AQ35: =SUM(AQ33:AQ34) -> 20123.9 | AR35: =SUM(AR33:AR34) -> 14782.9 | AS35: =SUM(AS33:AS34) -> 15809.5 | ... GR35: =SUM(GR33:GR34) -> 22788.35 | GS35: =SUM(GS33+GS34) -> 16841.2 | GT35: =B33 -> QUEENS HEAD | GU35: Dry % (avg) | GV35: =DRY!AH42 -> 0.70650322 | GW35: =AVERAGE(ES35:GR35) -> 14421.194 | GX35: =AVERAGE(FS35:GR35) -> 11255.042 | GY35: =AVERAGE(GF35:GR35) -> 11338.656 | GZ35: =AVERAGE(GN35:GR35) -> 21956.554 | HA35: =MAX(D35:GR35) -> 27362.67
B36: vs last week % | AL36: =SUM(AL35-AK35) -> 16205.8 | AM36: =SUM(AM35-AL35) -> 7062.75 | AN36: =SUM(AN35-AM35) -> -6209.4 | AO36: =SUM(AO35-AN35) -> -683.65 | AP36: =SUM(AP35-AO35) -> -6.9 | AQ36: =SUM(AQ35-AP35) -> 3755.3 | AR36: =SUM(AR35-AQ35) -> -5341 | AS36: =SUM(AS35-AR35) -> 1026.6 | ... DH36: =SUM(DH35-DG35) -> -622.1 | DI36: =SUM(DI35-DH35)/DH35 -> -0.28406151 | DJ36: =SUM(DJ35-DI35)/DI35 -> -0.12620089 | DK36: =SUM(DK35-DJ35)/DJ35 -> 0.16805761 | DL36: =SUM(DL35-DK35)/DK35 -> 0.11302387 | DM36: =SUM(DM35-DL35)/DL35 -> -0.016453652 | DN36: =SUM(DN35-DM35)/DM35 -> -0.13273951 | DO36: =SUM(DO35-DN35)/DN35 -> -0.017338373 | DP36: =SUM(DP35-DO35)/DO35 -> -0.2402214 | ... FZ36: =SUM(FZ35-FY35)/FY35 -> 0.42503515 | GM36: =(GM35-GL35)/GL35 -> 1.0243615 | GN36: =(GN35-GM35)/GM35 -> -0.14999097 | GO36: =(GO35-GN35)/GN35 -> -0.11916025 | GP36: =(GP35-GO35)/GO35 -> 0.15907964 | GQ36: =(GQ35-GP35)/GP35 -> 0.13873466 | GR36: =(GR35-GQ35)/GQ35 -> -0.084230382 | GU36: Labour % | GV36: =LABOUR!AG50 -> 0.34123508
B37: Same week last year | BD37: =D35 -> 0 | BE37: =E35 -> 0 | BF37: =F35 -> 0 | BG37: =G35 -> 0 | BH37: =H35 -> 0 | BI37: =I35 -> 0 | BJ37: =J35 -> 0 | BK37: =K35 -> 0 | ... GL37: =EL35 -> 21750.1 | GM37: =EL35 -> 21750.1 | GN37: =EM35 -> 17547.75 | GO37: =EN35 -> 18707.8 | GP37: =EO35 -> 23364.95 | GQ37: =EP35 -> 17779.12 | GR37: =EQ35 -> 16841.2 | GT37: Same week last year
B38: vs SWLY % | BY38: =IFERROR(((BY35-BY37)/BY37),0) -> 0 | BZ38: =IFERROR(((BZ35-BZ37)/BZ37),0) -> 0 | CA38: =IFERROR(((CA35-CA37)/CA37),0) -> 0 | CB38: =IFERROR(((CB35-CB37)/CB37),0) -> 0 | CC38: =IFERROR(((CC35-CC37)/CC37),0) -> 0 | CD38: =IFERROR(((CD35-CD37)/CD37),0) -> 0 | CE38: =IFERROR(((CE35-CE37)/CE37),0) -> 0 | CF38: =IFERROR(((CF35-CF37)/CF37),0) -> 0 | ... FZ38: =IFERROR(((FZ35-FZ37)/FZ37),0) -> 0.032341273 | GM38: =(GM35-GM37)/GM37 -> 0.15773491 | GN38: =(GN35-GN37)/GN37 -> 0.21975467 | GO38: =(GO35-GO37)/GO37 -> 0.0077855226 | GP38: =(GP35-GP37)/GP37 -> -0.064725155 | GQ38: =(GQ35-GQ37)/GQ37 -> 0.39964014 | GR38: =(GR35-GR37)/GR37 -> 0.35313101 | GT38: YoY LFL %
A40: SILVER PLOUGH | B40: SILVER PLOUGH | C40: WET | BH40: 6556.55 | BI40: 7902.45 | BJ40: 6891.1 | BK40: 7034.85 | BL40: 7404.1 | BM40: 6892.3 | BN40: 4555.35 | BO40: 6585.15 | BP40: 6329.2 | BQ40: 7662.6 | BR40: 6599.1 | BS40: 5444.7 | BT40: 6638.95 | BU40: 7082.25 | BV40: 6620.7 | BW40: 6705.2 | BX40: 9306.7 | BY40: 8716.9 | BZ40: 5547.6 | CA40: 6423.5 | CB40: 6680.25 | CC40: 8201.1 | CD40: 7017.15 | CE40: 9070.45 | CF40: 8023.1 | CG40: 8557.25 | CH40: 8003 | CI40: 7957 | CJ40: 7717.55 | CK40: 9472.95 | CL40: 10772.2 | CM40: 8165.1 | CN40: 7549.75 | CO40: 7715.55 | CP40: 7735.2 | CQ40: 8655.5 | CR40: 8268.05 | CS40: 8322.55 | CT40: 8120 | CU40: 8524.67 | CV40: 7848.25 | CW40: 8622.7 | CX40: 8769.25 | CY40: 8581.7 | CZ40: 7714.3 | DA40: 7651.65 | DB40: 8951.72 | DC40: 6914.9 | DD40: 13434.81 | DE40: 9522.8 | DF40: 9754.15 | DG40: 9661.25 | DH40: 9695.4 | DI40: 7478.95 | DJ40: 7893.2 | DK40: 7769.7 | DL40: 8308.3 | DM40: 9048.25 | DN40: 7397.5 | DO40: 7386.35 | DP40: 8318.6 | DQ40: 7463.15 | DR40: 8969.55 | DS40: 7598.85 | DT40: 6734.4 | DU40: 8170.2 | DV40: 6067.4 | DW40: 8625.9 | DX40: 10237 | DY40: 8832.85 | DZ40: 10606.4 | EA40: 7246.6 | EB40: 7776.6 | EC40: 6544.35 | ED40: 6574.3 | EE40: 7181.55 | EF40: 9240.1 | EG40: 8380.35 | EH40: 9043.2 | EI40: 7772.7 | EJ40: 8752.5 | EK40: 9799.85 | EL40: 12284.7 | EM40: 9718.7 | EN40: 11504.8 | EO40: 12051.45 | EP40: 10433.75 | EQ40: 11087.3 | ER40: 9876.25 | ES40: 9733.95 | ET40: 10921.7 | EU40: 10137.75 | EV40: 9285.11 | EW40: 11085.4 | EX40: 9620.05 | EY40: 8916.7 | EZ40: 10147.85 | FA40: 8827.8 | FB40: 8020.85 | FC40: 8721.1 | FD40: 9181.4 | FE40: 8315.2 | FF40: 7990.45 | FG40: 9014.85 | FH40: 8612.95 | FI40: 6882.75 | FJ40: 7318.75 | FK40: 7623.7 | FL40: 7355.9 | FM40: 7384.1 | FN40: 8322.15 | FO40: 9106.65 | FP40: 8739.85 | FQ40: 7848.7 | FR40: 8368.05 | FS40: 7472.65 | FT40: 8212.05 | FU40: 8261.55 | FV40: =4571.3+1630.55 -> 6201.85 | FW40: 9247.75 | FX40: 9585.85 | FY40: 11399.5 | FZ40: 12351.7 | GA40: 7869.3 | GB40: 8046.5 | GC40: 7814.25 | GD40: 7659.05 | GE40: 5637.95 | GF40: 7918.55 | GG40: 8704.9 | GH40: 7097.4 | GI40: =2378.1+6187.89 -> 8565.99 | GJ40: 8609.7 | GK40: 7326.95 | GL40: 6280.75 | GM40: 12116.82 | GN40: 9362.53 | GO40: 7648.52 | GP40: 8145.35 | GQ40: 8358.44 | GR40: 8753.67 | GS40: =EQ40 -> 11087.3 | GT40: WET | GU40: Weekly margins
C41: DRY | BH41: 6692.2 | BI41: 9794.6 | BJ41: 9932.65 | BK41: 9607.1 | BL41: 10037.885 | BM41: 9968.2 | BN41: 7626.3 | BO41: 9017.1 | BP41: 9377.5 | BQ41: 9344.6 | BR41: 9269.85 | BS41: 7458.15 | BT41: 8950.4 | BU41: 7921.7 | BV41: 10104.6 | BW41: 9433.1 | BX41: 11003.29 | BY41: 11056.45 | BZ41: 9186.11 | CA41: 8234.9 | CB41: 9236.25 | CC41: 12705.85 | CD41: 10543.1 | CE41: 12344.5 | CF41: 12978.25 | CG41: 12532.55 | CH41: 11523.05 | CI41: 13137.65 | CJ41: 10541.3 | CK41: 12887.9 | CL41: 15090.2 | CM41: 12333.7 | CN41: 9536.95 | CO41: 10118.4 | CP41: 10318.6 | CQ41: 10693.2 | CR41: 10848.99 | CS41: 9848.9 | CT41: 11802.5 | CU41: 11823.35 | CV41: 11066.2 | CW41: 13479.8 | CX41: 12568.45 | CY41: 10596 | CZ41: 10495.7 | DA41: 10598.3 | DB41: 12324.35 | DC41: 11706.7 | DD41: 9916.9 | DE41: 12673.3 | DF41: 13376.4 | DG41: 13811.8 | DH41: 13157.05 | DI41: 10835.1 | DJ41: 9649.75 | DK41: 11073.6 | DL41: 11813.4 | DM41: 12576.8 | DN41: 10111.45 | DO41: 9818.25 | DP41: 10344.2 | DQ41: 9691.55 | DR41: 12018.9 | DS41: 10989.55 | DT41: 9037.3 | DU41: 10619.4 | DV41: 9798.1 | DW41: 14187.95 | DX41: 14877.65 | DY41: 11828.15 | DZ41: 15330.4 | EA41: 11451.3 | EB41: 13076.4 | EC41: 10565.6 | ED41: 9650.7 | EE41: 9676.6 | EF41: 11056.7 | EG41: 12494.8 | EH41: 12075.25 | EI41: 10117 | EJ41: 12606.25 | EK41: 12154.75 | EL41: 14500.3 | EM41: 10765 | EN41: 13053.4 | EO41: 14363.65 | EP41: 14338.3 | EQ41: 13662.4 | ER41: 11535.8 | ES41: 10444.2 | ET41: 13582.75 | EU41: 15290.23 | EV41: 11418.45 | EW41: 15521.8 | EX41: 11479.35 | EY41: 13962.55 | EZ41: 12958.78 | FA41: 10561.35 | FB41: 11856.05 | FC41: 12370.55 | FD41: 12781.8 | FE41: 13616.4 | FF41: 11553.7 | FG41: 11965.4 | FH41: 14784.1 | FI41: 9661.1 | FJ41: 9583.02 | FK41: 10608 | FL41: 10306.1 | FM41: 11126.2 | FN41: 10565.6 | FO41: 9417.05 | FP41: 11000.7 | FQ41: 11140.05 | FR41: 10716.4 | FS41: 9831.8 | FT41: 10653.4 | FU41: 11014.55 | FV41: =7667.25+236 -> 7903.25 | FW41: 13668.75 | FX41: 12954.2 | FY41: 11240.35 | FZ41: 17649.75 | GA41: 9928.85 | GB41: 11595.95 | GC41: =11160.5+750 -> 11910.5 | GD41: 11947.45 | GE41: 9068.66 | GF41: 13309.35 | GG41: 12346.95 | GH41: 10675.75 | GI41: =2797.1+9674.86 -> 12471.96 | GJ41: 14851.54 | GK41: 11309.75 | GL41: 11177.83 | GM41: 17514.2 | GN41: 14026.82 | GO41: 13562.88 | GP41: 12944.5 | GQ41: 13559.81 | GR41: 14205.78 | GS41: =EQ41 -> 13662.4 | GT41: DRY | GU41: Dry % | GV41: =DRY!AG47 -> 0.74957743
B42: Site total | BH42: =+BH40+BH41 -> 13248.75 | BI42: =+BI40+BI41 -> 17697.05 | BJ42: =+BJ40+BJ41 -> 16823.75 | BK42: =+BK40+BK41 -> 16641.95 | BL42: =+BL40+BL41 -> 17441.985 | BM42: =+BM40+BM41 -> 16860.5 | BN42: =+BN40+BN41 -> 12181.65 | BO42: =+BO40+BO41 -> 15602.25 | ... GD42: =+GD40+GD41 -> 19606.5 | GE42: 16063 | GF42: =+GF40+GF41 -> 21227.9 | GG42: =+GG40+GG41 -> 21051.85 | GH42: =+GH40+GH41 -> 17773.15 | GI42: =+GI40+GI41 -> 21037.95 | GJ42: =+GJ40+GJ41 -> 23461.24 | GK42: =+GK40+GK41 -> 18636.7 | GL42: =+GL40+GL41 -> 17458.58 | GM42: =+GM40+GM41 -> 29631.02 | ... GR42: =+GR40+GR41 -> 22959.45 | GS42: =SUM(GS40+GS41) -> 24749.7 | GT42: =B40 -> SILVER PLOUGH | GU42: Dry % (avg) | GV42: =DRY!AH47 -> 0.7177138 | GW42: =AVERAGE(ES42:GR42) -> 20713.19 | GX42: =AVERAGE(FS42:GR42) -> 20820.403 | GY42: =AVERAGE(GF42:GR42) -> 21603.592 | GZ42: =AVERAGE(GN42:GR42) -> 22113.66 | HA42: =MAX(D42:GR42) -> 30001.45
B43: vs last week % | BH43: =SUM(BH42-BG42) -> 13248.75 | BI43: =SUM(BI42-BH42) -> 4448.3 | BJ43: =SUM(BJ42-BI42) -> -873.3 | BK43: =SUM(BK42-BJ42) -> -181.8 | BL43: =SUM(BL42-BK42) -> 800.035 | BM43: =SUM(BM42-BL42) -> -581.485 | BN43: =SUM(BN42-BM42) -> -4678.85 | BO43: =SUM(BO42-BN42) -> 3420.6 | ... DH43: =SUM(DH42-DG42) -> -620.6 | DI43: =SUM(DI42-DH42)/DH42 -> -0.19859577 | DJ43: =SUM(DJ42-DI42)/DI42 -> -0.042104286 | DK43: =SUM(DK42-DJ42)/DJ42 -> 0.074123793 | DL43: =SUM(DL42-DK42)/DK42 -> 0.067843743 | DM43: =SUM(DM42-DL42)/DL42 -> 0.074712872 | DN43: =SUM(DN42-DM42)/DM42 -> -0.19033944 | DO43: =SUM(DO42-DN42)/DN42 -> -0.017382539 | DP43: =SUM(DP42-DO42)/DO42 -> 0.084756402 | ... GK43: =SUM(GK42-GJ42)/GJ42 -> -0.20563875 | GL43: =(GL42-GK42)/GK42 -> -0.063215054 | GM43: =(GM42-GL42)/GL42 -> 0.69721822 | GN43: =(GN42-GM42)/GM42 -> -0.21064648 | GO43: =(GO42-GN42)/GN42 -> -0.093117167 | GP43: =(GP42-GO42)/GO42 -> -0.0057304091 | GQ43: =(GQ42-GP42)/GP42 -> 0.039279559 | GR43: =(GR42-GQ42)/GQ42 -> 0.047503793 | GU43: Labour % | GV43: =LABOUR!AG55 -> 0.3940861
B44: Same week last year | BD44: =D42 -> 0 | BE44: =E42 -> 0 | BF44: =F42 -> 0 | BG44: =G42 -> 0 | BH44: =H42 -> 0 | BI44: =I42 -> 0 | BJ44: =J42 -> 0 | BK44: =K42 -> 0 | ... GL44: =EL42 -> 26785 | GM44: =EL42 -> 26785 | GN44: =EM42 -> 20483.7 | GO44: =EN42 -> 24558.2 | GP44: =EO42 -> 26415.1 | GQ44: =EP42 -> 24772.05 | GR44: =EQ42 -> 24749.7 | GT44: Same week last year
B45: vs SWLY % | BY45: =IFERROR(((BY42-BY44)/BY44),0) -> 0 | BZ45: =IFERROR(((BZ42-BZ44)/BZ44),0) -> 0 | CA45: =IFERROR(((CA42-CA44)/CA44),0) -> 0 | CB45: =IFERROR(((CB42-CB44)/CB44),0) -> 0 | CC45: =IFERROR(((CC42-CC44)/CC44),0) -> 0 | CD45: =IFERROR(((CD42-CD44)/CD44),0) -> 0 | CE45: =IFERROR(((CE42-CE44)/CE44),0) -> 0 | CF45: =IFERROR(((CF42-CF44)/CF44),0) -> 0 | ... GR45: =IFERROR(((GR42-GR44)/GR44),0) -> -0.07233421 | GT45: YoY LFL %
A47: NOLE | B47: NOLE | C47: WET | D47: 3237 | E47: 2860.5 | F47: 2485.2 | G47: 3284.35 | H47: 2716.5 | I47: 1197.25 | J47: 1538.3 | K47: 1138.2 | L47: 1243.25 | M47: 1201.15 | N47: 1057.2 | O47: 610.05 | P47: 1134.2 | Q47: 1063.35 | R47: 1785.5 | S47: 1302 | T47: 897.05 | U47: 1102.85 | V47: 1121.95 | W47: 1093.85 | X47: 1061.25 | Y47: 784.1 | Z47: 653.25 | AA47: 740.5 | AB47: 811.3 | AC47: 883.15 | AD47: 1303.3 | AE47: 1787.05 | AF47: 2213.7 | AG47: 1628.85 | AH47: 1737.65 | AI47: 1620 | AJ47: 1689.1 | AK47: 1503.3 | AL47: 2373 | AM47: 2775 | AN47: 2113.6 | AO47: 2256.35 | AP47: 2832.95 | AQ47: 2895.15 | AR47: 2231.65 | AS47: 3320.75 | AT47: 4201.55 | AU47: 5114 | AV47: 3370.05 | AW47: 3336.05 | AX47: 4027.2 | AY47: 3277.7 | AZ47: 4055.75 | BA47: 2340.95 | BB47: 2214.95 | BC47: 2071.85 | BD47: 1667.15 | BE47: 2103.4 | BF47: 1928.8 | BG47: 1874.52 | BH47: 2344.95 | BI47: 2410.67 | BJ47: 2050.4 | BK47: 1085.5 | BL47: 1582.85 | BM47: 1480.45 | BN47: 1182.65 | BO47: 1075.3 | BP47: 1700.3 | BQ47: 1085.35 | BR47: 1381.15 | BS47: 1850.55 | BT47: 1181.35 | BU47: 1496.65 | BV47: 1289.45 | BW47: 1673.65 | BX47: 2158.75 | BY47: 1529.2 | BZ47: 1266.7 | CA47: 1020.15 | CB47: 997.4 | CC47: 1225.3 | CD47: 1433.95 | CE47: 1307.8 | CF47: 1561.65 | CG47: 1090.6 | CH47: 1399.5 | CI47: 1299.65 | CJ47: 1180.8 | CK47: 1649 | CL47: 1847.9 | CM47: 1657.45 | CN47: 1919.45 | CO47: 1582.45 | CP47: 1424 | CQ47: 1919.3 | CR47: 2388 | CS47: 2356.5 | CT47: 1717.65 | CU47: 2288.4 | CV47: 1848.4 | CW47: 1774.25 | CX47: 2248.3 | CY47: 2210.5 | CZ47: 1536.05 | DA47: 2052.3 | DB47: 2448.15 | DC47: 2964.05 | DD47: 3048.65 | DE47: 2542.6 | DF47: 2732.3 | DG47: 2436.9 | DH47: 2839.85 | DI47: 1533.35 | DJ47: 1251.8 | DK47: 1632.9 | DL47: 1269.1 | DM47: 1356.75 | DN47: 1153.1 | DO47: 1023.75 | DP47: 734.05 | DQ47: 1346.65 | DR47: 1705.05 | DS47: 1425.35 | DT47: 898.25 | DU47: 1312.6 | DV47: 1313.15 | DW47: 1290.2 | DX47: 1541.15 | DY47: 1328.3 | DZ47: 1645.15 | EA47: 858 | EB47: 1054.15 | EC47: 1036.3 | ED47: 1037.4 | EE47: 966.1 | EF47: 1124 | EG47: 1242.15 | EH47: 1138.65 | EI47: 1084.6 | EJ47: 1132.8 | EK47: 1290.9 | EL47: 1469.5 | EM47: 2356.6 | EN47: 2632.5 | EO47: 1861.8 | EP47: 1883.8 | EQ47: 3366.7 | ER47: 2230.5 | ES47: 2391.5 | ET47: 2129.1 | EU47: 3008.5 | EV47: 1873.8 | EW47: 2840.7 | EX47: 2513.9 | EY47: 2914.4 | EZ47: 2483.8 | FA47: 2785.7 | FB47: 2944.7 | FC47: 2910.8 | FD47: 3134.1 | FE47: 2759.1 | FF47: 2996.7 | FG47: 3124.5 | FH47: 2436.9 | FI47: 1584.4 | FJ47: 1331.6 | FK47: 1447.7 | FL47: 1271.2 | FM47: 1126.8 | FN47: 1415 | FO47: 1019.9 | FP47: 703.7 | FQ47: 1394.8 | FR47: 1276.6 | FS47: 920.3 | FT47: 941.6 | FU47: 1255.5 | FV47: 1214.9 | FW47: 1844.1 | FX47: 1572.3 | FY47: 1143.8 | FZ47: 1630.7 | GA47: 789.8 | GB47: 981.2 | GC47: 1044.5 | GD47: 1043.6 | GE47: 933.4 | GF47: 1223.4 | GG47: 1221.8 | GH47: 1368.9 | GI47: 947.2 | GJ47: 1299.1 | GK47: 1675.1 | GL47: 1243.8 | GM47: 1513 | GN47: 1875.7 | GO47: 1626.2 | GP47: 1861.4 | GQ47: 3091.7 | GR47: 2119.2 | GS47: =EQ47 -> 3366.7 | GT47: WET | GU47: Weekly margins
C48: DRY | D48: 10304.5 | E48: 9593 | F48: 9122.25 | G48: 9931.5 | H48: 9736.75 | I48: 5323.75 | J48: 6189.5 | K48: 4503.25 | L48: 5044.5 | M48: 4751 | N48: 4146.5 | O48: 3580.75 | P48: 5194.5 | Q48: 5463.25 | R48: 5951 | S48: 5230.5 | T48: 4131.5 | U48: 4608.25 | V48: 4801 | W48: 4667.5 | X48: 3965.5 | Y48: 3408 | Z48: 4765 | AA48: 4579.5 | AB48: 3595 | AC48: 4249 | AD48: 4005 | AE48: 4258.5 | AF48: 3905 | AG48: 3509 | AH48: 4017 | AI48: 3639.5 | AJ48: 3030.75 | AK48: 3422 | AL48: 4837 | AM48: 5471 | AN48: 4845 | AO48: 4701.5 | AP48: 5490 | AQ48: 7511.25 | AR48: 5497 | AS48: 7484.5 | AT48: 7618.5 | AU48: 10077.75 | AV48: 6750.5 | AW48: 7859 | AX48: 7986.5 | AY48: 7466.75 | AZ48: 7567.5 | BA48: 7127.5 | BB48: 9963.75 | BC48: 9538.5 | BD48: 8872 | BE48: 9466 | BF48: 9526 | BG48: 8509.5 | BH48: 9879.75 | BI48: 9534.2 | BJ48: 9123.25 | BK48: 5533.5 | BL48: 8373.75 | BM48: 7702.5 | BN48: 5190.75 | BO48: 5197 | BP48: 7606.25 | BQ48: 5357.75 | BR48: 6590 | BS48: 7638.75 | BT48: 6923 | BU48: 6645.75 | BV48: 6272.75 | BW48: 7826.5 | BX48: 10336 | BY48: 9203.38 | BZ48: 11462.5 | CA48: 9194.75 | CB48: 9116.25 | CC48: 9643.75 | CD48: =7498.5+2823.75 -> 10322.25 | CE48: 9126.25 | CF48: 11636.5 | CG48: 10026.5 | CH48: 9886.75 | CI48: 10231.75 | CJ48: 9746 | CK48: 11424 | CL48: 12738.75 | CM48: 12402.25 | CN48: 15867.5 | CO48: =8489.25+2499.75+671.25+1956.75 -> 13617 | CP48: 13151.25 | CQ48: 16629.1 | CR48: 17122.85 | CS48: 15714.5 | CT48: 15972.75 | CU48: 18301.65 | CV48: 16243.75 | CW48: 15918.63 | CX48: 18019.75 | CY48: 18665.6 | CZ48: 16574.65 | DA48: =11184.25+3452.75+2654.5+599.2 -> 17890.7 | DB48: =11688.5+3111.25+3375+92 -> 18266.75 | DC48: =12651.25+3851.8+3054.5 -> 19557.55 | DD48: =13735+5902+2619.5+184.4 -> 22440.9 | DE48: =11745.5+2791.25+4526+172 -> 19234.75 | DF48: =13169.5+3067.752+4157.25+327.6 -> 20722.102 | DG48: =12906.5+3054.25+171.75+4887.5 -> 21020 | DH48: =13633.5+5031.75+3247.75+219.75 -> 22132.75 | DI48: =8914.75+3429+2961+240.75 -> 15545.5 | DJ48: =6656.75+3726.25+2683.25+232.87 -> 13299.12 | DK48: 16192.875 | DL48: =7680.25+2758.5+3598.5+300 -> 14337.25 | DM48: =6758.75+2078+139.5+3535.24 -> 12511.49 | DN48: =7185.75+2468+1854.5+82.5 -> 11590.75 | DO48: =5926.75+2500.75+3284.25+128.62 -> 11840.37 | DP48: =5216.25+2603.75+1902+199.5 -> 9921.5 | DQ48: =8056.75+3924.5+2684.35+292.5 -> 14958.1 | DR48: =9643.25+2510.75+270.37+2815 -> 15239.37 | DS48: =8581+1828.5+2828+145.87 -> 13383.37 | DT48: =6700.5+2903.25+2220.5+216.75 -> 12041 | DU48: =8605.5+90.38+2306.7+3892.75 -> 14895.33 | DV48: =7986.5+3687.5+244.12+2598.25 -> 14516.37 | DW48: =8994.25+280.5+2323.05+3253.25 -> 14851.05 | DX48: =10626.5+110.62+3246+3361.9 -> 17345.02 | DY48: =7488.5+2124+2493.4+117 -> 12222.9 | DZ48: =10023.75+3542.25+2340.8 -> 15906.8 | EA48: =6711.75+1909.75+3031.75 -> 11653.25 | EB48: =7137.75+2505.8+1638.15 -> 11281.7 | EC48: =6604.25+2369.4+3690.85 -> 12664.5 | ED48: =7007.25+3446.85+2592 -> 13046.1 | EE48: =(1887.65-EE91)+6067+3894.75 -> 11602.4 | EF48: =7613.75+3098.85+2187.15 -> 12899.75 | EG48: =7369.5+2552.64+2380.5 -> 12302.64 | EH48: =7497+2549+3074.9 -> 13120.9 | EI48: =7833.5+3478.75+1620 -> 12932.25 | EJ48: =6929+3010+2498 -> 12437 | EK48: =7500.5+2763.9+3090.5 -> 13354.9 | EL48: =10158.5+4089.5+2533.3 -> 16781.3 | EM48: =11189.75+3595.45+2250 -> 17035.2 | EN48: =11976.25+2964+4123.25 -> 19063.5 | EO48: =10396+3600.5+2268.5 -> 16265 | EP48: =10133+2767.5+3817.75 -> 16718.25 | EQ48: =13957.25+1960+4172.25 -> 20089.5 | ER48: =10463.25+2805.25+2934 -> 16202.5 | ES48: =10377.5+3029+3536.75 -> 16943.25 | ET48: =10320.75+4111.5+2236 -> 16668.25 | EU48: =14244+2321.5+3482.25 -> 20047.75 | EV48: =10251.75+3479.25+2983 -> 16714 | EW48: =11299.5+3861.5+2076 -> 17237 | EX48: =12608.25+2358.5+4491.25 -> 19458 | EY48: =12292+3430+2638.5 -> 18360.5 | EZ48: =3618.25+11855+2833 -> 18306.25 | FA48: =11650.25+4628.65+3130.5 -> 19409.4 | FB48: =13684+2452.5+4141.3 -> 20277.8 | FC48: =13995+4590.25+1934.5 -> 20519.75 | FD48: =12814.5+2408+5325 -> 20547.5 | FE48: =12328+4805.25+2480.5 -> 19613.75 | FF48: =11718.75+4662+2977 -> 19357.75 | FG48: =13261.75+1162+4160 -> 18583.75 | FH48: =11868.75+1631+5195.25 -> 18695 | FI48: =8435.75+3665.7-FI91+2681 -> 14461.75 | FJ48: 14024.75 | FK48: 14852 | FL48: =7350.75+2919+3070.5 -> 13340.25 | FM48: =7858.75+2193.5+2894.5 -> 12946.75 | FN48: =7671+3464.55+3486 -> 14621.55 | FO48: =6561.5+2532.25+2291 -> 11384.75 | FP48: =5758.75+1616.5+1740 -> 9115.25 | FQ48: =7592.25+1871+3006.4 -> 12469.65 | FR48: =7413.75+1964+3161.31 -> 12539.06 | FS48: =6485.5+2721.5+2818 -> 12025 | FT48: =6352.75+3743.07+2839.25 -> 12935.07 | FU48: =7628.5+2512+3538.2 -> 13678.7 | FV48: =7550.5+3138.25+3132.89 -> 13821.64 | FW48: =9699.5+3385.25+2866.46 -> 15951.21 | FX48: =10463.5+3979.75+3896.16+497 -> 18836.41 | FY48: =7972+2633.3+3543.5 -> 14148.8 | FZ48: =9624.75+3163+4818.25 -> 17606 | GA48: =6667.75+3538.2+2926.5 -> 13132.45 | GB48: =7571+2392+3850.56 -> 13813.56 | GC48: =6544.75+2517.5+3432.71 -> 12494.96 | GD48: =6421.25+2943+5020.9 -> 14385.15 | GE48: =5796.25+1417.5+3748.77 -> 10962.52 | GF48: =8664.75+3136.25+3866.48 -> 15667.48 | GG48: =8085+3219.25+3883.25 -> 15187.5 | GH48: =6455.25+2864+2925.3 -> 12244.55 | GI48: =6493.75+2995.25+3541.71 -> 13030.71 | GJ48: =8060.5+4128.1+2645.25 -> 14833.85 | GK48: =8340.5+3750.5+4086.15 -> 16177.15 | GL48: =7909.5+4262.3+3167.75 -> 15339.55 | GM48: =3621.75+9278+4460 -> 17359.75 | GN48: =10930.25+3550.5+2688.09 -> 17168.84 | GO48: =2985.1+4304+7873.25 -> 15162.35 | GP48: =10028+3226.75+4558.1 -> 17812.85 | GQ48: =4365.25-141+11849.75+3890.3 -> 19964.3 | GR48: =9193.25+4206+3878.6 -> 17277.85 | GS48: =EQ48 -> 20089.5 | GT48: DRY | GU48: Dry % | GV48: =DRY!AG52 -> 0.72130838
B49: Site total | D49: =SUM(D47:D48) -> 13541.5 | E49: =SUM(E47:E48) -> 12453.5 | F49: =SUM(F47:F48) -> 11607.45 | G49: =SUM(G47:G48) -> 13215.85 | H49: =SUM(H47:H48) -> 12453.25 | I49: =SUM(I47:I48) -> 6521 | J49: =SUM(J47:J48) -> 7727.8 | K49: =SUM(K47:K48) -> 5641.45 | ... GR49: =SUM(GR47:GR48) -> 19397.05 | GS49: =SUM(GS47+GS48) -> 23456.2 | GT49: =B47 -> NOLE | GU49: Dry % (avg) | GV49: =DRY!AH52 -> 0.74594897 | GW49: =AVERAGE(ES49:GR49) -> 17571.457 | GX49: =AVERAGE(FS49:GR49) -> 16438.477 | GY49: =AVERAGE(GF49:GR49) -> 17561.018 | GZ49: =AVERAGE(GN49:GR49) -> 19592.078 | HA49: =MAX(D49:GR49) -> 25489.55
B50: vs last week % | E50: =SUM(E49-D49) -> -1088 | F50: =SUM(F49-E49) -> -846.05 | G50: =SUM(G49-F49) -> 1608.4 | H50: =SUM(H49-G49) -> -762.6 | I50: =SUM(I49-H49) -> -5932.25 | J50: =SUM(J49-I49) -> 1206.8 | K50: =SUM(K49-J49) -> -2086.35 | L50: =SUM(L49-K49) -> 646.3 | ... DH50: =SUM(DH49-DG49) -> 1515.7 | DI50: =SUM(DI49-DH49)/DH49 -> -0.31609644 | DJ50: =SUM(DJ49-DI49)/DI49 -> -0.14801524 | DK50: =SUM(DK49-DJ49)/DJ49 -> 0.22506171 | DL50: =SUM(DL49-DK49)/DK49 -> -0.12450651 | DM50: =SUM(DM49-DL49)/DL49 -> -0.11137197 | DN50: =SUM(DN49-DM49)/DM49 -> -0.081076618 | DO50: =SUM(DO49-DN49)/DN49 -> 0.0094374934 | DP50: =SUM(DP49-DO49)/DO49 -> -0.1716845 | ... GK50: =SUM(GK49-GJ49)/GJ49 -> 0.10657071 | GL50: =(GL49-GK49)/GK49 -> -0.071077875 | GM50: =(GM49-GL49)/GL49 -> 0.13805413 | GN50: =(GN49-GM49)/GM49 -> 0.009102542 | GO50: =(GO49-GN49)/GN49 -> -0.11845862 | GP50: =(GP49-GO49)/GO49 -> 0.171885 | GQ50: =(GQ49-GP49)/GP49 -> 0.17188711 | GR50: =(GR49-GQ49)/GQ49 -> -0.15869839 | GU50: Labour % | GV50: =LABOUR!AG60 -> 0.23830428
B51: Same week last year | BD51: =D49 -> 13541.5 | BE51: =E49 -> 12453.5 | BF51: =F49 -> 11607.45 | BG51: =G49 -> 13215.85 | BH51: =H49 -> 12453.25 | BI51: =I49 -> 6521 | BJ51: =J49 -> 7727.8 | BK51: =K49 -> 5641.45 | ... GL51: =EL49 -> 18250.8 | GM51: =EL49 -> 18250.8 | GN51: =EM49 -> 19391.8 | GO51: =EN49 -> 21696 | GP51: =EO49 -> 18126.8 | GQ51: =EP49 -> 18602.05 | GR51: =EQ49 -> 23456.2 | GT51: Same week last year
B52: vs SWLY % | BD52: =(BD49-BD51)/BD51 -> -0.22171473 | BE52: =(BE49-BE51)/BE51 -> -0.070992091 | BF52: =(BF49-BF51)/BF51 -> -0.013151037 | BG52: =(BG49-BG51)/BG51 -> -0.21427528 | BH52: =(BH49-BH51)/BH51 -> -0.018352639 | BI52: =(BI49-BI51)/BI51 -> 0.83175433 | BJ52: =(BJ49-BJ51)/BJ51 -> 0.4459031 | BK52: =(BK49-BK51)/BK51 -> 0.17327992 | ... GR52: =(GR49-GR51)/GR51 -> -0.17305233 | GT52: YoY LFL %
A54: KINGS ARMS | B54: KINGS ARMS | C54: WET | DT54: 16212.05 | DU54: 18302.3 | DV54: 16397.9 | DW54: 18828.15 | DX54: 23238.15 | DY54: 20957.85 | DZ54: 16878.75 | EA54: 11978.4 | EB54: 13193.5 | EC54: 11433.35 | ED54: 12191.85 | EE54: 12848.75 | EF54: 12532.2 | EG54: 14655.15 | EH54: 13955.05 | EI54: 13169.3 | EJ54: 14312.05 | EK54: 14952.35 | EL54: 13404.8 | EM54: 10372.9 | EN54: 10407.35 | EO54: 15031.25 | EP54: 11807.4 | EQ54: 10653.05 | ER54: 10565.55 | ES54: 10062.7 | ET54: 10822.05 | EU54: 10649.75 | EV54: 10022.6 | EW54: 11926.8 | EX54: 9319.8 | EY54: 9869.2 | EZ54: 8547.85 | FA54: 7591 | FB54: 19525.35 | FC54: 9128.95 | FD54: 9599.95 | FE54: 8581.75 | FF54: 8589.1 | FG54: 9643.55 | FH54: 9874.7 | FI54: 9468.55 | FJ54: 10189.7 | FK54: 11588.7 | FL54: 10416.85 | FM54: 9335.95 | FN54: 11595.05 | FO54: 9570.3 | FP54: 11059.15 | FQ54: 10212.9 | FR54: 10024.95 | FS54: 9996.9 | FT54: 11298.1 | FU54: 13340.4 | FV54: 12285.75 | FW54: 13343.15 | FX54: 17560.2 | FY54: 16634.3 | FZ54: 17151.85 | GA54: 8699.65 | GB54: 9880.8 | GC54: 10503.7 | GD54: 10009.2 | GE54: 11301.55 | GF54: 11225.35 | GG54: 13425.25 | GH54: 12165.35 | GI54: 9918.1 | GJ54: 12002.8 | GK54: =820.9+10712.03 -> 11532.93 | GL54: 10635.1 | GM54: 15458.1 | GN54: 10465.25 | GO54: 10871.85 | GP54: 9022.45 | GQ54: 10669.5 | GR54: 10375.45 | GS54: =EQ54 -> 10653.05 | GT54: WET | GU54: Weekly margins
C55: DRY | DT55: 7667.31 | DU55: 16402.5 | DV55: 15614.61 | DW55: 17027.25 | DX55: 20158 | DY55: 18263.25 | DZ55: 19847.5 | EA55: 13397.5 | EB55: 14479.75 | EC55: 12953.25 | ED55: 14203.5 | EE55: 14719.44 | EF55: 15594.25 | EG55: 17389.25 | EH55: 15546 | EI55: 14338.25 | EJ55: 13857 | EK55: 13135.25 | EL55: 16511.75 | EM55: 11106.75 | EN55: 12012.75 | EO55: 16434.5 | EP55: 13570.75 | EQ55: 10518.75 | ER55: 11233.25 | ES55: 11013.25 | ET55: 11156.75 | EU55: 11597.75 | EV55: 11442.25 | EW55: 13767 | EX55: 8724.75 | EY55: 9997.25 | EZ55: 11465 | FA55: 9343 | FB55: 15633.6 | FC55: 12183.25 | FD55: 10882.5 | FE55: 10194.5 | FF55: 10596.25 | FG55: 12134.5 | FH55: 13621 | FI55: 10965.5 | FJ55: 11227.75 | FK55: 12505 | FL55: 10834.5 | FM55: 10150.25 | FN55: 11921.75 | FO55: 10592.25 | FP55: 13102 | FQ55: 11801 | FR55: 11091.75 | FS55: 11331.25 | FT55: 12357 | FU55: 16177.25 | FV55: 13575.25 | FW55: 17020.75 | FX55: 17968.65 | FY55: 16012.25 | FZ55: 22583.75 | GA55: 8891.75 | GB55: 11770.5 | GC55: 12198.25 | GD55: 12309 | GE55: 11834.5 | GF55: 13000.5 | GG55: 14946.25 | GH55: 12229.25 | GI55: 11623.25 | GJ55: 15147.5 | GK55: =577.5+11359.52 -> 11937.02 | GL55: 13156 | GM55: 15338.75 | GN55: 13158.25 | GO55: 13646.5 | GP55: 10344 | GQ55: 11062 | GR55: 11672.75 | GS55: =EQ55 -> 10518.75 | GT55: DRY | GU55: Dry % | GV55: =DRY!AG27 -> 0.72999165
B56: Site total | D56: =SUM(D54:D55) -> 0 | E56: =SUM(E54:E55) -> 0 | F56: =SUM(F54:F55) -> 0 | G56: =SUM(G54:G55) -> 0 | H56: =SUM(H54:H55) -> 0 | I56: =SUM(I54:I55) -> 0 | J56: =SUM(J54:J55) -> 0 | K56: =SUM(K54:K55) -> 0 | ... BC56: =SUM(BC54:BC55) -> 0 | DT56: =SUM(DT54:DT55) -> 23879.36 | DU56: =SUM(DU54:DU55) -> 34704.8 | DV56: =SUM(DV54:DV55) -> 32012.51 | DW56: =SUM(DW54:DW55) -> 35855.4 | DX56: =SUM(DX54:DX55) -> 43396.15 | DY56: =SUM(DY54:DY55) -> 39221.1 | DZ56: =SUM(DZ54:DZ55) -> 36726.25 | EA56: =SUM(EA54:EA55) -> 25375.9 | ... GR56: =SUM(GR54:GR55) -> 22048.2 | GS56: =SUM(GS54+GS55) -> 21171.8 | GT56: =B54 -> KINGS ARMS | GU56: Dry % (avg) | GV56: =DRY!AH27 -> 0.72009151 | GW56: =AVERAGE(ES56:GR56) -> 23581.284 | GX56: =AVERAGE(FS56:GR56) -> 25425.585 | GY56: =AVERAGE(GF56:GR56) -> 24233.038 | GZ56: =AVERAGE(GN56:GR56) -> 22257.6 | HA56: =MAX(D56:GR56) -> 43396.15
B57: vs last week % | E57: =SUM(E56-D56) -> 0 | F57: =SUM(F56-E56) -> 0 | G57: =SUM(G56-F56) -> 0 | H57: =SUM(H56-G56) -> 0 | I57: =SUM(I56-H56) -> 0 | J57: =SUM(J56-I56) -> 0 | K57: =SUM(K56-J56) -> 0 | L57: =SUM(L56-K56) -> 0 | ... BC57: =SUM(BC56-BB56) -> 0 | DU57: =SUM(DU56-DT56)/DT56 -> 0.45333878 | DV57: =SUM(DV56-DU56)/DU56 -> -0.077576877 | DW57: =SUM(DW56-DV56)/DV56 -> 0.12004338 | DX57: =SUM(DX56-DW56)/DW56 -> 0.21031002 | DY57: =SUM(DY56-DX56)/DX56 -> -0.096207843 | DZ57: =SUM(DZ56-DY56)/DY56 -> -0.063609894 | EA57: =SUM(EA56-DZ56)/DZ56 -> -0.30905279 | EB57: =SUM(EB56-EA56)/EA56 -> 0.09053275 | ... GK57: =SUM(GK56-GJ56)/GJ56 -> -0.13555467 | GL57: =(GL56-GK56)/GK56 -> 0.013683455 | GM57: =(GM56-GL56)/GL56 -> 0.29446936 | GN57: =(GN56-GM56)/GM56 -> -0.2329248 | GO57: =(GO56-GN56)/GN56 -> 0.037879654 | GP57: =(GP56-GO56)/GO56 -> -0.21012425 | GQ57: =(GQ56-GP56)/GP56 -> 0.12212099 | GR57: =(GR56-GQ56)/GQ56 -> 0.014573315 | GU57: Labour % | GV57: =LABOUR!AG32 -> 0.38609955
B58: Same week last year | DT58: =BU56 -> 0 | DU58: =BV56 -> 0 | DV58: =BW56 -> 0 | DW58: =BX56 -> 0 | DX58: =BY56 -> 0 | DY58: =BZ56 -> 0 | DZ58: =CA56 -> 0 | EA58: =CB56 -> 0 | ... FR58: =DS56 -> 0 | FS58: =DS56 -> 0 | FT58: =DT56 -> 23879.36 | FU58: =DU56 -> 34704.8 | FV58: =DV56 -> 32012.51 | FW58: =DW56 -> 35855.4 | FX58: =DX56 -> 43396.15 | FY58: =DY56 -> 39221.1 | FZ58: =DZ56 -> 36726.25 | ... GL58: =EL56 -> 29916.55 | GM58: =EL56 -> 29916.55 | GN58: =EM56 -> 21479.65 | GO58: =EN56 -> 22420.1 | GP58: =EO56 -> 31465.75 | GQ58: =EP56 -> 25378.15 | GR58: =EQ56 -> 21171.8 | GT58: Same week last year
B59: LFL % | FT59: =(FT56-FT58)/FT58 -> -0.009391374 | FU59: =(FU56-FU58)/FU58 -> -0.14946492 | FV59: =(FV56-FV58)/FV58 -> -0.19215957 | FW59: =(FW56-FW58)/FW58 -> -0.15315685 | FX59: =(FX56-FX58)/FX58 -> -0.18129028 | FY59: =(FY56-FY58)/FY58 -> -0.16762788 | FZ59: =(FZ56-FZ58)/FZ58 -> 0.081940029 | GA59: =(GA56-GA58)/GA58 -> -0.30676744 | ... GR59: =(GR56-GR58)/GR58 -> 0.041394685 | GT59: YoY LFL %
A61: MANOR HOUSE INN | B61: MANOR HOUSE INN | C61: WET | ED61: 15442.35 | EE61: 10346.69 | EF61: 11338.72 | EG61: 10883.79 | EH61: 10459.99 | EI61: 10579.15 | EJ61: 9839.93 | EK61: 12720.3 | EL61: 10283.2 | EM61: 12097.8 | EN61: 10277.95 | EO61: 12228.7 | EP61: 11141.6 | EQ61: 11367.85 | ER61: 12995.15 | ES61: 11527.1 | ET61: 10786.7 | EU61: 11150.1 | EV61: 9567.9 | EW61: 12852.95 | EX61: 9946.95 | EY61: 8692.45 | EZ61: 11563.95 | FA61: 9917.2 | FB61: 9572.5 | FC61: 10210.9 | FD61: 11210.45 | FE61: 10780.1 | FF61: 11141.7 | FG61: 9003.2 | FH61: 9392.65 | FI61: 9980.95 | FJ61: 7554.4 | FK61: 9008.45 | FL61: 8031.4 | FM61: 8254.65 | FN61: 7672.8 | FO61: 7520.55 | FP61: 8224.95 | FQ61: 9960.65 | FR61: 9327.05 | FS61: 8389.65 | FT61: 8874.3 | FU61: 7447.3 | FV61: 9770.25 | FW61: 9614.85 | FX61: 8148.5 | FY61: 11665.3 | FZ61: 13357.3 | GA61: 7515.9 | GB61: 8474.45 | GC61: 7229.9 | GD61: 8756.15 | GE61: 8902.1 | GF61: 10647.55 | GG61: 9901.7 | GH61: 10774.1 | GI61: 8644.55 | GJ61: 10639.73 | GK61: 10639.87 | GL61: 8966.65 | GM61: 12610.2 | GN61: 11112.4 | GO61: 10191.83 | GP61: 11671.8 | GQ61: 10224.75 | GR61: 10951.2 | GS61: =EQ61 -> 11367.85 | GT61: WET | GU61: Weekly margins
C62: DRY | ED62: 15024.3 | EE62: 17224.25 | EF62: 19817.5 | EG62: 19115.5 | EH62: 16771.3 | EI62: 15283.75 | EJ62: 16738.44 | EK62: 18160.25 | EL62: 17080.25 | EM62: 15955.25 | EN62: 16334 | EO62: 18909.25 | EP62: 17468.25 | EQ62: 16473.75 | ER62: 15522.25 | ES62: 14671 | ET62: 16806.5 | EU62: 20150.6 | EV62: 16282.5 | EW62: 18823.05 | EX62: 15005.5 | EY62: 11706.5 | EZ62: 16362.5 | FA62: 13933.5 | FB62: 16351.75 | FC62: 17747.25 | FD62: 18751 | FE62: 15116.25 | FF62: 15957.12 | FG62: 13421.2 | FH62: 15960 | FI62: 14206.5 | FJ62: 12127.07 | FK62: 14079 | FL62: 13394.75 | FM62: 14588.25 | FN62: 13467.25 | FO62: 13138.51 | FP62: 13239.95 | FQ62: 14239.75 | FR62: 14807.5 | FS62: 14565.65 | FT62: 13565 | FU62: 14077.75 | FV62: 15963.25 | FW62: 17890.5 | FX62: 15724.5 | FY62: 16272.75 | FZ62: 24088.85 | GA62: 12180 | GB62: 12881.12 | GC62: 11789.25 | GD62: 13990 | GE62: 13036 | GF62: 16989.25 | GG62: 14384 | GH62: 16520 | GI62: 14630 | GJ62: 19989.82 | GK62: 15650 | GL62: 14780.75 | GM62: 21199.25 | GN62: 17146.75 | GO62: 15530.82 | GP62: 16167.75 | GQ62: 17152.5 | GR62: 16034.45 | GS62: =EQ62 -> 16473.75 | GT62: DRY | GU62: Dry % | GV62: =DRY!AG32 -> 0.74162781
B63: Site total | D63: =SUM(D61:D62) -> 0 | E63: =SUM(E61:E62) -> 0 | F63: =SUM(F61:F62) -> 0 | G63: =SUM(G61:G62) -> 0 | H63: =SUM(H61:H62) -> 0 | I63: =SUM(I61:I62) -> 0 | J63: =SUM(J61:J62) -> 0 | K63: =SUM(K61:K62) -> 0 | ... BC63: =SUM(BC61:BC62) -> 0 | ED63: =SUM(ED61:ED62) -> 30466.65 | EE63: =SUM(EE61:EE62) -> 27570.94 | EF63: =SUM(EF61:EF62) -> 31156.22 | EG63: =SUM(EG61:EG62) -> 29999.29 | EH63: =SUM(EH61:EH62) -> 27231.29 | EI63: =SUM(EI61:EI62) -> 25862.9 | EJ63: =SUM(EJ61:EJ62) -> 26578.37 | EK63: =SUM(EK61:EK62) -> 30880.55 | ... GR63: =SUM(GR61:GR62) -> 26985.65 | GS63: =SUM(GS61+GS62) -> 27841.6 | GT63: =B61 -> MANOR HOUSE INN | GU63: Dry % (avg) | GV63: =DRY!AH32 -> 0.69786554 | GW63: =AVERAGE(ES63:GR63) -> 25279.032 | GX63: =AVERAGE(FS63:GR63) -> 25666.24 | GY63: =AVERAGE(GF63:GR63) -> 27165.513 | GZ63: =AVERAGE(GN63:GR63) -> 27236.85 | HA63: =MAX(D63:GR63) -> 37446.15
B64: vs last week % | E64: =SUM(E63-D63) -> 0 | F64: =SUM(F63-E63) -> 0 | G64: =SUM(G63-F63) -> 0 | H64: =SUM(H63-G63) -> 0 | I64: =SUM(I63-H63) -> 0 | J64: =SUM(J63-I63) -> 0 | K64: =SUM(K63-J63) -> 0 | L64: =SUM(L63-K63) -> 0 | ... BC64: =SUM(BC63-BB63) -> 0 | EE64: =SUM(EE63-ED63)/ED63 -> -0.095045238 | EF64: =SUM(EF63-EE63)/EE63 -> 0.13003837 | EG64: =SUM(EG63-EF63)/EF63 -> -0.037133195 | EH64: =SUM(EH63-EG63)/EG63 -> -0.09226885 | EI64: =SUM(EI63-EH63)/EH63 -> -0.050250649 | EJ64: =SUM(EJ63-EI63)/EI63 -> 0.027663951 | EK64: =SUM(EK63-EJ63)/EJ63 -> 0.16186771 | EL64: =SUM(EL63-EK63)/EK63 -> -0.1138937 | ... GK64: =SUM(GK63-GJ63)/GJ63 -> -0.14168279 | GL64: =(GL63-GK63)/GK63 -> -0.096709113 | GM64: =(GM63-GL63)/GL63 -> 0.42371165 | GN64: =(GN63-GM63)/GM63 -> -0.16416416 | GO64: =(GO63-GN63)/GN63 -> -0.089758538 | GP64: =(GP63-GO63)/GO63 -> 0.082297119 | GQ64: =(GQ63-GP63)/GP63 -> -0.016605872 | GR64: =(GR63-GQ63)/GQ63 -> -0.014303847 | GU64: Labour % | GV64: =LABOUR!AG38 -> 0.32807638
B65: Same week last year | DT65: =BU63 -> 0 | DU65: =BV63 -> 0 | DV65: =BW63 -> 0 | DW65: =BX63 -> 0 | DX65: =BY63 -> 0 | DY65: =BZ63 -> 0 | DZ65: =CA63 -> 0 | EA65: =CB63 -> 0 | ... GL65: =EM63 -> 28053.05 | GM65: =EM63 -> 28053.05 | GN65: =EN63 -> 26611.95 | GO65: =EO63 -> 31137.95 | GP65: =EP63 -> 28609.85 | GQ65: =EQ63 -> 27841.6 | GR65: =ER63 -> 28517.4 | GT65: Same week last year
B66: LFL % | GC66: =(GC63-GC65)/GC65 -> -0.37573872 | GD66: =(GD63-GD65)/GD65 -> -0.17499548 | GE66: =(GE63-GE65)/GE65 -> -0.29586773 | GF66: =(GF63-GF65)/GF65 -> -0.07875153 | GG66: =(GG63-GG65)/GG65 -> -0.10816932 | GH66: =(GH63-GH65)/GH65 -> 0.055337955 | GI66: =(GI63-GI65)/GI65 -> -0.12430484 | GJ66: =(GJ63-GJ65)/GJ65 -> -0.0081280936 | ... GR66: =(GR63-GR65)/GR65 -> -0.053712821 | GT66: YoY LFL %
A68: FLEUR DE LYS | B68: =A68 -> FLEUR DE LYS | C68: WET | FG68: 8057.51 | FH68: 9771.28 | FI68: =5585.54*1.2 -> 6702.648 | FJ68: =6387.21*1.2 -> 7664.652 | FK68: =1.2*6177.04 -> 7412.448 | FL68: =6065.42*1.2 -> 7278.504 | FM68: =7045.43*1.2 -> 8454.516 | FN68: 8787.1 | FO68: 9151.55 | FP68: 9201.6 | FQ68: 9487.5 | FR68: 8196.9 | FS68: 7947.35 | FT68: 7380.3 | FU68: =1.2*6997.5 -> 8397 | FV68: 8101.25 | FW68: =7510.2-257.5 -> 7252.7 | FX68: 9301.7 | FY68: 8262.35 | FZ68: 12925 | GA68: 6628.65 | GB68: 8069.2 | GC68: 8478.95 | GD68: 8637.4 | GE68: 8651.6 | GF68: 9056.95 | GG68: 9431.95 | GH68: 8884.75 | GI68: 9151.3 | GJ68: 9568 | GK68: 9134.25 | GL68: 8397 | GM68: 10282.5 | GN68: 10815.85 | GO68: 9158.2 | GP68: 7927.75 | GQ68: 7952.4 | GR68: 6680.25 | GS68: =EJ68 -> 0 | GT68: WET | GU68: Weekly margins
C69: DRY | FG69: 7024.5 | FH69: 11715.5 | FI69: =8408.29*1.2 -> 10089.948 | FJ69: =7595*1.2 -> 9114 | FK69: =1.2*7995 -> 9594 | FL69: =8329.17*1.2 -> 9995.004 | FM69: =9502.61*1.2 -> 11403.132 | FN69: 11350.25 | FO69: 11622.5 | FP69: 10088.5 | FQ69: 13289.25 | FR69: 12094.75 | FS69: 12542.5 | FT69: 12709 | FU69: =1.2*10012.5 -> 12015 | FV69: 11582.5 | FW69: =11641+257.5 -> 11898.5 | FX69: 14297.5 | FY69: 11987.75 | FZ69: 18977.75 | GA69: 10872.01 | GB69: 12851 | GC69: 12913 | GD69: 10682.5 | GE69: 10587 | GF69: 12226.5 | GG69: 14241.6 | GH69: 10843.5 | GI69: 11478.5 | GJ69: 15143 | GK69: 12325.15 | GL69: 12155.5 | GM69: 15377.75 | GN69: 16004.75 | GO69: 12699.25 | GP69: 11064.95 | GQ69: 12058.5 | GR69: 10936 | GS69: =EJ69 -> 0 | GT69: DRY | GU69: Dry % | GV69: =DRY!AG17 -> 0.63488881
B70: Site total | D70: =SUM(D68:D69) -> 0 | E70: =SUM(E68:E69) -> 0 | F70: =SUM(F68:F69) -> 0 | G70: =SUM(G68:G69) -> 0 | H70: =SUM(H68:H69) -> 0 | I70: =SUM(I68:I69) -> 0 | J70: =SUM(J68:J69) -> 0 | K70: =SUM(K68:K69) -> 0 | ... BC70: =SUM(BC68:BC69) -> 0 | FG70: =SUM(FG68:FG69) -> 15082.01 | FH70: =SUM(FH68:FH69) -> 21486.78 | FI70: =SUM(FI68:FI69) -> 16792.596 | FJ70: =SUM(FJ68:FJ69) -> 16778.652 | FK70: =SUM(FK68:FK69) -> 17006.448 | FL70: =SUM(FL68:FL69) -> 17273.508 | FM70: =SUM(FM68:FM69) -> 19857.648 | FN70: =SUM(FN68:FN69) -> 20137.35 | ... GR70: =SUM(GR68:GR69) -> 17616.25 | GS70: =SUM(GS68+GS69) -> 0 | GT70: =B68 -> FLEUR DE LYS | GU70: Dry % (avg) | GV70: =DRY!AH17 -> 0.65955638 | GW70: =AVERAGE(ES70:GR70) -> 20644.555 | GX70: =AVERAGE(FS70:GR70) -> 21420.983 | GY70: =AVERAGE(GF70:GR70) -> 21768.931 | GZ70: =AVERAGE(GN70:GR70) -> 21059.58 | HA70: =MAX(D70:GR70) -> 31902.75
B71: vs last week % | E71: =SUM(E70-D70) -> 0 | F71: =SUM(F70-E70) -> 0 | G71: =SUM(G70-F70) -> 0 | H71: =SUM(H70-G70) -> 0 | I71: =SUM(I70-H70) -> 0 | J71: =SUM(J70-I70) -> 0 | K71: =SUM(K70-J70) -> 0 | L71: =SUM(L70-K70) -> 0 | ... BC71: =SUM(BC70-BB70) -> 0 | FH71: =SUM(FH70-FG70)/FG70 -> 0.42466289 | FI71: =SUM(FI70-FH70)/FH70 -> -0.21846847 | FJ71: =SUM(FJ70-FI70)/FI70 -> -0.00083036595 | FK71: =SUM(FK70-FJ70)/FJ70 -> 0.013576538 | FL71: =SUM(FL70-FK70)/FK70 -> 0.015703456 | FM71: =SUM(FM70-FL70)/FL70 -> 0.14960134 | FN71: =SUM(FN70-FM70)/FM70 -> 0.014085354 | FO71: =SUM(FO70-FN70)/FN70 -> 0.031617864 | ... GK71: =SUM(GK70-GJ70)/GJ70 -> -0.13158512 | GL71: =(GL70-GK70)/GK70 -> -0.0422612 | GM71: =(GM70-GL70)/GL70 -> 0.24852208 | GN71: =(GN70-GM70)/GM70 -> 0.045219746 | GO71: =(GO70-GN70)/GN70 -> -0.18504992 | GP71: =(GP70-GO70)/GO70 -> -0.13106515 | GQ71: =(GQ70-GP70)/GP70 -> 0.053610071 | GR71: =(GR70-GQ70)/GQ70 -> -0.11966728 | GU71: Labour % | GV71: =LABOUR!AG21 -> 0.37076161
B72: Same week last year | DT72: =BU70 -> 0 | DU72: =BV70 -> 0 | DV72: =BW70 -> 0 | DW72: =BX70 -> 0 | DX72: =BY70 -> 0 | DY72: =BZ70 -> 0 | DZ72: =CA70 -> 0 | EA72: =CB70 -> 0 | ... GL72: =EM70 -> 0 | GM72: =EM70 -> 0 | GN72: =EN70 -> 0 | GO72: =EO70 -> 0 | GP72: =EP70 -> 0 | GQ72: =EQ70 -> 0 | GR72: =ER70 -> 0 | GT72: Same week last year
B73: LFL % | GT73: YoY LFL %
A75: CHICKPEA | C75: WET | D75: =D40+D33+D47+D26+D19+D12+D5+D54+D61+D68 -> 39266.98 | E75: =E40+E33+E47+E26+E19+E12+E5+E54+E61+E68 -> 38227.15 | F75: =F40+F33+F47+F26+F19+F12+F5+F54+F61+F68 -> 35339.15 | G75: =G40+G33+G47+G26+G19+G12+G5+G54+G61+G68 -> 40106.72 | H75: =H40+H33+H47+H26+H19+H12+H5+H54+H61+H68 -> 35560.17 | I75: =I40+I33+I47+I26+I19+I12+I5+I54+I61+I68 -> 26859.29 | J75: =J40+J33+J47+J26+J19+J12+J5+J54+J61+J68 -> 35485.92 | K75: =K40+K33+K47+K26+K19+K12+K5+K54+K61+K68 -> 31939.9 | ... GR75: =GR40+GR33+GR47+GR26+GR19+GR12+GR5+GR54+GR61+GR68 -> 94410.98 | GS75: =EQ75 -> 91135.95 | GT75: WET
C76: DRY | D76: =D41+D34+D48+D27+D20+D13+D6+D55+D62+D69 -> 67796.8 | E76: =E41+E34+E48+E27+E20+E13+E6+E55+E62+E69 -> 64025.84 | F76: =F41+F34+F48+F27+F20+F13+F6+F55+F62+F69 -> 64714.05 | G76: =G41+G34+G48+G27+G20+G13+G6+G55+G62+G69 -> 70409.51 | H76: =H41+H34+H48+H27+H20+H13+H6+H55+H62+H69 -> 64889.18 | I76: =I41+I34+I48+I27+I20+I13+I6+I55+I62+I69 -> 51875.42 | J76: =J41+J34+J48+J27+J20+J13+J6+J55+J62+J69 -> 53425.4 | K76: =K41+K34+K48+K27+K20+K13+K6+K55+K62+K69 -> 48380.52 | ... GR76: =GR41+GR34+GR48+GR27+GR20+GR13+GR6+GR55+GR62+GR69 -> 165066.62 | GS76: =EQ76 -> 140293.15 | GT76: DRY
B77: Chickpea total | D77: =D42+D35+D49+D28+D21+D14+D7+D56+D63+D70 -> 107063.78 | E77: =E42+E35+E49+E28+E21+E14+E7+E56+E63+E70 -> 102252.99 | F77: =F42+F35+F49+F28+F21+F14+F7+F56+F63+F70 -> 100053.2 | G77: =G42+G35+G49+G28+G21+G14+G7+G56+G63+G70 -> 110516.23 | H77: =H42+H35+H49+H28+H21+H14+H7+H56+H63+H70 -> 100449.35 | I77: =I42+I35+I49+I28+I21+I14+I7+I56+I63+I70 -> 78734.71 | J77: =J42+J35+J49+J28+J21+J14+J7+J56+J63+J70 -> 88911.32 | K77: =K42+K35+K49+K28+K21+K14+K7+K56+K63+K70 -> 80320.42 | ... GR77: =GR42+GR35+GR49+GR28+GR21+GR14+GR7+GR56+GR63+GR70 -> 259477.6 | GS77: =SUM(GS75+GS76) -> 231429.1 | GT77: CHICKPEA | GW77: =AVERAGE(ES77:GR77) -> 234857.56 | GX77: =AVERAGE(FS77:GR77) -> 238564.02 | GY77: =AVERAGE(GF77:GR77) -> 245599.83 | GZ77: =AVERAGE(GN77:GR77) -> 263032.26 | HA77: =MAX(D77:GR77) -> 359232.9
B78: Weekly LFL | E78: =SUM(E77-D77) -> -4810.79 | F78: =SUM(F77-E77) -> -2199.79 | G78: =SUM(G77-F77) -> 10463.03 | H78: =SUM(H77-G77) -> -10066.88 | I78: =SUM(I77-H77) -> -21714.64 | J78: =SUM(J77-I77) -> 10176.61 | K78: =SUM(K77-J77) -> -8590.9 | L78: =SUM(L77-K77) -> -2177.29 | ... DH78: =SUM(DH77-DG77) -> 1252.02 | DI78: =SUM(DI77-DH77)/DH77 -> -0.19047813 | DJ78: =SUM(DJ77-DI77)/DI77 -> -0.1371631 | DK78: =SUM(DK77-DJ77)/DJ77 -> 0.17601688 | DL78: =SUM(DL77-DK77)/DK77 -> 0.040741965 | DM78: =SUM(DM77-DL77)/DL77 -> -0.059348325 | DN78: =SUM(DN77-DM77)/DM77 -> -0.036612002 | DO78: =SUM(DO77-DN77)/DN77 -> 0.018349077 | DP78: =SUM(DP77-DO77)/DO77 -> 0.060371554 | ... GL78: =SUM(GL77-GK77)/GK77 -> -0.014642994 | GM78: =SUM(GM77-GK77)/GK77 -> 0.32042952 | GN78: =SUM(GN77-GL77)/GL77 -> 0.24387595 | GO78: =SUM(GO77-GM77)/GM77 -> -0.1898614 | GP78: =SUM(GP77-GN77)/GN77 -> -0.1131356 | GQ78: =SUM(GQ77-GO77)/GO77 -> 0.11474226 | GR78: =SUM(GR77-GP77)/GP77 -> 0.034466042
B79: Same week last year | BD79: =D77 -> 107063.78 | BE79: =E77 -> 102252.99 | BF79: =F77 -> 100053.2 | BG79: =G77 -> 110516.23 | BH79: =H77 -> 100449.35 | BI79: =I77 -> 78734.71 | BJ79: =J77 -> 88911.32 | BK79: =K77 -> 80320.42 | ... GL79: =EL77 -> 244112.75 | GM79: =EL77 -> 244112.75 | GN79: =EM77 -> 220175.7 | GO79: =EN77 -> 226180.51 | GP79: =EO77 -> 265505.84 | GQ79: =EP77 -> 230821.11 | GR79: =EQ77 -> 231429.1
B80: vs last week % | BD80: =(BD77-BD79)/BD79 -> 0.40486418 | BE80: =(BE77-BE79)/BE79 -> 0.37717841 | BF80: =(BF77-BF79)/BF79 -> 0.33126757 | BG80: =(BG77-BG79)/BG79 -> 0.31763814 | BH80: =(BH77-BH79)/BH79 -> 0.56209692 | BI80: =(BI77-BI79)/BI79 -> 0.92748192 | BJ80: =(BJ77-BJ79)/BJ79 -> 0.57773948 | BK80: =(BK77-BK79)/BK79 -> 0.46844439 | ... GK80: =(GK77-GK79)/GK79 -> 0.075913091 | GL80: =(GL79-GK79)/GK79 -> 0.13818255 | GM80: =(GM79-GL79)/GL79 -> 0 | GN80: =(GN79-GM79)/GM79 -> -0.098057353 | GO80: =(GO79-GN79)/GN79 -> 0.02727281 | GP80: =(GP79-GO79)/GO79 -> 0.17386701 | GQ80: =(GQ79-GP79)/GP79 -> -0.13063641 | GR80: =(GR79-GQ79)/GQ79 -> 0.0026340312
A82: HETTIE BELLS | B82: HETTIE BELLS | C82: WET | CV82: 4706.2 | CW82: 9109.9 | CX82: 11280.4 | CY82: 10699.7 | CZ82: 8584.05 | DA82: 10195.9 | DB82: 8226.55 | DC82: 11623.45 | DD82: 11260.65 | DE82: 9211.15 | DF82: 13259.9 | DG82: 10333.75 | DH82: 12784.7 | DI82: 8891.6 | DJ82: 8846.9 | DK82: 9437.6 | DL82: 8256 | DM82: 7778.5 | DN82: 7717 | DO82: 8376.4 | DP82: 8821.65 | DQ82: 7375.95 | DR82: 7876.45 | DS82: 7793.25 | DT82: 7169.85 | DU82: 10912.05 | DV82: 7415 | DW82: 9382.55 | DX82: 12843.1 | DY82: 5533.8 | DZ82: 6073.8 | EA82: 6341.45 | EB82: 5926.05 | EC82: 6056.9 | ED82: 7578.95 | EE82: 7058.1 | EF82: 6257.25 | EG82: 7877.8 | EH82: 10646.15 | EI82: 9279.35 | EJ82: 8921.2 | EK82: 10643.2 | EL82: 10337.3 | EM82: 13458.7 | EN82: 13379.45 | EO82: 12744.75 | EP82: 11075.3 | EQ82: =24885.55+3618.51-84 -> 28420.06 | ER82: 10563.35 | ES82: 12657.35 | ET82: 11278.65 | EU82: 12237.8 | EV82: 10985.6 | EW82: 11926.8 | EX82: 18078.1 | EY82: =17024.05+367.5 -> 17391.55 | EZ82: 17437.47 | FA82: 16230.68 | FB82: 12764.5 | FC82: 15331.55 | FD82: 12485.5 | FE82: 13891.1 | FF82: 16623.4 | FG82: =22994.8+798 -> 23792.8 | FH82: 16134.5 | FI82: 12024.1 | FJ82: 11476.1 | FK82: 14517.3 | FL82: 11436.6 | FM82: 12564.1 | FN82: 12240.1 | FO82: 10114.3 | FP82: 10017 | FQ82: 7826.1 | FR82: 9862.2 | FS82: 10684.1 | FT82: 9678.6 | FU82: 11289.2 | FV82: 12694.1 | FW82: 14115.3 | FX82: 19640 | FY82: 12653.2 | FZ82: 10588.3 | GA82: 7769.3 | GB82: 11401.1 | GC82: 9519 | GD82: 12990.6 | GE82: 5805 | GF82: 9427.9 | GG82: 11281.93 | GH82: 12857.9 | GI82: 14628.2 | GJ82: 13164.5 | GK82: 19686.7 | GL82: 12623.65 | GM82: 15623.4 | GN82: 14328.8 | GO82: 11578.3 | GP82: 15456.3 | GQ82: 17479.6 | GR82: 17469.4 | GS82: =EQ82 -> 28420.06 | GT82: WET | GU82: Weekly margins
C83: DRY (without breakfast) | CV83: 1577.5 | CW83: 4491.5 | CX83: 5962 | CY83: 6041.5 | CZ83: 5707.1 | DA83: 4941.3 | DB83: 5400.8 | DC83: 5799.9 | DD83: 5433.9 | DE83: 6890.65 | DF83: 7143.05 | DG83: 7033.25 | DH83: 7045.95 | DI83: 5272.4 | DJ83: 5385.25 | DK83: 4592.75 | DL83: 4623.75 | DM83: 4258.4 | DN83: 3351 | DO83: 4542.35 | DP83: 4281 | DQ83: 4369.4 | DR83: 3333.2 | DS83: 4043.55 | DT83: 4261.4 | DU83: 3315.75 | DV83: 3017.8 | DW83: 3172.15 | DX83: 4485.6 | DY83: 2539.9 | DZ83: 2198 | EA83: 3210.75 | EB83: 2732 | EC83: 2898.25 | ED83: 3538 | EE83: 3104 | EF83: 3650.1 | EG83: 4681.4 | EH83: =4886.85-281.5 -> 4605.35 | EI83: =4301.4-266.4 -> 4035 | EJ83: =5218-1013.35 -> 4204.65 | EK83: =5000.25-708.15 -> 4292.1 | EL83: =5024.75-172.9 -> 4851.85 | EM83: =5527.05-731.9 -> 4795.15 | EN83: =5436.6-687.2 -> 4749.4 | EO83: =5741.6-520.95 -> 5220.65 | EP83: =5166.25-805.2 -> 4361.05 | EQ83: =3914.25+1005 -> 4919.25 | ER83: 3843 | ES83: 3701.75 | ET83: 2678.4 | EU83: 3547.7 | EV83: 3677.65 | EW83: 13767 | EX83: 5273.05 | EY83: 4030.5 | EZ83: 4272.65 | FA83: 3826.1 | FB83: 4337.8 | FC83: 4141.5 | FD83: 4394.85 | FE83: 3679 | FF83: 4241.8 | FG83: =3176.5+2553.58 -> 5730.08 | FH83: 4076.15 | FI83: 4005.35 | FJ83: 3358.7 | FK83: 3547.8 | FL83: 3938.85 | FM83: 3989.3 | FN83: 3763.6 | FO83: 2967.5 | FP83: 2631.45 | FQ83: 2757.4 | FR83: 2288.5 | FS83: 3666.7 | FT83: 2339.45 | FU83: 906.6 | FV83: 2856.7 | FW83: 3087.25 | FX83: 3624.25 | FY83: 1966.55 | FZ83: 2740.75 | GA83: 1978.75 | GB83: 2650.4 | GC83: 2013.1 | GD83: 2839.55 | GE83: 1919.85 | GF83: 2548.1 | GG83: 3897.55 | GH83: 3376.1 | GI83: 3127.45 | GJ83: 3612.7 | GK83: 4278.6 | GL83: 3931.5 | GM83: 4611.85 | GN83: 4523.15 | GO83: 2675.7 | GP83: 5053.35 | GQ83: 4600.65 | GR83: 4176.45 | GS83: =EQ83 -> 4919.25 | GT83: DRY | GU83: Labour % | GV83: =LABOUR!AG64 -> 0.20227628
C84: DELIVEROO (after commission) | DT84: =2775.35/1.2 -> 2312.7917 | DU84: =632.5/1.2 -> 527.08333 | DV84: =2629.84/1.2 -> 2191.5333 | DW84: =1956.8/1.2 -> 1630.6667 | DX84: =1838.44/1.2 -> 1532.0333 | DY84: 0 | DZ84: =958.55/1.2 -> 798.79167 | EA84: =1979.56/1.2 -> 1649.6333 | EB84: 1728.76 | EC84: 2164.73 | ED84: 1673.95 | EE84: 2859.55 | EF84: 1763.99 | EG84: 2256.45 | EH84: 1471.66 | EI84: 1543.28 | EJ84: 1022.38 | EK84: 1494.41 | EL84: 597.78 | EM84: 1281.8 | EN84: 203.4 | EO84: 639.3 | EP84: 596.19 | EQ84: 348.95 | ER84: 527.69 | ES84: 477.26 | ET84: 663.76 | EU84: 537.14 | EV84: 586.34 | EW84: 1014.27 | EX84: 898.66 | EY84: 784.26 | EZ84: 875.25 | FA84: 786 | FB84: 846.33 | FC84: 600.33 | FD84: 745 | FE84: =957.75*0.6 -> 574.65 | FF84: 774 | FG84: 650.19 | FH84: 1019.19 | FI84: 1343 | FJ84: 1500.5 | FK84: 1493.5 | FL84: 1669.25 | FM84: 1150.2 | FN84: 1497.5 | FO84: 1196.7 | FP84: 1095.16 | FQ84: 932.5 | FR84: 961.34 | FS84: =1558.75*0.66 -> 1028.775 | FT84: 791.24 | FU84: =249.5*0.6 -> 149.7 | FV84: 1195.48 | FW84: 572.03 | FX84: 1467 | FY84: 579.51 | FZ84: 814.97 | GA84: =1726.67*0.6 -> 1036.002 | GB84: 1005.84 | GC84: 1039.61 | GD84: 1545.7 | GE84: 610.03 | GF84: 921.57 | GG84: 1172.09 | GH84: 1066 | GI84: 837.87 | GJ84: 987.35 | GK84: 1170 | GL84: 1185 | GM84: 2010 | GN84: 1130.67 | GO84: 828.32 | GP84: 957 | GQ84: 1568.21 | GR84: =1536.04*0.65 -> 998.426 | GS84: =EQ84 -> 348.95 | GT84: DELIVEROO INCOME
B85: Site total | CV85: =+CV82+CV83 -> 6283.7 | CW85: =+CW82+CW83 -> 13601.4 | CX85: =+CX82+CX83 -> 17242.4 | CY85: =+CY82+CY83 -> 16741.2 | CZ85: =+CZ82+CZ83 -> 14291.15 | DA85: =+DA82+DA83 -> 15137.2 | DB85: =+DB82+DB83 -> 13627.35 | DC85: =+DC82+DC83 -> 17423.35 | ... DQ85: =+DQ82+DQ83 -> 11745.35 | DR85: =+DR82+DR83+DR84 -> 11209.65 | DS85: =+DS82+DS83+DS84 -> 11836.8 | DT85: =+DT82+DT83+DT84 -> 13744.042 | DU85: =+DU82+DU83+DU84 -> 14754.883 | DV85: =+DV82+DV83+DV84 -> 12624.333 | DW85: =+DW82+DW83+DW84 -> 14185.367 | DX85: =+DX82+DX83+DX84 -> 18860.733 | DY85: =+DY82+DY83+DY84 -> 8073.7 | ... FL85: =+FL82+FL83+FL84 -> 17044.7 | FM85: =+FM83+FM82+FM84 -> 17703.6 | FN85: =+FN83+FN82+FN84 -> 17501.2 | FO85: =+FO83+FO82+FO84 -> 14278.5 | FP85: =+FP83+FP82+FP84 -> 13743.61 | FQ85: =+FQ83+FQ82+FQ84 -> 11516 | FR85: =+FR83+FR82+FR84 -> 13112.04 | FS85: =+FS83+FS82+FS84 -> 15379.575 | FT85: =+FT83+FT82+FT84 -> 12809.29 | ... GR85: =+GR83+GR82+GR84 -> 22644.276 | GS85: =GS82+GS83+GS84 -> 33688.26 | GT85: =B82 -> HETTIE BELLS | GW85: =AVERAGE(ES85:GR85) -> 17860.15 | GX85: =AVERAGE(FS85:GR85) -> 17080.993 | GY85: =AVERAGE(GF85:GR85) -> 19296.326 | GZ85: =AVERAGE(GN85:GR85) -> 20564.865 | HA85: =MAX(D85:GR85) -> 33688.26
B86: vs last week % | CW86: =SUM(CW85-CV85) -> 7317.7 | CX86: =SUM(CX85-CW85) -> 3641 | CY86: =SUM(CY85-CX85) -> -501.2 | CZ86: =SUM(CZ85-CY85) -> -2450.05 | DA86: =SUM(DA85-CZ85) -> 846.05 | DB86: =SUM(DB85-DA85) -> -1509.85 | DC86: =SUM(DC85-DB85) -> 3796 | DD86: =SUM(DD85-DC85) -> -728.8 | ... DH86: =SUM(DH85-DG85) -> 2463.65 | DI86: =SUM(DI85-DH85)/DH85 -> -0.28575211 | DJ86: =SUM(DJ85-DI85)/DI85 -> 0.0048114939 | DK86: =SUM(DK85-DJ85)/DJ85 -> -0.014179165 | DL86: =SUM(DL85-DK85)/DK85 -> -0.082007933 | DM86: =SUM(DM85-DL85)/DL85 -> -0.065439935 | DN86: =SUM(DN85-DM85)/DM85 -> -0.080494147 | DO86: =SUM(DO85-DN85)/DN85 -> 0.1672163 | DP86: =SUM(DP85-DO85)/DO85 -> 0.014235123 | ... GK86: =SUM(GK85-GJ85)/GJ85 -> 0.41491341 | GL86: =(GL85-GK85)/GK85 -> -0.29421372 | GM86: =(GM85-GL85)/GL85 -> 0.25394937 | GN86: =(GN85-GM85)/GM85 -> -0.10171295 | GO86: =(GO85-GN85)/GN85 -> -0.2452281 | GP86: =(GP85-GO85)/GO85 -> 0.42329894 | GQ86: =(GQ85-GP85)/GP85 -> 0.10163719 | GR86: =(GR85-GQ85)/GQ85 -> -0.042462976
B87: Same week last year | BD87: =D85 -> 0 | EV87: =CV85 -> 6283.7 | EW87: =CW85 -> 13601.4 | EX87: =CX85 -> 17242.4 | EY87: =CY85 -> 16741.2 | EZ87: =CZ85 -> 14291.15 | FA87: =DA85 -> 15137.2 | FB87: =DB85 -> 13627.35 | FC87: =DC85 -> 17423.35 | ... GL87: =EL85 -> 15786.93 | GM87: =EL85 -> 15786.93 | GN87: =EM85 -> 19535.65 | GO87: =EN85 -> 18332.25 | GP87: =EO85 -> 18604.7 | GQ87: =EP85 -> 16032.54 | GR87: =EQ85 -> 33688.26
B88: vs SWLY % | EV88: =(EV85-EV87)/EV87 -> 1.4268488 | EW88: =(EW85-EW87)/EW87 -> 0.96362654 | EX88: =(EX85-EX87)/EX87 -> 0.40640572 | EY88: =(EY85-EY87)/EY87 -> 0.32644673 | EZ88: =(EZ85-EZ87)/EZ87 -> 0.58037457 | FA88: =(FA85-FA87)/FA87 -> 0.3769244 | FB88: =(FB85-FB87)/FB87 -> 0.31710347 | FC88: =(FC85-FC87)/FC87 -> 0.15209647 | ... GR88: =(GR85-GR87)/GR87 -> -0.32782886
A90: MARKET TAVERN | B90: MARKET TAVERN | C90: WET | CL90: 13074.09 | CM90: 14333.1 | CN90: 12574.13 | CO90: 11744.67 | CP90: 9835.43 | CQ90: 11269.88 | CR90: 13421.21 | CS90: 12873.18 | CT90: 15138.24 | CU90: 14813.51 | CV90: 12239.8 | CW90: 12172.88 | CX90: 15039.88 | CY90: 15740.7 | CZ90: 10694.56 | DA90: 14919.02 | DB90: 15032.16 | DC90: 17662.15 | DD90: 19291.11 | DE90: 16695.636 | DF90: 19283.43 | DG90: 16982.5 | DH90: 20013.39 | DI90: 10374.34 | DJ90: 13517.28 | DK90: 14785.44 | DL90: 10838.96 | DM90: 10957.88 | DN90: 10256.25 | DO90: 9424.45 | DP90: =12246.91+2540 -> 14786.91 | DQ90: 11567.5 | DR90: 12729.3 | DS90: 11896.7 | DT90: 11270.8 | DU90: 13738.26 | DV90: 16147.38 | DW90: 19768 | DX90: 21138 | DY90: 20303.9 | DZ90: 11761.55 | EA90: 9104.8 | EB90: 9391.3 | EC90: 11526.45 | ED90: 11592.25 | EE90: 10701.35 | EF90: 13022 | EG90: 13494.55 | EH90: 12466.85 | EI90: 11288.7 | EJ90: 11269.9 | EK90: 11990.52 | EL90: 16303.7 | EM90: 17186.95 | EN90: 17846.69 | EO90: 18547.3 | EP90: 17164.46 | EQ90: 26563.12 | ER90: 16550.98 | ES90: 17704.86 | ET90: 22997.2 | EU90: 19272.58 | EV90: 16725.46 | EW90: 21287.13 | EX90: 24652.54 | EY90: 22422.6 | EZ90: 24189.15 | FA90: 26088.26 | FB90: 21277.02 | FC90: 21291.26 | FD90: 20930.56 | FE90: 22333.1 | FF90: 23785.9 | FG90: 20445 | FH90: 19391.8 | FI90: 18445.86 | FJ90: 12635.98 | FK90: 15195.67 | FL90: 16201.4 | FM90: 13460.3 | FN90: 16503.94 | FO90: 12561.14 | GS90: =EJ90 -> 11269.9 | GT90: WET
C91: DRY | CL91: 1343.5 | CM91: 2506 | CN91: 345 | CO91: =2113.75-1956.75 -> 157 | CP91: 173.5 | CQ91: 143 | CR91: 131.75 | CS91: 72 | CT91: 175.5 | CU91: 213 | CV91: 170.75 | CW91: 163.5 | CX91: 142.75 | CY91: 144 | CZ91: 158.5 | DA91: =3656.75-3452.75 -> 204 | DB91: 139.5 | DC91: 203 | DD91: 116 | DE91: 115.5 | DF91: 128 | DG91: 167 | DH91: 132.5 | DI91: 72 | DJ91: 114 | DK91: 117 | DL91: 82 | DM91: 120 | DN91: 115.5 | DO91: 57 | DP91: 331 | DQ91: 223.1 | DR91: 268.1 | DS91: 197.2 | DT91: 206.2 | DU91: =115.5+187.2 -> 302.7 | DV91: 272.5 | DW91: =118.5+182.8 -> 301.3 | DX91: =340.5+154.4 -> 494.9 | DY91: =321+218.4 -> 539.4 | DZ91: =175.5+132.8 -> 308.3 | EA91: 252.5 | EB91: =93+126.4 -> 219.4 | EC91: =141+198.4 -> 339.4 | ED91: =229+174.8 -> 403.8 | EE91: =116+131 -> 247 | EF91: =93+194.4 -> 287.4 | EG91: 217.3 | EH91: 315 | EI91: =168+114 -> 282 | EJ91: =103.5+193.6 -> 297.1 | EK91: =147.5+190.4 -> 337.9 | EL91: =115.5+130.8 -> 246.3 | EM91: =248+157.2 -> 405.2 | EN91: 389.05 | EO91: 382.2 | EP91: =133.5+126.4 -> 259.9 | EQ91: =266.5+169.6 -> 436.1 | ER91: 337.3 | ES91: =156+213.6 -> 369.6 | ET91: =208.5+126.4 -> 334.9 | EU91: =156+171.2 -> 327.2 | EV91: =180.5+151.2 -> 331.7 | EW91: =166.5+162.4 -> 328.9 | EX91: 259.2 | EY91: =156.75+133.6 -> 290.35 | EZ91: 169.5 | FA91: =102.4+181.5 -> 283.9 | FB91: =172.5+164.8 -> 337.3 | FC91: =196.5+202.4 -> 398.9 | FD91: =183+202.4 -> 385.4 | FE91: =180+182.8 -> 362.8 | FF91: =181.5+117.2 -> 298.7 | FG91: =151.5+137.6 -> 289.1 | FH91: 312.4 | FI91: =109.5+211.2 -> 320.7 | FJ91: 255.2 | FK91: 267 | FL91: =156+231.6 -> 387.6 | FM91: =118.5+176.8 -> 295.3 | FN91: =189+200.8 -> 389.8 | FO91: =102+90.2 -> 192.2 | GS91: =EJ91 -> 297.1 | GT91: DRY
B92: Site total | CL92: =+CL90+CL91 -> 14417.59 | CM92: =+CM90+CM91 -> 16839.1 | CN92: =+CN90+CN91 -> 12919.13 | CO92: =+CO90+CO91 -> 11901.67 | CP92: =+CP90+CP91 -> 10008.93 | CQ92: =+CQ90+CQ91 -> 11412.88 | CR92: =+CR90+CR91 -> 13552.96 | CS92: =+CS90+CS91 -> 12945.18 | ... FO92: =+FO90+FO91 -> 12753.34 | FP92: =8925.2+137.1 -> 9062.3 | FQ92: =13025.7+206.8 -> 13232.5 | FR92: =14726.58+242.8 -> 14969.38 | FS92: =13812.06+240.4 -> 14052.46 | FT92: =14855.2+280.3 -> 15135.5 | FU92: =17255.1+325.8 -> 17580.9 | FV92: =19155.2+274.8 -> 19430 | FW92: =24353.94+290.3 -> 24644.24 | FX92: =24764.2+149 -> 24913.2 | FY92: =25392.2+497+120 -> 26009.2 | FZ92: =17988.4+402.2+440 -> 18830.6 | GA92: =10103+199 -> 10302 | GB92: =10602.1+186.3 -> 10788.4 | GC92: =12396.2+201 -> 12597.2 | GD92: =13608.9+245.9 -> 13854.8 | GE92: =10654.3+132.2 -> 10786.5 | GF92: =13842.1+195.7 -> 14037.8 | GG92: =14332.5+330.1 -> 14662.6 | GH92: =14737.5+196.7 -> 14934.2 | GI92: =14628.2+132.2 -> 14760.4 | GJ92: =12166.8+128.6 -> 12295.4 | GK92: =18890.78+214.4 -> 19105.18 | GL92: =15152.8+191.7 -> 15344.5 | GM92: 23812.8 | GN92: =20095.4+224.9 -> 20320.3 | GO92: =17990.8+798 -> 18788.8 | GP92: =29178.6+236.3 -> 29414.9 | GQ92: =141+27473.49 -> 27614.49 | GR92: =19360.8+260.4 -> 19621.2 | GS92: =EQ92 -> 26999.22 | GT92: =B90 -> MARKET TAVERN | GU92: Weekly margins | GW92: =AVERAGE(ES92:GR92) -> 18420.925 | GX92: =AVERAGE(FS92:GR92) -> 17832.214 | GY92: =AVERAGE(GF92:GR92) -> 18824.044 | GZ92: =AVERAGE(GN92:GR92) -> 23151.938 | HA92: =MAX(D92:GR92) -> 29414.9
B93: vs last week % | CL93: =SUM(CL92-CK92)/CK92 -> #DIV/0! | CM93: =SUM(CM92-CL92)/CL92 -> 0.16795525 | CN93: =SUM(CN92-CM92)/CM92 -> -0.23278976 | CO93: =SUM(CO92-CN92)/CN92 -> -0.078756077 | CP93: =SUM(CP92-CO92)/CO92 -> -0.15903146 | CQ93: =SUM(CQ92-CP92)/CP92 -> 0.14026974 | CR93: =SUM(CR92-CQ92)/CQ92 -> 0.18751446 | CS93: =SUM(CS92-CR92)/CR92 -> -0.044844816 | ... GK93: =SUM(GK92-GJ92)/GJ92 -> 0.55384778 | GL93: =(GL92-GK92)/GK92 -> -0.19684086 | GM93: =(GM92-GL92)/GL92 -> 0.55187852 | GN93: =(GN92-GM92)/GM92 -> -0.14666482 | GO93: =(GO92-GN92)/GN92 -> -0.075367982 | GP93: =(GP92-GO92)/GO92 -> 0.56555501 | GQ93: =(GQ92-GP92)/GP92 -> -0.061207415 | GR93: =(GR92-GQ92)/GQ92 -> -0.28945999 | GU93: Labour % | GV93: =LABOUR!AG68 -> 0.20916152
B94: Same week last year | EL94: =CL92 -> 14417.59 | EM94: =CM92 -> 16839.1 | EN94: =CN92 -> 12919.13 | EO94: =CO92 -> 11901.67 | EP94: =CP92 -> 10008.93 | EQ94: =CQ92 -> 11412.88 | ER94: =CR92 -> 13552.96 | ES94: =CS92 -> 12945.18 | ... GL94: =EL92 -> 16550 | GM94: =EL92 -> 16550 | GN94: =EM92 -> 17592.15 | GO94: =EN92 -> 18235.74 | GP94: =EO92 -> 18929.5 | GQ94: =EP92 -> 17424.36 | GR94: =EQ92 -> 26999.22
B95: vs SWLY % | EL95: =(EL92-EL94)/EL94 -> 0.14790336 | EM95: =(EM92-EM94)/EM94 -> 0.044720324 | EN95: =(EN92-EN94)/EN94 -> 0.41153003 | EO95: =(EO92-EO94)/EO94 -> 0.59049108 | EP95: =(EP92-EP94)/EP94 -> 0.74088139 | EQ95: =(EQ92-EQ94)/EQ94 -> 1.3656798 | ER95: =(ER92-ER94)/ER94 -> 0.24609532 | ES95: =(ES92-ES94)/ES94 -> 0.39623088 | ... GR95: =(GR92-GR94)/GR94 -> -0.27326789
A97: FIVE BELLS | B97: FIVE BELLS | C97: WET | D97: 5006.15 | E97: 5506.5 | F97: 6309.3 | G97: 7605.95 | H97: 8111.85 | I97: 5932.95 | J97: 7083.3 | K97: 5567.3 | L97: 7176.85 | M97: 7085.2 | N97: 7722.3 | O97: 6292.2 | P97: 9326.95 | Q97: 6342.05 | R97: 7547 | S97: 6816.6 | T97: 6506.65 | U97: 10760.3 | V97: 8035.95 | W97: 10903.3 | X97: 22281.2 | Y97: 15216.9 | Z97: 7108.55 | AA97: 8412.15 | AB97: 8397.9 | AC97: 7929.8 | AD97: 10693.3 | AE97: 10623.15 | AF97: 9137.5 | AG97: 9906.15 | AH97: 9826.6 | AI97: 13667.55 | AJ97: 10185.4 | AK97: 10517.3 | AL97: 13567.2 | AM97: 17645.55 | AN97: 11188.85 | AO97: 11659.6 | AP97: 15304.7 | AQ97: 11298.9 | AR97: 4271.6 | AS97: 6521.7 | AT97: 6972.6 | AU97: 7270.1 | AV97: 6160.65 | AW97: 11029.65 | AX97: 8315.1 | AY97: 8533.75 | AZ97: 6676.5 | BA97: 8849.45 | BB97: 8036.95 | BC97: 7520.3 | BD97: 7596.35 | BE97: 6679.15 | BF97: 7030.55 | BG97: 8616.2 | BH97: 7897.15 | BI97: 7141.15 | BJ97: 8287.3 | BK97: 6760.6 | BL97: 9421.75 | BM97: 8835.1 | BN97: 7227.75 | BO97: 7571.15 | BP97: 6616.65 | BQ97: 9951.8 | BR97: 8505.05 | BS97: 11310.25 | BT97: 9894.15 | BU97: 11328.4 | BV97: 11508.15 | BW97: 14791.3 | BX97: 28641.8 | BY97: 16548.95 | BZ97: 9285.2 | CA97: 8004.8 | CB97: 7578.3 | CC97: 8590.8 | CD97: 9768.34 | CE97: 9873.75 | CF97: 11354.2 | CG97: 8289.8 | CH97: 8905.5 | CI97: 10001.75 | CJ97: 11074 | CK97: 9872.85 | CL97: 15771.3 | CM97: 11179.3 | CN97: 10369.2 | CO97: 9105.85 | CP97: 10170.6 | CQ97: 13919.7 | CR97: 9375.4 | CS97: 9875.6 | CT97: 10687.6 | CU97: 9827.9 | CV97: 8951.8 | CW97: 14605.8 | CX97: 12625.6 | CY97: 14983.1 | CZ97: 13055.4 | DA97: 17399.65 | DB97: 5000 | DC97: 8285.7 | DD97: 9512.95 | DE97: 8879.35 | DF97: 9699.9 | DG97: 11183.9 | DH97: 8840.65 | DI97: 9921.5 | DJ97: 8863.35 | DK97: 9525.5 | DL97: 10173.5 | DM97: 10201.25 | DN97: 10040.3 | DO97: 8122.95 | DP97: 10017.15 | DQ97: 11089.55 | DR97: 10555.4 | DS97: 9848.3 | DT97: 11493.85 | DU97: 10740.85 | DV97: 14871.45 | DW97: 15141.9 | DX97: 21897.1 | DY97: 28189.5 | DZ97: 12529.5 | EA97: 9700 | EB97: 8720.25 | EC97: 9913.5 | ED97: 13116.09 | EE97: 11740.62 | EF97: 9256.38 | EG97: 10952.85 | EH97: 10687.06 | EI97: 10591.1 | EJ97: 12740.75 | EK97: 12214.55 | EL97: 11339.05 | EM97: 10600.75 | EN97: 9974.65 | EO97: 15992.1 | EP97: 11120.9 | EQ97: 12185.85 | ER97: 11184.5 | ES97: 11560.1 | ET97: 10417.65 | EU97: 12773 | EV97: 10822.1 | EW97: 11298.15 | EX97: 10540.6 | EY97: 8340.15 | EZ97: 8308.1 | FA97: 9383.75 | FB97: 9135.1 | FC97: 11601.6 | FD97: 10396.75 | FE97: 9385.55 | FF97: 8610.6 | FG97: 10740.35 | FH97: 10717.55 | FI97: 10040.45 | FJ97: 11681.15 | FK97: 10658.9 | FL97: 9262.55 | FM97: 10150.85 | FN97: 8903.45 | FO97: 8570.25 | GS97: =EJ97 -> 12740.75 | GT97: WET
C98: DRY | D98: 82.5 | E98: 85 | F98: 103 | G98: 96 | H98: 151 | I98: 112.5 | J98: 99 | K98: 93.5 | L98: 96 | M98: 93.5 | N98: 107.5 | O98: 62.5 | P98: 87.5 | Q98: 65 | R98: 73.5 | S98: 91.5 | T98: 82.5 | U98: 122 | V98: 107.5 | W98: 93 | X98: 146.5 | Y98: 130 | Z98: 103 | AA98: 93 | AB98: 75 | AC98: 112 | AD98: 96 | AE98: 125 | AF98: 244.5 | AG98: 299 | AH98: 120 | AI98: 111 | AJ98: 101 | AK98: 128 | AL98: 126 | AM98: 112.5 | AN98: 111 | AO98: 123 | AP98: 123 | AQ98: 98 | AR98: 52 | AS98: 82.5 | AT98: 94 | AU98: 81 | AV98: 59.5 | AW98: 88.5 | AX98: 72 | AY98: 85 | AZ98: 95 | BA98: 86.5 | BB98: 113.5 | BC98: 86.5 | BD98: 107 | BE98: 94.5 | BF98: 101 | BG98: 90 | BH98: 79 | BI98: 89.5 | BJ98: 92.5 | BK98: 104.5 | BL98: 106 | BM98: 108.5 | BN98: 103.5 | BO98: 68 | BP98: 68.5 | BQ98: 98.5 | BR98: 120 | BS98: 112 | BT98: 87.5 | BU98: 143 | BV98: 89.5 | BW98: 173 | BX98: 186 | BY98: 135.5 | BZ98: 84 | CA98: 74.5 | CB98: 86.5 | CC98: 87.5 | CD98: 101 | CE98: 124 | CF98: 107 | CG98: 94 | CH98: 93 | CI98: 112 | CJ98: 119.5 | CK98: 95.5 | CL98: 128.5 | CM98: 116 | CN98: 100 | CO98: 109 | CP98: 80.5 | CQ98: 102.5 | CR98: 104 | CS98: 94 | CT98: 94 | CU98: 112.5 | CV98: 91 | CW98: 125.5 | CX98: 117 | CY98: 125 | CZ98: 113.5 | DA98: 101 | DB98: 208.7 | DC98: 80 | DD98: 68.5 | DE98: 73 | DF98: 93.5 | DG98: 125 | DH98: 86.5 | DI98: 64 | DJ98: 68 | DK98: 102 | DL98: 70.5 | DM98: 123 | DN98: 77 | DO98: 57.5 | DP98: 85 | DQ98: 105 | DR98: 106 | DS98: 111.5 | DT98: 102 | DU98: 91.5 | DV98: 97 | DW98: 125 | DX98: 255.5 | DY98: 235 | DZ98: 138 | EA98: 138 | EB98: 103 | EC98: 176.55 | ED98: 228.41 | EE98: 184.08 | EF98: 127.52 | EG98: 198.1 | EH98: 144.44 | EI98: 252 | EJ98: 192 | EK98: 159 | EL98: 155 | EM98: 170.5 | EN98: 126 | EO98: 149 | EP98: 123.65 | EQ98: 127.6 | ER98: 129.8 | ES98: 181.1 | ET98: 179.75 | EU98: 123.4 | EV98: 176.1 | EW98: 191.1 | EX98: 146.85 | EY98: 159.9 | EZ98: 95.7 | FA98: 102.35 | FB98: 122.6 | FC98: 130 | FD98: 104.2 | FE98: 104.9 | FF98: 124 | FG98: 133.6 | FH98: 153.6 | FI98: 130.2 | FJ98: 104.4 | FK98: 110.4 | FL98: 110 | FM98: 130 | FN98: 145.5 | FO98: 72.1 | GS98: =EJ98 -> 192 | GT98: DRY
B99: Site total | D99: =SUM(D97:D98) -> 5088.65 | E99: =SUM(E97:E98) -> 5591.5 | F99: =SUM(F97:F98) -> 6412.3 | G99: =SUM(G97:G98) -> 7701.95 | H99: =SUM(H97:H98) -> 8262.85 | I99: =SUM(I97:I98) -> 6045.45 | J99: =SUM(J97:J98) -> 7182.3 | K99: =SUM(K97:K98) -> 5660.8 | ... FO99: =SUM(FO97:FO98) -> 8642.35 | FP99: =10784.6+195.6 -> 10980.2 | FQ99: =13059.9+118.2 -> 13178.1 | FR99: =11139.4+121 -> 11260.4 | FS99: =11131.75+126.1 -> 11257.85 | FT99: =11161.45+94.6 -> 11256.05 | FU99: =9910.05+134.9 -> 10044.95 | FV99: =12206.15+174.4 -> 12380.55 | FW99: =13537.1+144.3 -> 13681.4 | FX99: =24161.95+186.2 -> 24348.15 | FY99: =31020.2+230.3 -> 31250.5 | FZ99: =14949.8+116.7 -> 15066.5 | GA99: =13402.25+85.4 -> 13487.65 | GB99: =14502.9+123.9 -> 14626.8 | GC99: =14619.9+113.3 -> 14733.2 | GD99: =14777.45+163.4 -> 14940.85 | GE99: =15604.8+114.3 -> 15719.1 | GF99: =12804.9+122.3 -> 12927.2 | GG99: =10964.8+129.8 -> 11094.6 | GH99: =9570.85+147.4 -> 9718.25 | GI99: =8488.16+163.3 -> 8651.46 | GJ99: =124.6+9964.7 -> 10089.3 | GK99: =8124.5+140.3 -> 8264.8 | GL99: =9830.2+165.6 -> 9995.8 | GM99: =19496.25+238.7 -> 19734.95 | GN99: =10744.6+158.8 -> 10903.4 | GO99: =126.4+9858.1 -> 9984.5 | GP99: =9495.85+262.1 -> 9757.95 | GQ99: =12986.4+159.1 -> 13145.5 | GR99: =9614.75+272.2 -> 9886.95 | GS99: =EQ99 -> 12313.45 | GT99: =B97 -> FIVE BELLS | GU99: Weekly margins | GW99: =AVERAGE(ES99:GR99) -> 11898.026 | GX99: =AVERAGE(FS99:GR99) -> 13344.162 | GY99: =AVERAGE(GF99:GR99) -> 11088.82 | GZ99: =AVERAGE(GN99:GR99) -> 10735.66 | HA99: =MAX(D99:GR99) -> 31250.5
B100: vs last week % | E100: =SUM(E99-D99) -> 502.85 | F100: =SUM(F99-E99) -> 820.8 | G100: =SUM(G99-F99) -> 1289.65 | H100: =SUM(H99-G99) -> 560.9 | I100: =SUM(I99-H99) -> -2217.4 | J100: =SUM(J99-I99) -> 1136.85 | K100: =SUM(K99-J99) -> -1521.5 | L100: =SUM(L99-K99) -> 1612.05 | ... DN100: =SUM(DN99-DM99) -> -206.95 | DO100: =SUM(DO99-DN99)/DN99 -> -0.19143942 | DP100: =SUM(DP99-DO99)/DO99 -> 0.23491373 | DQ100: =SUM(DQ99-DP99)/DP99 -> 0.1081354 | DR100: =SUM(DR99-DQ99)/DQ99 -> -0.047625854 | DS100: =SUM(DS99-DR99)/DR99 -> -0.065807492 | DT100: =SUM(DT99-DS99)/DS99 -> 0.16426535 | DU100: =SUM(DU99-DT99)/DT99 -> -0.065842521 | DV100: =SUM(DV99-DU99)/DU99 -> 0.3818285 | ... GK100: =SUM(GK99-GJ99)/GJ99 -> -0.18083514 | GL100: =(GL99-GK99)/GK99 -> 0.20944245 | GM100: =(GM99-GL99)/GL99 -> 0.97432422 | GN100: =(GN99-GM99)/GM99 -> -0.4475081 | GO100: =(GO99-GN99)/GN99 -> -0.084276464 | GP100: =(GP99-GO99)/GO99 -> -0.02269017 | GQ100: =(GQ99-GP99)/GP99 -> 0.34715796 | GR100: =(GR99-GQ99)/GQ99 -> -0.24788331 | GU100: Labour % | GV100: =LABOUR!AG72 -> 0.14576791
B101: Same week last year | BD101: =D99 -> 5088.65 | BE101: =E99 -> 5591.5 | BF101: =F99 -> 6412.3 | BG101: =G99 -> 7701.95 | BH101: =H99 -> 8262.85 | BI101: =I99 -> 6045.45 | BJ101: =J99 -> 7182.3 | BK101: =K99 -> 5660.8 | ... GL101: =EL99 -> 11494.05 | GM101: =EL99 -> 11494.05 | GN101: =EM99 -> 10771.25 | GO101: =EN99 -> 10100.65 | GP101: =EO99 -> 16141.1 | GQ101: =EP99 -> 11244.55 | GR101: =EQ99 -> 12313.45
B102: vs SWLY % | BD102: =(BD99-BD101)/BD101 -> 0.5138298 | BE102: =(BE99-BE101)/BE101 -> 0.21141912 | BF102: =(BF99-BF101)/BF101 -> 0.11216724 | BG102: =(BG99-BG101)/BG101 -> 0.13038906 | BH102: =(BH99-BH101)/BH101 -> -0.034697471 | BI102: =(BI99-BI101)/BI101 -> 0.19604827 | BJ102: =(BJ99-BJ101)/BJ101 -> 0.16672932 | BK102: =(BK99-BK101)/BK101 -> 0.21274378 | ... GR102: =(GR99-GR101)/GR101 -> -0.19706094
A104: SAM WELLERS | B104: SAM WELLERS | C104: WET | D104: 6326.6 | E104: 6926.5 | F104: 6773.45 | G104: 7219.65 | H104: 8467 | I104: 7525.7 | J104: 7312.9 | K104: 8876.3 | L104: 6888.25 | M104: 9432.45 | N104: 6142.8 | O104: 8935.45 | P104: 8786.05 | Q104: 8314.8 | R104: 10195.35 | S104: 9541.5 | T104: 13037.95 | U104: 23006.1 | V104: 22884.35 | W104: 13429.9 | X104: 10558.9 | Y104: 13131.4 | Z104: 8881.05 | AA104: 7828.95 | AB104: 9140.55 | AC104: 9027.85 | AD104: 9009.65 | AE104: 10276.2 | AF104: 12087.3 | AG104: 11429.75 | AH104: 10296.35 | AI104: 11052.45 | AJ104: 11118.4 | AK104: 11065.3 | AL104: 9613.7 | AM104: 10177.05 | AN104: 8898.5 | AO104: 8277.85 | AP104: 9684.8 | AQ104: 11402.8 | AR104: 8075.55 | AS104: 9556.95 | AT104: 9188.4 | AU104: 8640.05 | AV104: 7546.45 | AW104: 7706.4 | AX104: 6945.7 | AY104: 7984.55 | AZ104: 7174.45 | BA104: 7866.5 | BB104: 7929.55 | BC104: 9000.5 | BD104: 9782.4 | BE104: 8551.95 | BF104: 10826.65 | BG104: 9540.85 | BH104: 8226.65 | BI104: 2035 | BJ104: 4083.15 | BK104: 10992.6 | BL104: 9538.7 | BM104: 10031.05 | BN104: 10756.8 | BO104: 9988.85 | BP104: 11875.45 | BQ104: 10965.65 | BR104: 10705.15 | BS104: 13847.9 | BT104: 17969.15 | BU104: 24796.45 | BV104: 22568.8 | BW104: 15868.4 | BX104: 18105.45 | BY104: 15058.95 | BZ104: 8256.55 | CA104: 8188.75 | CB104: 8054.6 | CC104: 7517.65 | CD104: 7425.6 | CE104: 8991.65 | CF104: 9390.85 | CG104: 9150.5 | CH104: 9491.6 | CI104: 9655.95 | CJ104: 9085.15 | CK104: 9774.45 | CL104: 9231.15 | CM104: 7559.3 | CN104: 8940.2 | CO104: 8875 | CP104: 12059.9 | CQ104: 9851.85 | CR104: 8994.7 | CS104: 12501.35 | CT104: 8331.7 | CU104: 11585.1 | CV104: 8992 | CW104: 10988.03 | CX104: 8479.4 | CY104: 9010.45 | CZ104: 8319.43 | DA104: 10057.75 | DB104: 8448.97 | DC104: 9113.3 | DD104: 8074.3 | DE104: 8733.7 | DF104: 10396.8 | DG104: 10508.05 | DH104: 10745.4 | DI104: 9349.9 | DJ104: 9888.25 | DK104: 11341.6 | DL104: 10461.85 | DM104: 13366.05 | DN104: 11395.55 | DO104: 11063.7 | DP104: 12932.05 | DQ104: 12567.7 | DR104: 11542.25 | DS104: 9848.3 | DT104: 14317.65 | DU104: 24308.85 | DV104: 21595.25 | DW104: 25554.75 | DX104: 18139.15 | DY104: 17670.58 | DZ104: 12821.4 | EA104: 9670.7 | EB104: 10913.65 | EC104: 11093.7 | ED104: 12824.5 | EE104: 13188.3 | EF104: 12935.2 | EG104: 12991.1 | EH104: 7839.35 | EI104: 13050.8 | EJ104: 13679.25 | EK104: 13820.75 | EL104: 13429.95 | EM104: 8845.9 | EN104: 8564.65 | EO104: 10959.45 | EP104: 12622 | EQ104: 10027.05 | ER104: 9858.75 | ES104: 10752.45 | ET104: 11206.35 | EU104: 11774.05 | EV104: 12852.6 | EW104: 11356.55 | EX104: 10603.1 | EY104: 10837.5 | EZ104: 9573.25 | FA104: 12589.95 | FB104: 12926.3 | FC104: =10982.95+45.6 -> 11028.55 | FD104: 10940.3 | FE104: 12004.2 | FF104: 12976.2 | FG104: 13297.9 | FH104: 14826.45 | FI104: 13229.35 | FJ104: 14686.15 | FK104: 15625.15 | FL104: 14470.1 | FM104: 17544.6 | FN104: 17544.6 | GS104: =DL104 -> 10461.85 | GT104: WET
C105: DRY | D105: 201 | E105: 161.5 | F105: 182.5 | G105: 157.5 | H105: 102.5 | I105: 88 | J105: 58.5 | K105: 125 | L105: 81.5 | M105: 83 | N105: 62 | O105: 113 | P105: 118.5 | Q105: 123 | R105: 166.5 | S105: 150.5 | T105: 137.5 | U105: 242.5 | V105: 194 | W105: 150 | X105: 112 | Y105: 189.5 | Z105: 111.5 | AA105: 101 | AB105: 102.5 | AC105: 68 | AD105: 94.5 | AE105: 132.5 | AF105: 153.5 | AG105: 116 | AH105: 99 | AI105: 139 | AJ105: 111.5 | AK105: 118.5 | AL105: 102 | AM105: 105 | AN105: 108 | AO105: 78 | AP105: 75 | AQ105: 124.5 | AR105: 69.5 | AS105: 61 | AT105: 83 | AU105: 81 | AV105: 88 | AW105: 74 | AX105: 85 | AY105: 66 | AZ105: 76 | BA105: 65.5 | BB105: 84 | BC105: 95 | BD105: 105 | BE105: 94.5 | BF105: 75 | BG105: 116.5 | BH105: 75 | BI105: 13 | BJ105: 635 | BK105: 1085.5 | BL105: 1306 | BM105: 98 | BN105: 115 | BO105: 136 | BP105: 294 | BQ105: 303 | BR105: 173.5 | BS105: 113.5 | BT105: 153 | BU105: 156 | BV105: 205 | BW105: 170 | BX105: 155 | BY105: 145 | BZ105: 48 | CA105: 75 | CB105: 73.5 | CC105: 101 | CD105: 85 | CE105: 70 | CF105: 83 | CG105: 88 | CH105: 94.5 | CI105: 88.5 | CJ105: 78 | CK105: 85.5 | CL105: 78 | CM105: 83 | CN105: 80 | CO105: 104 | CP105: 127 | CQ105: 121 | CR105: 79 | CS105: 88.8 | CT105: 102 | CU105: 99.6 | CV105: 135.6 | CW105: 142.8 | CX105: 109.8 | CY105: 81 | CZ105: 87 | DA105: 127.8 | DB105: 64.8 | DC105: 108.6 | DD105: 57.6 | DE105: 81 | DF105: 127.2 | DG105: 119.4 | DH105: 180.95 | DI105: 136.65 | DJ105: 130.45 | DK105: 188.75 | DL105: 151.05 | DM105: 124.7 | DN105: 125.05 | DO105: 122.85 | DP105: 160.35 | DQ105: 175.95 | DR105: 129.85 | DS105: 111.5 | DT105: 228.45 | DU105: 172.55 | DV105: 244.65 | DW105: 279.2 | DX105: 236.15 | DY105: 176.75 | DZ105: 167.2 | EA105: 130.6 | EB105: 141.2 | EC105: 127.2 | ED105: 181.8 | EE105: 162.55 | EF105: 162.4 | EG105: 170.6 | EH105: 75.3 | EI105: 169.7 | EJ105: 181.9 | EK105: 151.35 | EL105: 121.35 | EM105: 122.9 | EN105: 65.55 | EO105: 119.2 | EP105: 95.8 | EQ105: 143.95 | ER105: 94.4 | ES105: 108.6 | ET105: 122 | EU105: 94.8 | EV105: 133 | EW105: 95.8 | EX105: 121.9 | EY105: 118.35 | EZ105: 116.1 | FA105: 106.8 | FB105: 95.5 | FC105: 59.3 | FD105: 146.5 | FE105: 172.6 | FF105: 125.2 | FG105: 151.1 | FH105: 175.5 | FI105: 142.2 | FJ105: 185.7 | FK105: 149 | FL105: 145.5 | FM105: 149.5 | FN105: 149.5 | GS105: =DL105 -> 151.05 | GT105: DRY
B106: Site total | D106: =SUM(D104:D105) -> 6527.6 | E106: =SUM(E104:E105) -> 7088 | F106: =SUM(F104:F105) -> 6955.95 | G106: =SUM(G104:G105) -> 7377.15 | H106: =SUM(H104:H105) -> 8569.5 | I106: =SUM(I104:I105) -> 7613.7 | J106: =SUM(J104:J105) -> 7371.4 | K106: =SUM(K104:K105) -> 9001.3 | ... FM106: =SUM(FM104:FM105) -> 17694.1 | FN106: 16620 | FO106: =16396.4+204.7 -> 16601.1 | FP106: =18117.45+161.7 -> 18279.15 | FQ106: =18698.2+230.9 -> 18929.1 | FR106: =16974+160.4 -> 17134.4 | FS106: =17348.6+192 -> 17540.6 | FT106: =17743.6+185.1 -> 17928.7 | FU106: =26834.65+229.2 -> 27063.85 | FV106: =35764.55+225+42 -> 36031.55 | FW106: =27348.7+191.5+75.6 -> 27615.8 | FX106: =22173.1+136+50.4 -> 22359.5 | FY106: =20595.2+146.1+42 -> 20783.3 | FZ106: =20330+202+16.8 -> 20548.8 | GA106: =10492.15+124.3+33.6 -> 10650.05 | GB106: =15019.35+131.1 -> 15150.45 | GC106: =13826.9+176.9 -> 14003.8 | GD106: =14639.9+155+175.2 -> 14970.1 | GE106: =15598.85+138.7+285.6 -> 16023.15 | GF106: =16720.01+162.6+154 -> 17036.61 | GG106: =17757.1+198.2+195.6 -> 18150.9 | GH106: =15471.15+126+458.6 -> 16055.75 | GI106: =14637.15+145.9+563.85 -> 15346.9 | GJ106: =16031+344.4+171.1 -> 16546.5 | GK106: =17169.6+1104+145.6 -> 18419.2 | GL106: =13145.35+90.1+827.15 -> 14062.6 | GM106: =169+20066.15 -> 20235.15 | GN106: =15443.85+189.7+568.9 -> 16202.45 | GO106: =16047.85+114.3 -> 16162.15 | GP106: =11539.05+116.2 -> 11655.25 | GQ106: =15263.75+97.5 -> 15361.25 | GR106: =15373.2+103.1 -> 15476.3 | GS106: =EQ106 -> 10171 | GT106: =B104 -> SAM WELLERS | GU106: Weekly margins | GW106: =AVERAGE(ES106:GR106) -> 15899.239 | GX106: =AVERAGE(FS106:GR106) -> 18130.025 | GY106: =AVERAGE(GF106:GR106) -> 16208.539 | GZ106: =AVERAGE(GN106:GR106) -> 14971.48 | HA106: =MAX(D106:GR106) -> 36031.55
B107: vs last week % | E107: =SUM(E106-D106) -> 560.4 | F107: =SUM(F106-E106) -> -132.05 | G107: =SUM(G106-F106) -> 421.2 | H107: =SUM(H106-G106) -> 1192.35 | I107: =SUM(I106-H106) -> -955.8 | J107: =SUM(J106-I106) -> -242.3 | K107: =SUM(K106-J106) -> 1629.9 | L107: =SUM(L106-K106) -> -2031.55 | ... DH107: =SUM(DH106-DG106) -> 298.9 | DI107: =SUM(DI106-DH106)/DH106 -> -0.13177319 | DJ107: =SUM(DJ106-DI106)/DI106 -> 0.056095208 | DK107: =SUM(DK106-DJ106)/DJ106 -> 0.15088285 | DL107: =SUM(DL106-DK106)/DK106 -> -0.07956827 | DM107: =SUM(DM106-DL106)/DL106 -> 0.27116528 | DN107: =SUM(DN106-DM106)/DM106 -> -0.1460371 | DO107: =SUM(DO106-DN106)/DN106 -> -0.028995886 | DP107: =SUM(DP106-DO106)/DO106 -> 0.17036977 | ... GK107: =SUM(GK106-GJ106)/GJ106 -> 0.11317801 | GL107: =(GL106-GK106)/GK106 -> -0.23652493 | GM107: =(GM106-GL106)/GL106 -> 0.43893377 | GN107: =(GN106-GM106)/GM106 -> -0.19929183 | GO107: =(GO106-GN106)/GN106 -> -0.0024872782 | GP107: =(GP106-GO106)/GO106 -> -0.27885523 | GQ107: =(GQ106-GP106)/GP106 -> 0.3179683 | GR107: =(GR106-GQ106)/GQ106 -> 0.0074896249 | GU107: Labour % | GV107: =LABOUR!AG76 -> 0.15088878
B108: Same week last year | BD108: =D106 -> 6527.6 | BE108: =E106 -> 7088 | BF108: =F106 -> 6955.95 | BG108: =G106 -> 7377.15 | BH108: =H106 -> 8569.5 | BI108: =I106 -> 7613.7 | BJ108: =J106 -> 7371.4 | BK108: =K106 -> 9001.3 | ... GL108: =EL106 -> 13551.3 | GM108: =EL106 -> 13551.3 | GN108: =EM106 -> 8968.8 | GO108: =EN106 -> 8630.2 | GP108: =EO106 -> 11078.65 | GQ108: =EP106 -> 12717.8 | GR108: =EQ106 -> 10171
B109: vs SWLY % | BD109: =(BD106-BD108)/BD108 -> 0.51470678 | BE109: =(BE106-BE108)/BE108 -> 0.21987161 | BF109: =(BF106-BF108)/BF108 -> 0.567241 | BG109: =(BG106-BG108)/BG108 -> 0.30908955 | BH109: =(BH106-BH108)/BH108 -> -0.031256199 | BI109: =(BI106-BI108)/BI108 -> -0.7310112 | BJ109: =(BJ106-BJ108)/BJ108 -> -0.35993841 | BK109: =(BK106-BK108)/BK108 -> 0.34181729 | ... GR109: =(GR106-GR108)/GR108 -> 0.52161046
A111: WELLINGTON ARMS | B111: WELLINGTON ARMS | C111: WET | BT111: 4187.3 | BU111: 6198.5 | BV111: 5290.8 | BW111: 7021.25 | BX111: 13528.2 | BY111: 7669.25 | BZ111: 4791.05 | CA111: 4652.8 | CB111: 3773.95 | CC111: 5175.2 | CD111: 5079.85 | CE111: 4543.1 | CF111: 4669.91 | CG111: 4890 | CH111: 4702 | CI111: 6486.3 | CJ111: 6712.3 | CK111: 6883.4 | CL111: 7728.45 | CM111: 9151.85 | CN111: 7432.8 | CO111: 6624.4 | CP111: 6096.1 | CQ111: 8590.75 | CR111: 7403.4 | CS111: 5909.75 | CT111: 5754.7 | CU111: 7037.25 | CV111: 5881.45 | CW111: 6424.2 | CX111: 7328.45 | CY111: 7021.45 | CZ111: 5658.45 | DA111: 6967.85 | DB111: 5926.4 | DC111: 6699.1 | DD111: 7402.95 | DE111: 6986.65 | DF111: 6675.45 | DG111: 6813.65 | DH111: 7195.45 | DI111: 5128.85 | DJ111: 6126.45 | DK111: 5817.7 | DL111: 5854.6 | DM111: 5805.5 | DN111: 6858.65 | DO111: 5349.55 | DP111: 5260.1 | DQ111: 4730.55 | DR111: 4968 | DS111: 5804.05 | DT111: 4820.1 | DU111: 6956.55 | DV111: 5492.75 | DW111: 6538.15 | DX111: 7897.65 | DY111: 10884.55 | DZ111: 6500.85 | EA111: 5075.55 | EB111: 4418.45 | EC111: 5486.8 | ED111: 5905.3 | EE111: 5167.6 | EF111: 6478 | EG111: 5542.9 | EH111: 6546.45 | EI111: 5924.7 | EJ111: 6922.15 | EK111: 7554.8 | EL111: 6920.1 | EM111: 7201.7 | EN111: 7964.45 | EO111: 9205.05 | EP111: 7101.4 | EQ111: 8042.5 | ER111: 8919.15 | ES111: 9841.85 | ET111: 7936.55 | EU111: 8241.5 | EV111: 5970.95 | EW111: 7304.5 | EX111: 7006.6 | EY111: 8260.95 | EZ111: 6415.1 | FA111: 6684.75 | FB111: 8163.7 | FC111: 7771.6 | FD111: 6128.1 | FE111: 5982.6 | FF111: 7031.8 | FG111: 8215.95 | FH111: 8937.55 | FI111: 9142.6 | FJ111: 7613.1 | FK111: 8246.95 | FL111: 7760.85 | FM111: 7861.25 | FN111: 7861.25 | GS111: =DL111 -> 5854.6 | GT111: WET
C112: DRY | BT112: 44 | BU112: 62 | BV112: 57 | BW112: 111.5 | BX112: 94 | BY112: 81.5 | BZ112: 0 | CA112: 0 | CB112: 78 | CC112: 78 | CH112: 58.5 | CI112: 92 | CJ112: 105 | CK112: 117 | CL112: 142.5 | CM112: 142 | CN112: 149 | CO112: 135 | CP112: 101 | CQ112: 119.5 | CR112: 101 | CS112: 88.5 | CT112: 96 | CU112: 106 | CV112: 143 | CW112: 106.5 | CX112: 140 | CY112: 134 | CZ112: 115.5 | DA112: 117 | DB112: 94.5 | DC112: 96 | DD112: 99.5 | DE112: 295.1 | DF112: 273.8 | DG112: 273 | DH112: 222.7 | DI112: 137.8 | DJ112: 182.4 | DK112: 161.2 | DL112: 139.8 | DM112: 66 | DN112: 94.1 | DO112: 69.5 | DP112: 105.8 | DQ112: 127.5 | DR112: 98.4 | DS112: 154.3 | DT112: 90.5 | DU112: 175.1 | DV112: 104.4 | DW112: 159 | DX112: 194.4 | DY112: 158.3 | DZ112: 117.1 | EA112: 66 | EB112: 82.6 | EC112: 89.4 | ED112: 78.8 | EE112: 83.2 | EF112: 147.6 | EG112: 157.2 | EH112: 144.3 | EI112: 207.6 | EJ112: 107.7 | EK112: 209.5 | EL112: 207.5 | EM112: 210.9 | EN112: 163.2 | EO112: 175 | EP112: 224.8 | EQ112: 178 | ER112: 194.6 | ES112: 155.3 | ET112: 124.8 | EU112: 170.2 | EV112: 150.8 | EW112: 134 | EX112: 123 | EY112: 98.8 | EZ112: 129.3 | FA112: 89.4 | FB112: 123.1 | FC112: 121.5 | FD112: 141.1 | FE112: 152.8 | FF112: 130 | FG112: 120.4 | FH112: 177.3 | FI112: 165.9 | FJ112: 160.2 | FK112: 140.7 | FL112: 148.1 | FM112: 132.8 | FN112: 132.8 | GS112: =DL112 -> 139.8 | GT112: DRY
B113: Site total | BT113: =SUM(BT111:BT112) -> 4231.3 | BU113: =SUM(BU111:BU112) -> 6260.5 | BV113: =SUM(BV111:BV112) -> 5347.8 | BW113: =SUM(BW111:BW112) -> 7132.75 | BX113: =SUM(BX111:BX112) -> 13622.2 | BY113: =SUM(BY111:BY112) -> 7750.75 | BZ113: =SUM(BZ111:BZ112) -> 4791.05 | CA113: =SUM(CA111:CA112) -> 4652.8 | ... FM113: =SUM(FM111:FM112) -> 7994.05 | FN113: 7874.3 | FO113: =12149.35+118.9 -> 12268.25 | FP113: =7142.9+139.1 -> 7282 | FQ113: =7916.2+169.4 -> 8085.6 | FR113: =7099.1+125.1 -> 7224.2 | FS113: =8553.15+160.5 -> 8713.65 | FT113: =6998.4+119.9 -> 7118.3 | FU113: =8811.75+140.5 -> 8952.25 | FV113: =7190.05+125.9 -> 7315.95 | FW113: =6942.65+120.9 -> 7063.55 | FX113: =8995.55+135.3 -> 9130.85 | FY113: =12988.35+187.1 -> 13175.45 | FZ113: =9314.45+131.8 -> 9446.25 | GA113: =6629.8+124.5 -> 6754.3 | GB113: =7311.85+125.2 -> 7437.05 | GC113: =8211.1+120.4 -> 8331.5 | GD113: =6540.5+90.8 -> 6631.3 | GE113: =7063.2+122.6 -> 7185.8 | GF113: =6999.05+97.9 -> 7096.95 | GG113: =6208.5+119.2 -> 6327.7 | GH113: =7955.9+105.6 -> 8061.5 | GI113: =8571.6+145.5 -> 8717.1 | GJ113: =6257.25+84 -> 6341.25 | GK113: =7975.85+111.4 -> 8087.25 | GL113: =7098+124.9 -> 7222.9 | GM113: =9370+136 -> 9506 | GN113: =9097.1+112.4 -> 9209.5 | GO113: =115.1+9639.35 -> 9754.45 | GP113: =118.4+6858.5 -> 6976.9 | GQ113: =8066.25+122 -> 8188.25 | GR113: =7526.25+106.1 -> 7632.35 | GS113: =EQ113 -> 8220.5 | GT113: =B111 -> WELLINGTON ARMS | GU113: Weekly margins | GW113: =AVERAGE(ES113:GR113) -> 8010.0183 | GX113: =AVERAGE(FS113:GR113) -> 8091.4731 | GY113: =AVERAGE(GF113:GR113) -> 7932.4692 | GZ113: =AVERAGE(GN113:GR113) -> 8352.29 | HA113: =MAX(D113:GR113) -> 13622.2
B114: vs last week % | BT114: =SUM(BT113-BS113) -> 4231.3 | BU114: =SUM(BU113-BT113) -> 2029.2 | BV114: =SUM(BV113-BU113) -> -912.7 | BW114: =SUM(BW113-BV113) -> 1784.95 | BX114: =SUM(BX113-BW113) -> 6489.45 | BY114: =SUM(BY113-BX113) -> -5871.45 | BZ114: =SUM(BZ113-BY113) -> -2959.7 | CA114: =SUM(CA113-BZ113) -> -138.25 | ... DH114: =SUM(DH113-DG113) -> 331.5 | DI114: =SUM(DI113-DH113)/DH113 -> -0.29003188 | DJ114: =SUM(DJ113-DI113)/DI113 -> 0.1978867 | DK114: =SUM(DK113-DJ113)/DJ113 -> -0.052299547 | DL114: =SUM(DL113-DK113)/DK113 -> 0.0025924501 | DM114: =SUM(DM113-DL113)/DL113 -> -0.020502469 | DN114: =SUM(DN113-DM113)/DM113 -> 0.18415226 | DO114: =SUM(DO113-DN113)/DN113 -> -0.22058898 | DP114: =SUM(DP113-DO113)/DO113 -> -0.0098079922 | ... GK114: =SUM(GK113-GJ113)/GJ113 -> 0.27534004 | GL114: =(GL113-GK113)/GK113 -> -0.10687811 | GM114: =(GM113-GL113)/GL113 -> 0.31609187 | GN114: =(GN113-GM113)/GM113 -> -0.031190827 | GO114: =(GO113-GN113)/GN113 -> 0.059172594 | GP114: =(GP113-GO113)/GO113 -> -0.28474696 | GQ114: =(GQ113-GP113)/GP113 -> 0.17362296 | GR114: =(GR113-GQ113)/GQ113 -> -0.067889964 | GU114: Labour % | GV114: =LABOUR!AG80 -> 0.15722549
B115: Same week last year | BD115: =D113 -> 0 | BE115: =E113 -> 0 | BF115: =F113 -> 0 | BG115: =G113 -> 0 | BH115: =H113 -> 0 | BI115: =I113 -> 0 | BJ115: =J113 -> 0 | BK115: =K113 -> 0 | ... GL115: =EL113 -> 7127.6 | GM115: =EL113 -> 7127.6 | GN115: =EM113 -> 7412.6 | GO115: =EN113 -> 8127.65 | GP115: =EO113 -> 9380.05 | GQ115: =EP113 -> 7326.2 | GR115: =EQ113 -> 8220.5
...

Sheet Dry margin
B1: Net dry | C1: Food spend (PW) | D1: Chickpea Food | E1: GP
A2: PA | B2: 31041.125 | C2: 10372.31 | D2: -3851 | E2: =(B2-(C2+D2))/B2 -> 0.78991386
A3: GA | B3: 13747.625 | C3: 3674.36 | D3: 420 | E3: =(B3-(C3+D3))/B3 -> 0.70217692
A4: BC | B4: 10831.525 | C4: 3515.63 | D4: 190 | E4: =(B4-(C4+D4))/B4 -> 0.65788474
A5: DG | B5: 11533 | C5: 2465.39 | D5: 480 | E5: =(B5-(C5+D5))/B5 -> 0.74461198
A6: QH | B6: 8672.9417 | C6: 3207.11 | D6: 600 | E6: =(B6-(C6+D6))/B6 -> 0.5610359
A7: SP | B7: 9880.0417 | C7: 2804.09 | D7: 399 | E7: =(B7-(C7+D7))/B7 -> 0.67580197
A8: KA | B8: 13028 | C8: 1991.28 | D8: 180 | E8: =(B8-(C8+D8))/B8 -> 0.83333743
A9: MHI | B9: 13626.458 | C9: 3575.8 | D9: 190 | E9: =(B9-(C9+D9))/B9 -> 0.72364059
A10: Nole | B10: 16898.167 | C10: 3385.36 | D10: 1392 | E10: =(B10-(C10+D10))/B10 -> 0.71728531

Sheet Chickpea Food
A1: Sum of total | B1: Column Labels
A2: Row Labels | B2: BC | C2: DG | D2: GA | E2: KA | F2: MH | G2: NOLE | H2: QH | I2: SP | J2: Grand Total
A3: Bread dough | B3: 40 | F3: 40 | I3: 24 | J3: 104
A4: COMPLETED PIE ORDER | C4: 60 | H4: 90 | I4: 90 | J4: 240
A5: Pizza dough 1x(15) LRG white trays (KA/SP/GA/MH) | B5: 150 | C5: 420 | D5: 420 | E5: 150 | F5: 150 | H5: 240 | I5: 285 | J5: 1815
A6: Pizza dough 1x(8) (Nole/DG Only) | G6: 1392 | J6: 1392
A7: Pork And Apple Pies 1x(6) | E7: 30 | H7: 270 | J7: 300
A8: Grand Total | B8: 190 | C8: 480 | D8: 420 | E8: 180 | F8: 190 | G8: 1392 | H8: 600 | I8: 399 | J8: 3851

Sheet orders_2025-07-28_11-52
A1: order_number | B1: tax_invoice_number | C1: cancellation_invoice_number | D1: email | E1: sku | F1: name | G1: weight | H1: price | I1: total | J1: quantity | K1: options | L1: tax_details | M1: customer_tax_exempt | N1: customer_tax_id | O1: reversed_tax_applied | P1: timestamp | Q1: shipto_person_name | R1: shipto_person_company_name | S1: shipto_person_street_1 | T1: shipto_person_street_2 | U1: shipto_person_city | V1: shipto_person_country_code | W1: shipto_person_postal_code | X1: shipto_person_state_code | Y1: shipto_person_country_name | Z1: shipto_person_state_name | AA1: shipto_person_phone | AB1: bill_person_name | AC1: bill_person_company_name | AD1: bill_person_street_1 | AE1: bill_person_street_2 | AF1: bill_person_city | AG1: bill_person_country_code | AH1: bill_person_postal_code | AI1: bill_person_state_code | AJ1: bill_person_country_name | AK1: bill_person_state_name | AL1: bill_person_phone | AM1: customer_group | AN1: payment_method | AO1: shipping_method | AP1: payment_status | AQ1: fulfillment_status | AR1: payment_status_code | AS1: fulfillment_status_code | AT1: order_subtotal | AU1: order_tax | AV1: order_shipping | AW1: order_handling_fee | AX1: order_total | AY1: order_tax_1_name | AZ1: order_tax_1_value | BA1: order_tracking_number | BB1: coupon_code | BC1: coupon_discount | BD1: volume_discount | BE1: detail_discount | BF1: discount | BG1: order_weight | BH1: order_comments | BI1: affiliate_id | BJ1: utm_source | BK1: utm_medium | BL1: utm_campaign | BM1: customer_ipaddress | BN1: note_for_staff | BO1: accept_marketing | BP1: referer_id | BQ1: gift_card_redemption | BR1: masked_gift_card_code | BS1: payment_transaction_id | BT1: tips | BU1: surcharges | BV1: What day would you like this for? | BW1: Which site is this for? | BX1: Which site is it for? | BY1: Select Delivery Day (IF same day pick up please put today) | BZ1: null | CA1: language
A2: CHICKPEA0XXCY123 | B2: 3671 | D2: hello@nolepizza.co.uk | E2: 0 | F2: Pizza dough 1x(8) (Nole/DG Only) | G2: 0 | H2: 8 | I2: 160 | J2: 20 | M2: FALSE | O2: FALSE | P2: 45859.85 | AN2: . | AP2: Awaiting Payment | AQ2: Delivered | AR2: QUEUED | AS2: DELIVERED | AT2: 160 | AU2: 0 | AV2: 0 | AW2: 0 | AX2: 160 | BC2: 0 | BD2: 0 | BE2: volume_discount:0.00;customer_group_discount:0.00;customer_group_volume_discount:0.00;shipping_discount:0.00 | BF2: 0 | BG2: 0 | BM2: 217.168.251.25 | BQ2: 0 | BX2: NOLE | BY2: TUESDAY | BZ2: 27304e57-4352-4fb0-b94e-d6db7e900904 | CA2: en
A3: CHICKPEAUM7GE123 | B3: 3672 | D3: hello@dogandgunnetheravon.co.uk | E3: 54 | F3: Pizza dough 1x(15) LRG white trays (KA/SP/GA/MH) | G3: 0 | H3: 15 | I3: 75 | J3: 5 | M3: FALSE | O3: FALSE | P3: 45859.887 | AN3: . | AP3: Awaiting Payment | AQ3: Delivered | AR3: QUEUED | AS3: DELIVERED | AT3: 135 | AU3: 0 | AV3: 0 | AW3: 0 | AX3: 135 | BC3: 0 | BD3: 0 | BE3: volume_discount:0.00;customer_group_discount:0.00;customer_group_volume_discount:0.00;shipping_discount:0.00 | BF3: 0 | BG3: 0 | BM3: 31.113.195.59 | BQ3: 0 | BX3: DG | BY3: WEDNESDAY | BZ3: 29c2eb6d-5606-46c7-a805-9dce2a4da54e | CA3: en
A4: CHICKPEAUM7GE123 | B4: 3672 | D4: hello@dogandgunnetheravon.co.uk | E4: 18 | F4: COMPLETED PIE ORDER | G4: 0 | H4: 30 | I4: 60 | J4: 2 | M4: FALSE | O4: FALSE | P4: 45859.887 | AN4: . | AP4: Awaiting Payment | AQ4: Delivered | AR4: QUEUED | AS4: DELIVERED | AT4: 135 | AU4: 0 | AV4: 0 | AW4: 0 | AX4: 135 | BC4: 0 | BD4: 0 | BE4: volume_discount:0.00;customer_group_discount:0.00;customer_group_volume_discount:0.00;shipping_discount:0.00 | BF4: 0 | BG4: 0 | BM4: 31.113.195.59 | BQ4: 0 | BX4: DG | BY4: WEDNESDAY | BZ4: 29c2eb6d-5606-46c7-a805-9dce2a4da54e | CA4: en
A5: CHICKPEA1CP1D123 | B5: 3674 | D5: brad@chickpea.group | E5: 8 | F5: Nole Paper | G5: 0 | H5: 68.12 | I5: 68.12 | J5: 1 | M5: FALSE | O5: FALSE | P5: 45859.912 | AN5: . | AP5: Awaiting Payment | AQ5: Delivered | AR5: QUEUED | AS5: DELIVERED | AT5: 68.12 | AU5: 0 | AV5: 0 | AW5: 0 | AX5: 68.12 | BC5: 0 | BD5: 0 | BE5: volume_discount:0.00;customer_group_discount:0.00;customer_group_volume_discount:0.00;shipping_discount:0.00 | BF5: 0 | BG5: 0 | BH5: Tue/wed either works | BM5: 148.252.146.126 | BQ5: 0 | BX5: PA | BY5: TUESDAY | BZ5: a9085ce1-922c-4a42-be08-08f265d45f82 | CA5: en
A6: CHICKPEAEXAPE123 | B6: 3673 | D6: connor@chickpea.group | E6: 3 | F6: Bread dough | G6: 0 | H6: 4 | I6: 16 | J6: 4 | M6: FALSE | O6: FALSE | P6: 45859.905 | AN6: . | AP6: Awaiting Payment | AQ6: Delivered | AR6: QUEUED | AS6: DELIVERED | AT6: 16 | AU6: 0 | AV6: 0 | AW6: 0 | AX6: 16 | BC6: 0 | BD6: 0 | BE6: volume_discount:0.00;customer_group_discount:0.00;customer_group_volume_discount:0.00;shipping_discount:0.00 | BF6: 0 | BG6: 0 | BM6: 185.216.146.118 | BQ6: 0 | BX6: BC | BY6: TUESDAY | CA6: en
A7: CHICKPEAELGST123 | B7: 3675 | D7: hello@silverplough-pitton.co.uk | E7: 3004 | F7: Refuse sacks x200 | G7: 0 | H7: 10.7 | I7: 21.4 | J7: 2 | M7: FALSE | O7: FALSE | P7: 45860.486 | AN7: . | AP7: Awaiting Payment | AQ7: Delivered | AR7: QUEUED | AS7: DELIVERED | AT7: 21.4 | AU7: 0 | AV7: 0 | AW7: 0 | AX7: 21.4 | BC7: 0 | BD7: 0 | BE7: volume_discount:0.00;customer_group_discount:0.00;customer_group_volume_discount:0.00;shipping_discount:0.00 | BF7: 0 | BG7: 0 | BM7: 85.193.155.53 | BQ7: 0 | BX7: SP | BY7: WEDNESDAY | BZ7: 72be4c9c-4358-4384-955a-7a65ce2eaab9 | CA7: en
A8: CHICKPEALCU9U123 | B8: 3677 | D8: hello@silverplough-pitton.co.uk | E8: 18 | F8: COMPLETED PIE ORDER | G8: 0 | H8: 30 | I8: 90 | J8: 3 | M8: FALSE | O8: FALSE | P8: 45860.851 | AN8: . | AP8: Awaiting Payment | AQ8: Delivered | AR8: QUEUED | AS8: DELIVERED | AT8: 128 | AU8: 0 | AV8: 0 | AW8: 0 | AX8: 128 | BC8: 0 | BD8: 0 | BE8: volume_discount:0.00;customer_group_discount:0.00;customer_group_volume_discount:0.00;shipping_discount:0.00 | BF8: 0 | BG8: 0 | BM8: 85.193.155.53 | BQ8: 0 | BX8: SP | BY8: WEDNESDAY | BZ8: f2d4cb4d-e334-445c-95f8-b8859f20afe3 | CA8: en
A9: CHICKPEALCU9U123 | B9: 3677 | D9: hello@silverplough-pitton.co.uk | E9: 3 | F9: Bread dough | G9: 0 | H9: 4 | I9: 8 | J9: 2 | M9: FALSE | O9: FALSE | P9: 45860.851 | AN9: . | AP9: Awaiting Payment | AQ9: Delivered | AR9: QUEUED | AS9: DELIVERED | AT9: 128 | AU9: 0 | AV9: 0 | AW9: 0 | AX9: 128 | BC9: 0 | BD9: 0 | BE9: volume_discount:0.00;customer_group_discount:0.00;customer_group_volume_discount:0.00;shipping_discount:0.00 | BF9: 0 | BG9: 0 | BM9: 85.193.155.53 | BQ9: 0 | BX9: SP | BY9: WEDNESDAY | BZ9: f2d4cb4d-e334-445c-95f8-b8859f20afe3 | CA9: en
A10: CHICKPEALCU9U123 | B10: 3677 | D10: hello@silverplough-pitton.co.uk | E10: 54 | F10: Pizza dough 1x(15) LRG white trays (KA/SP/GA/MH) | G10: 0 | H10: 15 | I10: 30 | J10: 2 | M10: FALSE | O10: FALSE | P10: 45860.851 | AN10: . | AP10: Awaiting Payment | AQ10: Delivered | AR10: QUEUED | AS10: DELIVERED | AT10: 128 | AU10: 0 | AV10: 0 | AW10: 0 | AX10: 128 | BC10: 0 | BD10: 0 | BE10: volume_discount:0.00;customer_group_discount:0.00;customer_group_volume_discount:0.00;shipping_discount:0.00 | BF10: 0 | BG10: 0 | BM10: 85.193.155.53 | BQ10: 0 | BX10: SP | BY10: WEDNESDAY | BZ10: f2d4cb4d-e334-445c-95f8-b8859f20afe3 | CA10: en
A11: CHICKPEAO7I0X123 | B11: 3679 | D11: rhysegriffith@gmail.com | E11: 54 | F11: Pizza dough 1x(15) LRG white trays (KA/SP/GA/MH) | G11: 0 | H11: 15 | I11: 30 | J11: 2 | M11: FALSE | O11: FALSE | P11: 45860.867 | AN11: . | AP11: Awaiting Payment | AQ11: Delivered | AR11: QUEUED | AS11: DELIVERED | AT11: 30 | AU11: 0 | AV11: 0 | AW11: 0 | AX11: 30 | BC11: 0 | BD11: 0 | BE11: volume_discount:0.00;customer_group_discount:0.00;customer_group_volume_discount:0.00;shipping_discount:0.00 | BF11: 0 | BG11: 0 | BM11: 85.193.148.232 | BQ11: 0 | BX11: QH | BY11: WEDNESDAY | CA11: en
A12: CHICKPEA8IGG1123 | B12: 3676 | D12: rhysegriffith@gmail.com | E12: 54 | F12: Pizza dough 1x(15) LRG white trays (KA/SP/GA/MH) | G12: 0 | H12: 15 | I12: 30 | J12: 2 | M12: FALSE | O12: FALSE | P12: 45860.85 | AN12: . | AP12: Canceled | AQ12: Delivery Canceled | AR12: CANCELLED | AS12: WILL_NOT_DELIVER | AT12: 300 | AU12: 0 | AV12: 0 | AW12: 0 | AX12: 300 | BC12: 0 | BD12: 0 | BE12: volume_discount:0.00;customer_group_discount:0.00;customer_group_volume_discount:0.00;shipping_discount:0.00 | BF12: 0 | BG12: 0 | BM12: 85.193.148.232 | BQ12: 0 | BX12: QH | BY12: WEDNESDAY | CA12: en
A13: CHICKPEA8IGG1123 | B13: 3676 | D13: rhysegriffith@gmail.com | E13: 66 | F13: Pork And Apple Pies 1x(6) | G13: 0 | H13: 30 | I13: 270 | J13: 9 | M13: FALSE | O13: FALSE | P13: 45860.85 | AN13: . | AP13: Canceled | AQ13: Delivery Canceled | AR13: CANCELLED | AS13: WILL_NOT_DELIVER | AT13: 300 | AU13: 0 | AV13: 0 | AW13: 0 | AX13: 300 | BC13: 0 | BD13: 0 | BE13: volume_discount:0.00;customer_group_discount:0.00;customer_group_volume_discount:0.00;shipping_discount:0.00 | BF13: 0 | BG13: 0 | BM13: 85.193.148.232 | BQ13: 0 | BX13: QH | BY13: WEDNESDAY | CA13: en
A14: CHICKPEAF3MQU123 | B14: 3678 | D14: hello@nolepizza.co.uk | E14: 0 | F14: Pizza dough 1x(8) (Nole/DG Only) | G14: 0 | H14: 8 | I14: 184 | J14: 23 | M14: FALSE | O14: FALSE | P14: 45860.857 | AN14: . | AP14: Awaiting Payment | AQ14: Delivered | AR14: QUEUED | AS14: DELIVERED | AT14: 184 | AU14: 0 | AV14: 0 | AW14: 0 | AX14: 184 | BC14: 0 | BD14: 0 | BE14: volume_discount:0.00;customer_group_discount:0.00;customer_group_volume_discount:0.00;shipping_discount:0.00 | BF14: 0 | BG14: 0 | BM14: 217.168.251.25 | BQ14: 0 | BX14: NOLE | BY14: WEDNESDAY | BZ14: 27304e57-4352-4fb0-b94e-d6db7e900904 | CA14: en
A15: CHICKPEARJZOL123 | B15: 3680 | D15: rory.short@hotmail.co.uk | E15: 66 | F15: Pork And Apple Pies 1x(6) | G15: 0 | H15: 30 | I15: 30 | J15: 1 | M15: FALSE | O15: FALSE | P15: 45860.894 | AN15: . | AP15: Awaiting Payment | AQ15: Delivered | AR15: QUEUED | AS15: DELIVERED | AT15: 30 | AU15: 0 | AV15: 0 | AW15: 0 | AX15: 30 | BC15: 0 | BD15: 0 | BE15: volume_discount:0.00;customer_group_discount:0.00;customer_group_volume_discount:0.00;shipping_discount:0.00 | BF15: 0 | BG15: 0 | BM15: 85.193.145.142 | BQ15: 0 | BX15: KA | BY15: WEDNESDAY | BZ15: a08f5e5d-5e9c-4ea9-bb69-b3a74a5958bc | CA15: en
A16: CHICKPEARXCEX123 | B16: 3681 | D16: connorrance95@gmail.com | E16: 18 | F16: COMPLETED PIE ORDER | G16: 0 | H16: 30 | I16: 90 | J16: 3 | M16: FALSE | O16: FALSE | P16: 45861.74 | AN16: . | AP16: Awaiting Payment | AQ16: Delivered | AR16: QUEUED | AS16: DELIVERED | AT16: 90 | AU16: 0 | AV16: 0 | AW16: 0 | AX16: 90 | BC16: 0 | BD16: 0 | BE16: volume_discount:0.00;customer_group_discount:0.00;customer_group_volume_discount:0.00;shipping_discount:0.00 | BF16: 0 | BG16: 0 | BH16: All ready delivered this morning | BM16: 85.193.148.232 | BQ16: 0 | BX16: QH | BY16: WEDNESDAY | BZ16: a3384d82-4e8b-484f-aa1e-67c2ecfd4758 | CA16: en
A17: CHICKPEA8DEK4123 | B17: 3682 | D17: declan@chickpea.group | E17: 54 | F17: Pizza dough 1x(15) LRG white trays (KA/SP/GA/MH) | G17: 0 | H17: 15 | I17: 75 | J17: 5 | M17: FALSE | O17: FALSE | P17: 45861.765 | AN17: . | AP17: Awaiting Payment | AQ17: Delivered | AR17: QUEUED | AS17: DELIVERED | AT17: 75 | AU17: 0 | AV17: 0 | AW17: 0 | AX17: 75 | BC17: 0 | BD17: 0 | BE17: volume_discount:0.00;customer_group_discount:0.00;customer_group_volume_discount:0.00;shipping_discount:0.00 | BF17: 0 | BG17: 0 | BM17: 85.193.155.53 | BQ17: 0 | BX17: SP | BY17: THURSDAY | BZ17: 3464c083-3c57-44d0-a50f-98ef1b6b0c6e | CA17: en
A18: CHICKPEAVLIO8123 | B18: 3683 | D18: hello@dogandgunnetheravon.co.uk | E18: 54 | F18: Pizza dough 1x(15) LRG white trays (KA/SP/GA/MH) | G18: 0 | H18: 15 | I18: 120 | J18: 8 | M18: FALSE | O18: FALSE | P18: 45861.887 | AN18: . | AP18: Awaiting Payment | AQ18: Delivered | AR18: QUEUED | AS18: DELIVERED | AT18: 188.12 | AU18: 0 | AV18: 0 | AW18: 0 | AX18: 188.12 | BC18: 0 | BD18: 0 | BE18: volume_discount:0.00;customer_group_discount:0.00;customer_group_volume_discount:0.00;shipping_discount:0.00 | BF18: 0 | BG18: 0 | BM18: 31.113.195.59 | BQ18: 0 | BX18: DG | BY18: THURSDAY | BZ18: 29c2eb6d-5606-46c7-a805-9dce2a4da54e | CA18: en
A19: CHICKPEAVLIO8123 | B19: 3683 | D19: hello@dogandgunnetheravon.co.uk | E19: 8 | F19: Nole Paper | G19: 0 | H19: 68.12 | I19: 68.12 | J19: 1 | M19: FALSE | O19: FALSE | P19: 45861.887 | AN19: . | AP19: Awaiting Payment | AQ19: Delivered | AR19: QUEUED | AS19: DELIVERED | AT19: 188.12 | AU19: 0 | AV19: 0 | AW19: 0 | AX19: 188.12 | BC19: 0 | BD19: 0 | BE19: volume_discount:0.00;customer_group_discount:0.00;customer_group_volume_discount:0.00;shipping_discount:0.00 | BF19: 0 | BG19: 0 | BM19: 31.113.195.59 | BQ19: 0 | BX19: DG | BY19: THURSDAY | BZ19: 29c2eb6d-5606-46c7-a805-9dce2a4da54e | CA19: en
A20: CHICKPEAIBXEP123 | B20: 3684 | D20: salisbury@nolepizza.co.uk | E20: 0 | F20: Pizza dough 1x(8) (Nole/DG Only) | G20: 0 | H20: 8 | I20: 112 | J20: 14 | M20: FALSE | O20: FALSE | P20: 45861.888 | AN20: . | AP20: Awaiting Payment | AQ20: Delivered | AR20: QUEUED | AS20: DELIVERED | AT20: 112 | AU20: 0 | AV20: 0 | AW20: 0 | AX20: 112 | BC20: 0 | BD20: 0 | BE20: volume_discount:0.00;customer_group_discount:0.00;customer_group_volume_discount:0.00;shipping_discount:0.00 | BF20: 0 | BG20: 0 | BM20: 109.145.145.143 | BQ20: 0 | BX20: NOLE | BY20: THURSDAY | BZ20: 6e079ec2-c4ff-460b-a88f-2e17c5c5d928 | CA20: en
A21: CHICKPEAEKBIM123 | B21: 3685 | D21: rory.short@hotmail.co.uk | E21: 54 | F21: Pizza dough 1x(15) LRG white trays (KA/SP/GA/MH) | G21: 0 | H21: 15 | I21: 45 | J21: 3 | M21: FALSE | O21: FALSE | P21: 45861.89 | AN21: . | AP21: Awaiting Payment | AQ21: Delivered | AR21: QUEUED | AS21: DELIVERED | AT21: 45 | AU21: 0 | AV21: 0 | AW21: 0 | AX21: 45 | BC21: 0 | BD21: 0 | BE21: volume_discount:0.00;customer_group_discount:0.00;customer_group_volume_discount:0.00;shipping_discount:0.00 | BF21: 0 | BG21: 0 | BM21: 85.193.145.142 | BQ21: 0 | BX21: KA | BY21: THURSDAY | BZ21: a08f5e5d-5e9c-4ea9-bb69-b3a74a5958bc | CA21: en
A22: CHICKPEATHCJ1123 | B22: 3686 | D22: hello@grosvenorarmshindon.co.uk | E22: 54 | F22: Pizza dough 1x(15) LRG white trays (KA/SP/GA/MH) | G22: 0 | H22: 15 | I22: 210 | J22: 14 | M22: FALSE | O22: FALSE | P22: 45862.472 | AN22: . | AP22: Awaiting Payment | AQ22: Delivered | AR22: QUEUED | AS22: DELIVERED | AT22: 210 | AU22: 0 | AV22: 0 | AW22: 0 | AX22: 210 | BC22: 0 | BD22: 0 | BE22: volume_discount:0.00;customer_group_discount:0.00;customer_group_volume_discount:0.00;shipping_discount:0.00 | BF22: 0 | BG22: 0 | BM22: 31.96.53.158 | BQ22: 0 | BX22: GA | BY22: FRIDAY | BZ22: 4ca1ecec-46e4-4be7-bed3-1fe69909d846 | CA22: en
A23: CHICKPEAZ8ACD123 | B23: 3687 | D23: bruno@chickpea.group | E23: 54 | F23: Pizza dough 1x(15) LRG white trays (KA/SP/GA/MH) | G23: 0 | H23: 15 | I23: 75 | J23: 5 | M23: FALSE | O23: FALSE | P23: 45862.619 | AN23: . | AP23: Awaiting Payment | AQ23: Delivered | AR23: QUEUED | AS23: DELIVERED | AT23: 95 | AU23: 0 | AV23: 0 | AW23: 0 | AX23: 95 | BC23: 0 | BD23: 0 | BE23: volume_discount:0.00;customer_group_discount:0.00;customer_group_volume_discount:0.00;shipping_discount:0.00 | BF23: 0 | BG23: 0 | BM23: 85.193.145.221 | BQ23: 0 | BX23: MH | BY23: FRIDAY | BZ23: 63e12738-a92e-4471-bb50-4329a43bc905 | CA23: en
A24: CHICKPEAZ8ACD123 | B24: 3687 | D24: bruno@chickpea.group | E24: 3 | F24: Bread dough | G24: 0 | H24: 4 | I24: 20 | J24: 5 | M24: FALSE | O24: FALSE | P24: 45862.619 | AN24: . | AP24: Awaiting Payment | AQ24: Delivered | AR24: QUEUED | AS24: DELIVERED | AT24: 95 | AU24: 0 | AV24: 0 | AW24: 0 | AX24: 95 | BC24: 0 | BD24: 0 | BE24: volume_discount:0.00;customer_group_discount:0.00;customer_group_volume_discount:0.00;shipping_discount:0.00 | BF24: 0 | BG24: 0 | BM24: 85.193.145.221 | BQ24: 0 | BX24: MH | BY24: FRIDAY | BZ24: 63e12738-a92e-4471-bb50-4329a43bc905 | CA24: en
A25: CHICKPEAXISKY123 | B25: 3690 | D25: kianacmoore@gmail.com | E25: 54 | F25: Pizza dough 1x(15) LRG white trays (KA/SP/GA/MH) | G25: 0 | H25: 15 | I25: 210 | J25: 14 | M25: FALSE | O25: FALSE | P25: 45862.647 | AN25: . | AP25: Canceled | AQ25: Delivery Canceled | AR25: CANCELLED | AS25: WILL_NOT_DELIVER | AT25: 210 | AU25: 0 | AV25: 0 | AW25: 0 | AX25: 210 | BC25: 0 | BD25: 0 | BE25: volume_discount:0.00;customer_group_discount:0.00;customer_group_volume_discount:0.00;shipping_discount:0.00 | BF25: 0 | BG25: 0 | BM25: 86.156.2.199 | BQ25: 0 | BX25: GA | BY25: FRIDAY | BZ25: 3b6b92b5-1166-448e-b38a-05aa876ab700 | CA25: en
A26: CHICKPEANYO21123 | B26: 3688 | D26: connorrance95@gmail.com | E26: 54 | F26: Pizza dough 1x(15) LRG white trays (KA/SP/GA/MH) | G26: 0 | H26: 15 | I26: 90 | J26: 6 | M26: FALSE | O26: FALSE | P26: 45862.622 | AN26: . | AP26: Awaiting Payment | AQ26: Delivered | AR26: QUEUED | AS26: DELIVERED | AT26: 90 | AU26: 0 | AV26: 0 | AW26: 0 | AX26: 90 | BC26: 0 | BD26: 0 | BE26: volume_discount:0.00;customer_group_discount:0.00;customer_group_volume_discount:0.00;shipping_discount:0.00 | BF26: 0 | BG26: 0 | BM26: 85.193.148.232 | BQ26: 0 | BX26: QH | BY26: FRIDAY | BZ26: aa576cf3-0984-45f8-b559-9713f0e4c0f9 | CA26: en
A27: CHICKPEARLWXB123 | B27: 3689 | D27: connor@chickpea.group | E27: 54 | F27: Pizza dough 1x(15) LRG white trays (KA/SP/GA/MH) | G27: 0 | H27: 15 | I27: 150 | J27: 10 | M27: FALSE | O27: FALSE | P27: 45862.647 | AN27: . | AP27: Awaiting Payment | AQ27: Delivered | AR27: QUEUED | AS27: DELIVERED | AT27: 150 | AU27: 0 | AV27: 0 | AW27: 0 | AX27: 150 | BC27: 0 | BD27: 0 | BE27: volume_discount:0.00;customer_group_discount:0.00;customer_group_volume_discount:0.00;shipping_discount:0.00 | BF27: 0 | BG27: 0 | BM27: 91.196.221.195 | BQ27: 0 | BX27: BC | BY27: SATURDAY | CA27: en
A28: CHICKPEAXYGHL123 | B28: 3691 | D28: hello@nolepizza.co.uk | E28: 0 | F28: Pizza dough 1x(8) (Nole/DG Only) | G28: 0 | H28: 8 | I28: 400 | J28: 50 | M28: FALSE | O28: FALSE | P28: 45862.883 | AN28: . | AP28: Awaiting Payment | AQ28: Delivered | AR28: QUEUED | AS28: DELIVERED | AT28: 400 | AU28: 0 | AV28: 0 | AW28: 0 | AX28: 400 | BC28: 0 | BD28: 0 | BE28: volume_discount:0.00;customer_group_discount:0.00;customer_group_volume_discount:0.00;shipping_discount:0.00 | BF28: 0 | BG28: 0 | BM28: 217.168.251.25 | BQ28: 0 | BX28: NOLE | BY28: FRIDAY | BZ28: 27304e57-4352-4fb0-b94e-d6db7e900904 | CA28: en
A29: CHICKPEAB1DHE123 | B29: 3692 | D29: rory.short@hotmail.co.uk | E29: 54 | F29: Pizza dough 1x(15) LRG white trays (KA/SP/GA/MH) | G29: 0 | H29: 15 | I29: 60 | J29: 4 | M29: FALSE | O29: FALSE | P29: 45862.896 | AN29: . | AP29: Awaiting Payment | AQ29: Delivered | AR29: QUEUED | AS29: DELIVERED | AT29: 60 | AU29: 0 | AV29: 0 | AW29: 0 | AX29: 60 | BC29: 0 | BD29: 0 | BE29: volume_discount:0.00;customer_group_discount:0.00;customer_group_volume_discount:0.00;shipping_discount:0.00 | BF29: 0 | BG29: 0 | BM29: 85.193.145.142 | BQ29: 0 | BX29: KA | BY29: FRIDAY | BZ29: a08f5e5d-5e9c-4ea9-bb69-b3a74a5958bc | CA29: en
A30: CHICKPEA6ZUOU123 | B30: 3693 | D30: chrismod24@duck.com | E30: 3 | F30: Bread dough | G30: 0 | H30: 4 | I30: 24 | J30: 6 | M30: FALSE | O30: FALSE | P30: 45862.898 | AN30: . | AP30: Awaiting Payment | AQ30: Delivered | AR30: QUEUED | AS30: DELIVERED | AT30: 24 | AU30: 0 | AV30: 0 | AW30: 0 | AX30: 24 | BC30: 0 | BD30: 0 | BE30: volume_discount:0.00;customer_group_discount:0.00;customer_group_volume_discount:0.00;shipping_discount:0.00 | BF30: 0 | BG30: 0 | BM30: 85.193.157.121 | BQ30: 0 | BX30: BC | BY30: FRIDAY | BZ30: 19e37f15-3368-4079-89a0-4d09d9bfd907 | CA30: en
A31: CHICKPEA5JJIS123 | B31: 3694 | D31: declanzakk@gmail.com | E31: 54 | F31: Pizza dough 1x(15) LRG white trays (KA/SP/GA/MH) | G31: 0 | H31: 15 | I31: 105 | J31: 7 | M31: FALSE | O31: FALSE | P31: 45863.76 | AN31: . | AP31: Awaiting Payment | AQ31: Delivered | AR31: QUEUED | AS31: DELIVERED | AT31: 105 | AU31: 0 | AV31: 0 | AW31: 0 | AX31: 105 | BC31: 0 | BD31: 0 | BE31: volume_discount:0.00;customer_group_discount:0.00;customer_group_volume_discount:0.00;shipping_discount:0.00 | BF31: 0 | BG31: 0 | BM31: 85.193.155.53 | BQ31: 0 | BX31: SP | BY31: SATURDAY | BZ31: 21ef0295-c431-4ccf-af59-ad391d24989f | CA31: en
A32: CHICKPEAKDNYQ123 | B32: 3696 | D32: gareth@chickpea.group | E32: 54 | F32: Pizza dough 1x(15) LRG white trays (KA/SP/GA/MH) | G32: 0 | H32: 15 | I32: 45 | J32: 3 | M32: FALSE | O32: FALSE | P32: 45863.892 | AN32: . | AP32: Awaiting Payment | AQ32: Delivered | AR32: QUEUED | AS32: DELIVERED | AT32: 45 | AU32: 0 | AV32: 0 | AW32: 0 | AX32: 45 | BC32: 0 | BD32: 0 | BE32: volume_discount:0.00;customer_group_discount:0.00;customer_group_volume_discount:0.00;shipping_discount:0.00 | BF32: 0 | BG32: 0 | BM32: 85.193.145.142 | BQ32: 0 | BX32: KA | BY32: SATURDAY | BZ32: 926fe990-a567-4695-9467-1605dfe828fa | CA32: en
A33: CHICKPEAZVGRL123 | B33: 3697 | D33: newdogandgun@gmail.com | E33: 54 | F33: Pizza dough 1x(15) LRG white trays (KA/SP/GA/MH) | G33: 0 | H33: 15 | I33: 90 | J33: 6 | M33: FALSE | O33: FALSE | P33: 45863.9 | AN33: . | AP33: Awaiting Payment | AQ33: Delivered | AR33: QUEUED | AS33: DELIVERED | AT33: 90 | AU33: 0 | AV33: 0 | AW33: 0 | AX33: 90 | BC33: 0 | BD33: 0 | BE33: volume_discount:0.00;customer_group_discount:0.00;customer_group_volume_discount:0.00;shipping_discount:0.00 | BF33: 0 | BG33: 0 | BM33: 31.96.115.65 | BQ33: 0 | BX33: DG | BY33: SATURDAY | BZ33: 7d5292ed-5d96-4478-af02-e913c32829d7 | CA33: en
A34: CHICKPEAH8ENB123 | B34: 3698 | D34: bruno@chickpea.group | E34: 54 | F34: Pizza dough 1x(15) LRG white trays (KA/SP/GA/MH) | G34: 0 | H34: 15 | I34: 75 | J34: 5 | M34: FALSE | O34: FALSE | P34: 45863.902 | AN34: . | AP34: Awaiting Payment | AQ34: Delivered | AR34: QUEUED | AS34: DELIVERED | AT34: 95 | AU34: 0 | AV34: 0 | AW34: 0 | AX34: 95 | BC34: 0 | BD34: 0 | BE34: volume_discount:0.00;customer_group_discount:0.00;customer_group_volume_discount:0.00;shipping_discount:0.00 | BF34: 0 | BG34: 0 | BM34: 85.193.145.221 | BQ34: 0 | BX34: MH | BY34: SATURDAY | BZ34: 9eab4b13-a63b-41dd-a13d-69e6e93242f7 | CA34: en
A35: CHICKPEAH8ENB123 | B35: 3698 | D35: bruno@chickpea.group | E35: 3 | F35: Bread dough | G35: 0 | H35: 4 | I35: 20 | J35: 5 | M35: FALSE | O35: FALSE | P35: 45863.902 | AN35: . | AP35: Awaiting Payment | AQ35: Delivered | AR35: QUEUED | AS35: DELIVERED | AT35: 95 | AU35: 0 | AV35: 0 | AW35: 0 | AX35: 95 | BC35: 0 | BD35: 0 | BE35: volume_discount:0.00;customer_group_discount:0.00;customer_group_volume_discount:0.00;shipping_discount:0.00 | BF35: 0 | BG35: 0 | BM35: 85.193.145.221 | BQ35: 0 | BX35: MH | BY35: SATURDAY | BZ35: 9eab4b13-a63b-41dd-a13d-69e6e93242f7 | CA35: en
A36: CHICKPEAZ2DVZ123 | B36: 3695 | D36: hello@nolepizza.co.uk | E36: 0 | F36: Pizza dough 1x(8) (Nole/DG Only) | G36: 0 | H36: 8 | I36: 160 | J36: 20 | M36: FALSE | O36: FALSE | P36: 45863.891 | AN36: . | AP36: Awaiting Payment | AQ36: Delivered | AR36: QUEUED | AS36: DELIVERED | AT36: 160 | AU36: 0 | AV36: 0 | AW36: 0 | AX36: 160 | BC36: 0 | BD36: 0 | BE36: volume_discount:0.00;customer_group_discount:0.00;customer_group_volume_discount:0.00;shipping_discount:0.00 | BF36: 0 | BG36: 0 | BM36: 217.168.251.25 | BQ36: 0 | BX36: NOLE | BY36: SATURDAY | BZ36: 27304e57-4352-4fb0-b94e-d6db7e900904 | CA36: en
A37: CHICKPEADGDKT123 | B37: 3699 | D37: connor@chickpea.group | E37: 8 | F37: Nole Paper | G37: 0 | H37: 68.12 | I37: 68.12 | J37: 1 | M37: FALSE | O37: FALSE | P37: 45863.929 | AN37: . | AP37: Awaiting Payment | AQ37: Delivered | AR37: QUEUED | AS37: DELIVERED | AT37: 87.01 | AU37: 0 | AV37: 0 | AW37: 0 | AX37: 87.01 | BC37: 0 | BD37: 0 | BE37: volume_discount:0.00;customer_group_discount:0.00;customer_group_volume_discount:0.00;shipping_discount:0.00 | BF37: 0 | BG37: 0 | BM37: 91.196.221.191 | BQ37: 0 | BX37: BC | BY37: SATURDAY | CA37: en
